Workbook

Sheet 2024
A1: School Type | B1: School No | C1: School Name | D1: ACAD | E1: Dropped/Retained | F1: Academic Year | G1: SSF Date | H1: Offering | I1: School Revenue Type | J1: SSF Number | K1: Status | L1: Total Order Value (Exclusive GST) | M1: Total Order Value (Inclusive GST) | N1: ASSET Revenue | O1: ASSETStudents | P1: ASSET rate | Q1: CARES Revenue | R1: CARESStudents | S1: CARES rate | T1: Mindspark Revenue | U1: MindsparkStudents | V1: Mindspark rate | W1: Teacher Training Revenue | X1: Payment Mode | Y1: No Of Installments | Z1: Full Payment Date | AA1: First Installment Date | AB1: First Installment Amount | AC1: Second Installment Date | AD1: Second Installment Amount | AE1: Third Installment Date | AF1: Third Installment Amount | AG1: Fourth Installment Date | AH1: Fourth Installment Amount | AI1: TDS Amount | AJ1: First payment Date | AK1: Latest payment Date | AL1: To be invoiced till date | AM1: Amount Received | AN1: Due till date as per payment schedule | AO1: Total Discount % | AP1: Standard Discount % | AQ1: Pre Payment Discount % | AR1: Volume Discount % | AS1: Bundle Discount % | AT1: Loyalty Discount % | AU1: ASSETRound | AV1: Ei ASSET Mode | AW1: CAREStestpack | AX1: Ei CARES Version | AY1: Ei CARES Mode Of Printing | AZ1: Ei CARES Mode | BA1: Ei Mindspark Mode | BB1: Board | BC1: City | BD1: State | BE1: Division | BF1: Zone | BG1: Vertical | BH1: Program Start Date | BI1: Program End Date | BJ1: Order Type | BK1: ID | BL1: Zoho CRM Account ID | BM1: Deal ID | BN1: Created Date | BO1: Added User | BP1: Modified User | BQ1: SSF Creator Email | BR1: SSF Creator | BS1: CRM Account Owner | BT1: CRM Acad Consultant | BU1: Logistic Approved Date | BV1: SSF Signing Perosn Name | BW1: SSF Signing Perosn Designation | BX1: SSF Signing Perosn Mail ID | BY1: SSF Signing Perosn Phone No | BZ1: School CRM Email | CA1: Principal Name | CB1: Principal Email | CC1: Principal Phone No | CD1: Coordinator Name | CE1: Coordinator Email | CF1: Coordinator Phone No | CG1: School Fees | CH1: Billing Address Line 1 | CI1: Billing Address Line 2 | CJ1: Billing Postal Code | CK1: Shipping Address Line 1 | CL1: Shipping City | CM1: Shipping State | CN1: Shipping Postal Code | CO1: TAN NO | CP1: CRM Billing Street | CQ1: CRM Shipping Street
A2: 1-year School | B2: 1002463 | C2: Cambridge School, New Friends Colony | D2: =VLOOKUP(B2,'2025'!B:C,2,0) -> Vaishali | F2: 2024 | G2: 2024-04-30 00:00:00 | H2: Ei ASSET | I2: Regular | J2: IN-2022001979 | K2: Approved By Logistic Team | L2: 267000 | M2: 267000 | N2: 267000 | O2: 356 | P2: 750 | Q2: 0 | R2: 0 | T2: 0 | U2: 0 | W2: 0 | X2: Installments | Y2: 2 | AA2: 2024-05-07 00:00:00 | AB2: 80100 | AC2: 2024-11-07 00:00:00 | AD2: 186900 | AE2: 2000-01-01 00:00:00 | AF2: 0 | AG2: 2000-01-01 00:00:00 | AH2: 0 | AI2: 5340 | AJ2: 2024-06-28 00:00:00 | AK2: 2025-01-21 00:00:00 | AL2: 267000 | AM2: 261659 | AN2: 1 | AO2: 0.5 | AP2: 0.5 | AU2: Winter Round | AV2: OMR | AW2: 0 | AX2: MCQ | BB2: CBSE | BC2: Delhi | BD2: Delhi | BE2: North | BF2: Delhi/Haryana | BG2: National Sales | BH2: 2024-05-01 00:00:00 | BI2: 2025-03-31 00:00:00 | BJ2: Regular School: Active school with student count and rate per student defined | BK2: 22028000022319092 | BL2: 51788000002746818 | BM2: zcrm_51788000269056279 | BN2: 2024-04-30 00:00:00 | BO2: puneet.khurana_ei | BP2: hakim.kanchwala_eiindia1 | BQ2: puneet.khurana@ei.study | BR2: Puneet khurana | BS2: Vaishali Yadav | BU2: 2024-05-13 09:06:54 | BV2: Mrs. Sunandita Ganguly | BW2: Principal | BX2: sunandita.nfc@cambridgeschool.edu.in | BY2: +919711953984 | BZ2: mailus.nfc@cambridgeschool.edu.in | CA2: Mrs. Sunandita Ganguly | CB2: sunandita.nfc@cambridgeschool.edu.in | CC2: +919711953984 | CD2: Ms Latika Mehra | CE2: latikam.nfc@cambridgeschool.edu.in | CF2: +919810606517 | CG2: 88500 | CH2: A - Block, A 96 New Friends Colony, ,Delhi,Delhi - 110065 | CJ2: 110065 | CK2: A - Block, A 96 New Friends Colony, ,Delhi,Delhi - 110065 | CL2: Delhi | CM2: Delhi | CN2: 110065 | CO2: PNEK06448B | CP2: A - Block, A 96 New Friends Colony, ,Delhi,Delhi - 110065 | CQ2: A - Block, A 96 New Friends Colony, ,Delhi,Delhi - 110065
A3: Retention School | B3: 1016619 | C3: St. Paul'S School | D3: =VLOOKUP(B3,'2025'!B:C,2,0) -> Lopamudra Das | F3: 2024 | G3: 2024-06-25 00:00:00 | H3: Ei CARES | I3: Regular | J3: IN-2022002275 | K3: Approved By Logistic Team | L3: 1014560 | M3: 1014560 | N3: 0 | O3: 0 | Q3: 1014560 | R3: 1166 | S3: 870 | T3: 0 | U3: 0 | W3: 0 | X3: Installments | Y3: 4 | AA3: 2024-06-29 00:00:00 | AB3: 253640 | AC3: 2024-08-31 00:00:00 | AD3: 253640 | AE3: 2024-10-31 00:00:00 | AF3: 253640 | AG3: 2024-12-31 00:00:00 | AH3: 253640 | AI3: 101631 | AJ3: 2024-07-22 00:00:00 | AK3: 2025-01-20 00:00:00 | AL3: 1014560 | AM3: 914669 | AN3: -1740 | AO3: 0.5166 | AP3: 0.46659999999999996 | AT3: 0.05 | AU3: 0 | AW3: 2 | AX3: MCQ | AY3: Printing By EI | AZ3: OMR | BB3: CISCE | BC3: Rourkela | BD3: Odisha | BE3: East | BF3: Odisha | BG3: National Sales | BH3: 2024-06-24 00:00:00 | BI3: 2025-03-31 00:00:00 | BJ3: Regular School: Active school with student count and rate per student defined | BK3: 22028000023176128 | BL3: 51788000002747044 | BM3: zcrm_51788000270481001 | BN3: 2024-06-25 00:00:00 | BO3: lopamudra.das_eiindia1 | BP3: mitul.patel_ei1 | BQ3: lopamudra.das@ei.study | BR3: Lopamudra das | BS3: Lopamudra Das | BU3: 2024-07-01 10:19:15 | BV3: Fr. Joseph Sarpira Sadam | BW3: Principal | BX3: stpaulrkl@gmail.com | BY3: +919437290604 | BZ3: stpaulrkl@gmail.com | CG3: 0 | CH3: Hamirpur, Rourkela - 769003, Odisha, INDIA. | CJ3: 769003 | CK3: Hamirpur, Rourkela - 769003, Odisha, INDIA. | CL3: Rourkela | CM3: Odisha | CN3: 769003 | CO3: BBNT00367D | CP3: Hamirpur, Rourkela - 769003, Odisha, INDIA. | CQ3: Hamirpur, Rourkela - 769003, Odisha, INDIA.
A4: Retention School | B4: 1019428 | C4: KLE KG & English Medium State School, Nipani | F4: 2024 | G4: 2024-06-16 00:00:00 | H4: Ei ASSET, Ei Mindspark | I4: Regular | J4: IN-2022002210, IN-2022002237 | K4: Approved By Logistic Team | L4: 674546 | M4: 750348 | N4: 253424 | O4: 815 | P4: 311 | Q4: 0 | R4: 0 | T4: 421122 | U4: 828 | V4: 509 | W4: 0 | X4: Installments | Y4: 2 | AA4: 2024-07-15 00:00:00 | AB4: 126712, 248462 | AC4: 2024-11-15 00:00:00, 2024-12-15 00:00:00 | AD4: 126712, 248462 | AE4: 2000-01-01 00:00:00 | AF4: 0 | AG4: 2000-01-01 00:00:00 | AH4: 0 | AI4: 25408.7, 41542 | AJ4: 2024-09-05 00:00:00, 2024-09-18 00:00:00 | AK4: 2025-01-17 00:00:00 | AL4: 253424, 496924 | AM4: 228678.3, 448658 | AN4: -663, 6724 | AO4: 0.7927, 0.8332999999999999 | AP4: 0.7927, 0.8332999999999999 | AU4: 0, Winter Round | AV4: OMR | AW4: 0 | AX4: MCQ | BA4: Offline | BB4: State Board | BC4: Nipani | BD4: Karnataka | BE4: South | BF4: Karnataka/Kerala | BG4: National Sales | BH4: 2024-06-01 00:00:00 | BI4: 2025-04-30 00:00:00, 2025-05-31 00:00:00 | BJ4: Regular School: Active school with student count and rate per student defined | BK4: 22028000023002408, 22028000023033488 | BL4: 51788000002747167 | BM4: zcrm_51788000270604012, zcrm_51788000270690656 | BN4: 2024-06-16 00:00:00 | BO4: vineet.upadhye_ei | BP4: mitul.patel_ei1 | BQ4: vineet.upadhye@ei.study | BR4: Vineet upadhye | BS4: Nisha Murali | BU4: 2024-06-18 10:41:02, 2024-06-18 10:43:54 | BV4: Maruf Shaikh | BX4: maruf.shaikh@ei.study | BY4: +919016039311 | BZ4: kleems@rediffmail.com | CG4: 0 | CH4: Old P.B road Nipani | CJ4: 591237 | CK4: Old P.B road Nipani | CL4: Nipani | CM4: Karnataka | CN4: 591237 | CO4: BLRK04875D | CP4: Old P.B road Nipani | CQ4: Old P.B road Nipani
A5: Retention School | B5: 1021816 | C5: The Doon Girls^ School | D5: =VLOOKUP(B5,'2025'!B:C,2,0) -> Tanya | F5: 2024 | G5: 2024-04-01 00:00:00 | H5: Ei ASSET,Ei CARES, Ei Mindspark | I5: Regular | J5: IN-2022001799, IN-2022001800 | K5: Approved By Logistic Team | L5: 344761 | M5: 371278 | N5: 46902 | O5: 79 | P5: 594 | Q5: 150542 | R5: 79 | S5: 1906 | T5: 147317 | U5: 79 | V5: 1865 | W5: 0 | X5: Installments | Y5: 4 | AA5: 2024-04-15 00:00:00 | AB5: 43459, 49361 | AC5: 2024-07-15 00:00:00 | AD5: 43459, 49361 | AE5: 2024-10-15 00:00:00 | AF5: 43459, 49361 | AG5: 2024-12-31 00:00:00 | AH5: 43459, 49361 | AI5: 0 | AJ5: 2024-09-13 00:00:00 | AK5: 2024-09-13 00:00:00, 2024-12-26 00:00:00 | AL5: 173836, 197444 | AM5: 236917, 87395 | AN5: -63081, 110049 | AO5: 0.6944, 0.7618 | AP5: 0.6944, 0.7618 | AU5: 0, Summer Round | AV5: OMR | AW5: 0, 8 | AX5: MCQ, MCQ + Subjective | AZ5: Online | BA5: Online | BB5: CISCE | BC5: Dehradun | BD5: Uttarakhand | BE5: North | BF5: UP/Uttarakhand | BG5: National Sales | BH5: 2024-04-01 00:00:00 | BI5: 2025-03-31 00:00:00 | BJ5: Regular School: Active school with student count and rate per student defined | BK5: 22028000021869840, 22028000021869888 | BL5: 51788000002747187 | BM5: zcrm_51788000267771001, zcrm_51788000267801001 | BN5: 2024-04-01 00:00:00 | BO5: anshul.nagpal_ei | BP5: sourabh.mehta_eiindia | BQ5: anshul.nagpal@ei.study | BR5: Anshul nagpal | BS5: Tanya Marina Brooks | BU5: 2024-04-04 17:12:47, 2024-04-04 17:12:52 | BV5: Ms. Monisha Dutta | BW5: Principal | BX5: doongirlsschool@gmail.com | BY5: +919927683344 | BZ5: doongirlsschool@gmail.com | CA5: Ms. Monisha Dutta | CB5: doongirlsschool@gmail.com | CC5: +919927683344 | CD5: Mr. Rohit Raj Singh | CE5: rrs@thedoongirlsschool.com | CF5: +919634483993 | CG5: 0 | CH5: 4, Circular Road, Dalanwala, | CJ5: 248001 | CK5: 4, Circular Road, Dalanwala, | CL5: Dehradun | CM5: Uttarakhand | CN5: 248001 | CP5: 4, Circular Road, Dalanwala, | CQ5: 4, Circular Road, Dalanwala,
A6: Retention School | B6: 10251 | C6: Sri Aurobindo International School | F6: 2024 | G6: 2024-04-04 00:00:00, 2024-08-09 00:00:00 | H6: Ei CARES | I6: Regular | J6: IN-2022001852, IN-2022001853, IN-2022002413 | K6: Approved By Logistic Team | L6: 904469 | M6: 904469 | N6: 0 | O6: 0 | Q6: 904469 | R6: 729 | S6: 0, 1202, 2090 | T6: 0 | U6: 0 | W6: 0 | X6: Full Payment | Z6: 2024-03-31 00:00:00, 2024-04-30 00:00:00 | AA6: 2000-01-01 00:00:00 | AB6: 0 | AC6: 2000-01-01 00:00:00 | AD6: 0 | AE6: 2000-01-01 00:00:00 | AF6: 0 | AG6: 2000-01-01 00:00:00 | AH6: 0 | AI6: 0, 4206, 84866 | AJ6: 2024-05-07 00:00:00 | AK6: 2024-05-07 00:00:00 | AL6: 0, 43264, 861205 | AM6: 0, 37856, 763797 | AN6: 0, 1202, 12542 | AO6: 0.5229, 0.5916, 1 | AP6: 0.4729, 0.5416, 1 | AQ6: 0.05 | AU6: 0 | AW6: 2, 6, 8 | AX6: MCQ | AZ6: Online | BB6: CISCE | BC6: Hyderabad | BD6: Telangana | BE6: South | BF6: AP/Telangana | BG6: National Sales | BH6: 2024-06-01 00:00:00 | BI6: 2025-03-31 00:00:00 | BJ6: Regular School: Active school with student count and rate per student defined | BK6: 22028000021919812, 22028000021919844, 22028000024041572 | BL6: 51788000002728476 | BM6: zcrm_51788000267805111, zcrm_51788000267805248, zcrm_51788000272301001 | BN6: 2024-04-04 00:00:00, 2024-08-09 00:00:00 | BO6: chaitanya.kolluri_ei | BP6: hakim.kanchwala_eiindia1 | BQ6: chaitanya.kolluri@ei.study | BR6: Chaitanya kolluri | BS6: Jasper Jessie | BU6: 2024-04-22 14:51:39, 2024-04-22 14:51:44, 2024-08-10 12:50:42 | BV6: Mr. Praveen, Mr. Praveen SAIS | BW6: Accounts | BX6: saishyd@gmail.com | BY6: +919849659075 | CA6: Ms. Vinjamur Jayashree | CB6: vinjamurjayashree@gmail.com | CD6: Ms. Meena Murthy | CE6: gmlochani@gmail.com | CF6: +919866561332 | CG6: 0 | CH6: 2-2-4/1 O U Road, Sri Aurobindo Marg,Vidyanagar, | CJ6: 500044 | CK6: 2-2-4/1 O U Road, Sri Aurobindo Marg,Vidyanagar, | CL6: Hyderabad | CM6: Telangana | CN6: 500044 | CO6: HYDI01894E | CP6: Vidyanagar, | CQ6: Vidyanagar,
A7: 1-year School | B7: 1026343 | C7: Mind Tree School, Ambala City | D7: =VLOOKUP(B7,'2025'!B:C,2,0) -> Bhavishya | F7: 2024 | G7: 2024-06-28 00:00:00 | H7: Ei ASSET | I7: Regular | J7: IN-2022002289 | K7: Approved By Logistic Team | L7: 96600 | M7: 96600 | N7: 96600 | O7: 161 | P7: 600 | Q7: 0 | R7: 0 | T7: 0 | U7: 0 | W7: 0 | X7: Full Payment | Z7: 2024-08-05 00:00:00 | AA7: 2000-01-01 00:00:00 | AB7: 0 | AC7: 2000-01-01 00:00:00 | AD7: 0 | AE7: 2000-01-01 00:00:00 | AF7: 0 | AG7: 2000-01-01 00:00:00 | AH7: 0 | AI7: 5880 | AJ7: 2024-08-27 00:00:00 | AK7: 2024-08-27 00:00:00 | AL7: 96600 | AM7: 52920 | AN7: 37800 | AO7: 0.6 | AP7: 0.6 | AU7: Summer Round | AV7: OMR | AW7: 0 | AX7: MCQ | BB7: CBSE | BC7: Ambala | BD7: Haryana | BE7: North | BF7: Delhi/Haryana | BG7: National Sales | BH7: 2024-05-13 00:00:00 | BI7: 2025-03-31 00:00:00 | BJ7: Regular School: Active school with student count and rate per student defined | BK7: 22028000023208508 | BL7: 51788000002747228 | BM7: zcrm_51788000255130095 | BN7: 2024-06-28 00:00:00 | BO7: gaurav.mehta_eiindia | BP7: sourabh.mehta_eiindia | BQ7: gaurav.mehta@ei.study | BR7: Gaurav mehta | BS7: Bhavishya Bansal | BU7: 2024-07-01 13:00:38 | BV7: Ms. Neelam Ohri | BW7: Principal | BX7: mindtree.ambala@gmail.com | BY7: +918685000121 | BZ7: mindtreeschool@gmail.com | CG7: 48000 | CH7: Mind Tree School, Sector 1 | CJ7: 134011 | CK7: Mind Tree School, Sector 1 | CL7: Ambala | CM7: Haryana | CN7: 134011 | CP7: Mind Tree School, Sector 1 | CQ7: Mind Tree School, Sector 1
A8: Retention School | B8: 10423 | C8: Shri Shikshayatan School | D8: =VLOOKUP(B8,'2025'!B:C,2,0) -> Lopa | F8: 2024 | G8: 2024-03-08 00:00:00 | H8: Ei ASSET | I8: Regular | J8: IN-2022001599 | K8: Approved By Logistic Team | L8: 649545 | M8: 649545 | N8: 649545 | O8: 1300 | P8: 500 | Q8: 0 | R8: 0 | T8: 0 | U8: 0 | W8: 0 | X8: Installments | Y8: 2 | AA8: 2024-04-22 00:00:00 | AB8: 194864 | AC8: 2024-07-04 00:00:00 | AD8: 454682 | AE8: 2000-01-01 00:00:00 | AF8: 0 | AG8: 2000-01-01 00:00:00 | AH8: 0 | AI8: 9486 | AJ8: 2024-06-25 00:00:00 | AK8: 2025-02-13 00:00:00 | AL8: 649546 | AM8: 620955 | AN8: 19105 | AO8: 0.6668999999999999 | AP8: 0.6668999999999999 | AU8: Summer Round | AV8: OMR | AW8: 0 | AX8: MCQ | BB8: CBSE | BC8: Kolkata | BD8: West Bengal | BE8: East | BF8: West Bengal | BG8: National Sales | BH8: 2024-04-08 00:00:00 | BI8: 2025-03-31 00:00:00 | BJ8: Regular School: Active school with student count and rate per student defined | BK8: 22028000021440040 | BL8: 51788000002728478 | BM8: zcrm_51788000266368106 | BN8: 2024-03-08 00:00:00 | BO8: ratnabali.mukherjee_eiindia | BP8: mitul.patel_ei1 | BQ8: ratnabali.mukherjee@ei.study | BR8: Ratnabali mukherjee | BS8: Gargi Ghosh | BU8: 2024-04-24 14:37:25 | BV8: Mrs. Sangeeta Tandon | BW8: Principal | BX8: principal@shrishikshayatanschool.com | BY8: +919831872819 | BZ8: principal@shrishikshayatanschool.com | CA8: Mrs. Sangeeta Tandon | CB8: principal@shrishikshayatanschool.com | CC8: +919831872819 | CD8: Rupali | CE8: principal@shrishikshayatanschool.com | CF8: +918100376881 | CG8: 0 | CH8: 11, Lord Sinha Road, Elgin, | CJ8: 700071 | CK8: 11, Lord Sinha Road, Elgin, | CL8: Kolkata | CM8: West Bengal | CN8: 700071 | CO8: CALS05598F | CP8: 11, Lord Sinha Road, Elgin, | CQ8: 11, Lord Sinha Road, Elgin,
A9: Retention School | B9: 104830 | C9: P.S. Senior Secondary School | D9: =VLOOKUP(B9,'2025'!B:C,2,0) -> Vineeth T V | F9: 2024 | G9: 2024-01-24 00:00:00 | H9: Ei CARES | I9: Regular | J9: IN-2022001422 | K9: Approved By Logistic Team | L9: 1609105 | M9: 1609105 | N9: 0 | O9: 0 | Q9: 1609105 | R9: 1192 | S9: 1350 | T9: 0 | U9: 0 | W9: 0 | X9: Installments | Y9: 3 | AA9: 2024-06-01 00:00:00 | AB9: 482732 | AC9: 2024-08-01 00:00:00 | AD9: 563187 | AE9: 2024-12-01 00:00:00 | AF9: 563187 | AG9: 2000-01-01 00:00:00 | AH9: 0 | AI9: 157940 | AJ9: 2024-06-24 00:00:00 | AK9: 2024-12-17 00:00:00 | AL9: 1609106 | AM9: 1421466 | AN9: 29700 | AO9: 0.4808 | AP9: 0.4808 | AU9: 0 | AW9: 4 | AX9: MCQ | AY9: Printing By EI | AZ9: OMR | BB9: CBSE | BC9: Chennai | BD9: Tamil Nadu | BE9: South | BF9: Tamil Nadu | BG9: National Sales | BH9: 2024-06-01 00:00:00 | BI9: 2025-04-30 00:00:00 | BJ9: Regular School: Active school with student count and rate per student defined | BK9: 22028000020766924 | BL9: 51788000002731864 | BM9: zcrm_51788000263929001 | BN9: 2024-01-24 00:00:00 | BO9: nisha.murali_eiindia | BP9: hakim.kanchwala_eiindia1 | BQ9: nisha.murali@ei.study | BR9: Nisha murali | BS9: Vineeth T V | BU9: 2024-02-01 14:54:01 | BV9: Mrs.Revathy Parameswaran | BW9: Principal | BX9: Pssrsec@gmail.com | BY9: +919444907456 | BZ9: pssrsec@gmail.com | CA9: Mrs.Revathy Parameswaran | CB9: Pssrsec@gmail.com | CC9: +919444907456 | CD9: Shivakumar | CE9: prsivaku042@gmail.com | CF9: +919677100124 | CG9: 0 | CH9: 33 Alarmelmangapuram, Mylapore, Chennai Â 600 004 | CJ9: 600004 | CK9: 33 Alarmelmangapuram, Mylapore, Chennai Â 600 004 | CL9: Chennai | CM9: Tamil Nadu | CN9: 600004 | CO9: CHEP02342E | CP9: 33 Alarmelmangapuram, Mylapore, Chennai Â 600 004 | CQ9: 33 Alarmelmangapuram, Mylapore, Chennai Â 600 004
A10: New School | B10: 1061266 | C10: Ingraham Institute English School | E10: Dropped | F10: 2024 | G10: 2024-05-14 00:00:00 | H10: Ei CARES | I10: Regular | J10: IN-2022002053 | K10: Approved By Logistic Team | L10: 583833 | M10: 583833 | N10: 0 | O10: 0 | Q10: 583833 | R10: 556 | S10: 1050 | T10: 0 | U10: 0 | W10: 0 | X10: Installments | Y10: 4 | AA10: 2024-05-18 00:00:00 | AB10: 58383 | AC10: 2024-08-01 00:00:00 | AD10: 233533 | AE10: 2024-10-01 00:00:00 | AF10: 145958 | AG10: 2024-12-02 00:00:00 | AH10: 145958 | AI10: 61348 | AJ10: 2024-06-21 00:00:00 | AK10: 2025-03-12 00:00:00 | AL10: 583832 | AM10: 552148 | AN10: -29664 | AO10: 0.5227 | AP10: 0.5227 | AU10: 0 | AW10: 2 | AX10: MCQ + Subjective | AY10: Printing By EI | AZ10: OMR | BB10: CISCE | BC10: Ghaziabad | BD10: Uttar Pradesh | BE10: North | BF10: NCR | BG10: National Sales | BH10: 2024-05-20 00:00:00 | BI10: 2025-03-31 00:00:00 | BJ10: Regular School: Active school with student count and rate per student defined | BK10: 22028000022495488 | BL10: 51788000002747830 | BM10: zcrm_51788000261218012 | BN10: 2024-05-14 00:00:00 | BO10: puneet.khurana_ei | BP10: sourabh.mehta_eiindia | BQ10: puneet.khurana@ei.study | BR10: Puneet khurana | BS10: Puneet Khurana | BT10: Vaishali Yadav | BU10: 2024-05-16 14:47:22 | BV10: Mrs. Arpana Ruth | BW10: Principal | BX10: arpana2@yahoo.com | BY10: +919971995516 | BZ10: ingrinst@gmail.com | CA10: Mrs. Arpana Ruth | CB10: arpana2@yahoo.com | CC10: +919971995516 | CG10: 0 | CH10: Hapur Road | CJ10: 201001 | CK10: Hapur Road | CL10: Ghaziabad | CM10: Uttar Pradesh | CN10: 201001 | CP10: Hapur Road | CQ10: Hapur Road
A11: 1-year School | B11: 108345 | C11: Manasarowar Pushkarini Vidyashrama | E11: Dropped | F11: 2024 | G11: 2024-03-27 00:00:00 | H11: Ei ASSET | I11: Regular | J11: IN-2022001755 | K11: Approved By Logistic Team | L11: 1282717 | M11: 1282717 | N11: 1282717 | O11: 1166 | P11: 1100 | Q11: 0 | R11: 0 | T11: 0 | U11: 0 | W11: 0 | X11: Installments | Y11: 2 | AA11: 2024-06-14 00:00:00 | AB11: 641359 | AC11: 2024-08-14 00:00:00 | AD11: 641359 | AE11: 2000-01-01 00:00:00 | AF11: 0 | AG11: 2000-01-01 00:00:00 | AH11: 0 | AI11: 68037 | AJ11: 2024-08-01 00:00:00 | AK11: 2024-12-23 00:00:00 | AL11: 1282718 | AM11: 1196976 | AN11: 17705 | AO11: 0.2666 | AP11: 0.2666 | AU11: Summer Round | AV11: OMR | AW11: 0 | AX11: MCQ | BB11: CBSE | BC11: Mysore | BD11: Karnataka | BE11: South | BF11: Karnataka/Kerala | BG11: National Sales | BH11: 2024-04-01 00:00:00 | BI11: 2025-03-31 00:00:00 | BJ11: Regular School: Active school with student count and rate per student defined | BK11: 22028000021773164 | BL11: 51788000002731894 | BM11: zcrm_51788000266114662 | BN11: 2024-03-27 00:00:00 | BO11: aji.thomas_eiindia | BP11: sourabh.mehta_eiindia | BQ11: aji.thomas@ei.study | BR11: Aji thomas | BS11: Mohammadi Zohra | BT11: Mohammadi Zohra | BU11: 2024-05-09 11:10:39 | BV11: Mrs. HARSHIDA HARIKUMAR | BW11: Principal | BX11: harshida@pushkarinimys.com | BY11: +918971180000 | BZ11: mpvmysore@yahoo.com | CA11: Mrs. HARSHIDA HARIKUMAR | CB11: harshida@pushkarinimys.com | CC11: +918971180000 | CD11: Hemalatha | CE11: latha7179@yahoo.in | CF11: +919886079179 | CG11: 4000 | CH11: Vijayanagar 2Nd Stage Mysore Karnataka | CJ11: 570017 | CK11: Vijayanagar 2Nd Stage Mysore Karnataka | CL11: Mysore | CM11: Karnataka | CN11: 570017 | CP11: Vijayanagar 2Nd Stage Mysore Karnataka | CQ11: Vijayanagar 2Nd Stage Mysore Karnataka
A12: Key Account | B12: 110298 | C12: Platinum Jubilee High School | E12: Dropped | F12: 2024 | G12: 2024-10-22 00:00:00 | H12: Ei ASSET | I12: Regular | J12: IN-2022002536 | K12: Approved By Logistic Team | L12: 0 | M12: 0 | N12: 0 | O12: 701 | P12: 0 | Q12: 0 | R12: 0 | T12: 0 | U12: 0 | W12: 0 | X12: Full Payment | Z12: 2024-10-23 00:00:00 | AA12: 2000-01-01 00:00:00 | AB12: 0 | AC12: 2000-01-01 00:00:00 | AD12: 0 | AE12: 2000-01-01 00:00:00 | AF12: 0 | AG12: 2000-01-01 00:00:00 | AH12: 0 | AI12: 0 | AL12: 0 | AM12: 0 | AN12: 0 | AO12: 1 | AP12: 1 | AU12: Winter Round | AV12: OMR | AW12: 0 | AX12: MCQ | BB12: State Board | BC12: Warangal | BD12: Telangana | BE12: South | BF12: AP/Telangana | BG12: National Sales | BH12: 2024-09-01 00:00:00 | BI12: 2025-03-31 00:00:00 | BJ12: Regular School: Active school with student count and rate per student defined | BK12: 22028000025644064 | BL12: 51788000002732015 | BM12: zcrm_51788000274553290 | BN12: 2024-10-22 00:00:00 | BO12: maruf.shaikh1 | BP12: maruf.shaikh1 | BQ12: maruf.shaikh@ei.study | BR12: Maruf shaikh | BS12: Manjeetsingh Ladhad | BU12: 2024-10-22 12:55:58 | BV12: Jagdish Peche | BW12: Principal | BX12: jagdish.peche@akesi.org | BY12: +919652313666 | CA12: Jagdish Peche | CB12: jagdish.peche@akesi.org | CC12: +919652313666 | CD12: Prasanna | CE12: jagdish.peche@akesi.org | CF12: +916303627829 | CG12: 0 | CH12: 16-8-19/1, Fort Road Abbani Kunta Warangal Telangana INDIA | CJ12: 506002 | CK12: 16-8-19/1, Fort Road Abbani Kunta Warangal Telangana INDIA | CL12: Warangal | CM12: Telangana | CN12: 506002 | CP12: 16-8-19/1, Fort Road Abbani Kunta Warangal Telangana INDIA | CQ12: 16-8-19/1, Fort Road Abbani Kunta Warangal Telangana INDIA
A13: Retention School | B13: 1131322 | C13: The Global Edge School | F13: 2024 | G13: 2024-04-05 00:00:00 | H13: Ei ASSET | I13: Regular | J13: IN-2022001858 | K13: Approved By Logistic Team | L13: 380190 | M13: 380190 | N13: 380190 | O13: 667 | P13: 570 | Q13: 0 | R13: 0 | T13: 0 | U13: 0 | W13: 0 | X13: Full Payment | Z13: 2024-07-31 00:00:00 | AA13: 2000-01-01 00:00:00 | AB13: 0 | AC13: 2000-01-01 00:00:00 | AD13: 0 | AE13: 2000-01-01 00:00:00 | AF13: 0 | AG13: 2000-01-01 00:00:00 | AH13: 0 | AI13: 38019 | AJ13: 2024-09-23 00:00:00 | AK13: 2024-09-23 00:00:00 | AL13: 380190 | AM13: 342171 | AN13: 0 | AO13: 0.62 | AP13: 0.62 | AU13: Summer Round | AV13: OMR | AW13: 0 | AX13: MCQ | BB13: CBSE | BC13: Hyderabad | BD13: Telangana | BE13: South | BF13: AP/Telangana | BG13: National Sales | BH13: 2024-06-01 00:00:00 | BI13: 2025-03-31 00:00:00 | BJ13: Regular School: Active school with student count and rate per student defined | BK13: 22028000021930452 | BL13: 51788000002749196 | BM13: zcrm_51788000266680049 | BN13: 2024-04-05 00:00:00 | BO13: chaitanya.kolluri_ei | BP13: hakim.kanchwala_eiindia1 | BQ13: chaitanya.kolluri@ei.study | BR13: Chaitanya kolluri | BS13: Jasper Jessie | BU13: 2024-04-24 10:20:43 | BV13: Ms, Swathi Reddy | BW13: School Owner | BX13: accountsincharge@globaledgeschool.com | BY13: +919640551155 | CA13: Ms. Anju Madan | CB13: principal@globaledgeschool.com | CD13: Ms.Anitha Jha | CE13: anithajha@globaledgeschool.com | CF13: +919052424441 | CG13: 0 | CH13: Plot no. 8/A,Part of Survey no.s 74 and 75,Jai Hind Enclave,100 feet road,Madhapur | CJ13: 500081 | CK13: Plot no. 8/A,Part of Survey no.s 74 and 75,Jai Hind Enclave,100 feet road,Madhapur | CL13: Hyderabad | CM13: Telangana | CN13: 500081 | CO13: HYDM04246E | CP13: Plot no. 8/A,Part of Survey no.s 74 and 75,Jai Hind Enclave,100 feet road,Madhapur | CQ13: Plot no. 8/A,Part of Survey no.s 74 and 75,Jai Hind Enclave,100 feet road,Madhapur
A14: New School | B14: 1134175 | C14: St. Mary Champion H.Sec. School | E14: Dropped | F14: 2024 | G14: 2024-02-20 00:00:00 | H14: Ei CARES | I14: Regular | J14: IN-2022001530 | K14: Approved By Logistic Team | L14: 468000 | M14: 468000 | N14: 0 | O14: 0 | Q14: 468000 | R14: 300 | S14: 1560 | T14: 0 | U14: 0 | W14: 0 | X14: Installments | Y14: 3 | AA14: 2024-03-15 00:00:00 | AB14: 140400 | AC14: 2024-09-02 00:00:00 | AD14: 163800 | AE14: 2024-12-31 00:00:00 | AF14: 163800 | AG14: 2000-01-01 00:00:00 | AH14: 0 | AI14: 45436 | AJ14: 2024-03-04 00:00:00 | AK14: 2025-01-10 00:00:00 | AL14: 468000 | AM14: 408915 | AN14: 13649 | AO14: 0.4 | AP14: 0.4 | AU14: 0 | AW14: 4 | AX14: MCQ | AY14: Printing By EI | AZ14: OMR | BB14: CBSE | BC14: Indore | BD14: Madhya Pradesh | BE14: North | BF14: MP/Chattisgarh | BG14: National Sales | BH14: 2024-04-02 00:00:00 | BI14: 2025-03-29 00:00:00 | BJ14: Regular School: Active school with student count and rate per student defined | BK14: 22028000021136288 | BL14: 51788000002749223 | BM14: zcrm_51788000254781412 | BN14: 2024-02-20 00:00:00 | BO14: Laxminarayan Dogayan | BP14: fagun.saraiya_eiindia1 | BQ14: laxminarayan.dogayan@ei.study | BR14: Laxminarayan dogayan | BS14: Laxminarayan Dogayan | BT14: Shruti Chauhan | BU14: 2024-02-23 10:37:00 | BV14: Mr. Victor Swamy | BW14: Admin | BX14: victor.swamy@gmail.con | BY14: +917389623616 | BZ14: principal_smchss@yahoo.com | CG14: 50000 | CH14: Suryadev Nagar, Gopur Square | CJ14: 452009 | CK14: Suryadev Nagar, Gopur Square | CL14: Indore | CM14: Madhya Pradesh | CN14: 452009 | CO14: BPLS14197B | CP14: Suryadev Nagar, Gopur Square | CQ14: Suryadev Nagar, Gopur Square
A15: Retention School | B15: 1163014 | C15: Vidya Devi Jindal School | D15: =VLOOKUP(B15,'2025'!B:C,2,0) -> Sudhi | F15: 2024 | G15: 2024-04-04 00:00:00 | H15: Ei ASSET, Ei Mindspark | I15: Regular | J15: IN-2022001842, IN-2022001843, IN-2022001844 | K15: Approved By Logistic Team | L15: 1664554 | M15: 1752664 | N15: 1175052 | O15: 854 | P15: 1376 | Q15: 0 | R15: 0 | T15: 489502 | U15: 210 | V15: 2331 | W15: 0 | X15: Full Payment | Z15: 2024-04-06 00:00:00 | AA15: 2000-01-01 00:00:00 | AB15: 0 | AC15: 2000-01-01 00:00:00 | AD15: 0 | AE15: 2000-01-01 00:00:00 | AF15: 0 | AG15: 2000-01-01 00:00:00 | AH15: 0 | AI15: 0 | AJ15: 2024-05-03 00:00:00 | AK15: 2024-05-03 00:00:00 | AL15: 577612, 587526 | AM15: 0, 490970, 885728 | AN15: -298202, 587526, 86642 | AO15: 0.4462, 0.618 | AP15: 0.4462, 0.618 | AU15: 0, Summer Round, Winter Round | AV15: OMR | AW15: 0 | AX15: MCQ | BA15: Online | BB15: CBSE | BC15: Hisar | BD15: Haryana | BE15: North | BF15: Delhi/Haryana | BG15: National Sales | BH15: 2024-04-04 00:00:00 | BI15: 2025-03-31 00:00:00 | BJ15: Regular School: Active school with student count and rate per student defined | BK15: 22028000021909640, 22028000021909708, 22028000021909804 | BL15: 51788000002749807 | BM15: zcrm_51788000267810265, zcrm_51788000267810442, zcrm_51788000267810619 | BN15: 2024-04-04 00:00:00 | BO15: virender.verma_ei | BP15: fagun.saraiya_eiindia1 | BQ15: virender.verma@ei.study | BR15: Virender verma | BS15: Bhavishya Bansal | BU15: 2024-04-05 15:50:53, 2024-04-05 15:51:33, 2024-04-05 15:52:04 | BV15: Ms. Kamalica Bhowmick | BW15: Other | BX15: doac@vdjs.edu.in | BY15: +919831461183 | BZ15: info@vdjs.edu.in | CG15: 0 | CH15: Hisar-Delhi Bypass Rd, Hisar Cantt, Hisar, Haryana 125044 | CJ15: 125044 | CK15: Hisar-Delhi Bypass Rd, Hisar Cantt, Hisar, Haryana 125044 | CL15: Hisar | CM15: Haryana | CN15: 125044 | CO15: RTKV01058B | CP15: Hisar-Delhi Bypass Rd, Hisar Cantt, Hisar, Haryana 125044 | CQ15: Hisar-Delhi Bypass Rd, Hisar Cantt, Hisar, Haryana 125044
A16: Retention School | B16: 1204891 | C16: B.K Birla Public School, Kalyan | D16: =VLOOKUP(B16,'2025'!B:C,2,0) -> Saloni Shah | F16: 2024 | G16: 2024-06-08 00:00:00, 2024-07-04 00:00:00 | H16: Ei ASSET, Ei Mindspark | I16: Regular | J16: IN-2022002186, IN-2022002308 | K16: Approved By Logistic Team | L16: 2202356 | M16: 2359020 | N16: 1332000 | O16: 2220 | P16: 600 | Q16: 0 | R16: 0 | T16: 870356 | U16: 395 | V16: 2203 | W16: 0 | X16: Installments | Y16: 2 | AA16: 2024-06-10 00:00:00, 2024-07-04 00:00:00 | AB16: 256755, 333000 | AC16: 2024-07-31 00:00:00, 2024-10-31 00:00:00 | AD16: 770265, 999000 | AE16: 2000-01-01 00:00:00 | AF16: 0 | AG16: 2000-01-01 00:00:00 | AH16: 0 | AI16: 133200, 78716 | AJ16: 2024-06-14 00:00:00, 2024-08-16 00:00:00 | AK16: 2024-11-07 00:00:00, 2025-02-21 00:00:00 | AL16: 1027020, 1332000 | AM16: 1198800, 754879 | AN16: 0, 193425 | AO16: 0.2778, 0.6 | AP16: 0.2778, 0.6 | AU16: 0, Winter Round | AV16: OMR | AW16: 0 | AX16: MCQ | BA16: Online | BB16: CBSE | BC16: Kalyan | BD16: Maharashtra | BE16: West | BF16: Mumbai | BG16: National Sales | BH16: 2024-06-01 00:00:00, 2024-06-08 00:00:00 | BI16: 2025-05-31 00:00:00 | BJ16: Regular School: Active school with student count and rate per student defined | BK16: 22028000022859928, 22028000023342260 | BL16: 51788000002750595 | BM16: zcrm_51788000270447061, zcrm_51788000271386001 | BN16: 2024-06-08 00:00:00, 2024-07-04 00:00:00 | BO16: hetal.parmar_ei | BP16: fagun.saraiya_eiindia1 | BQ16: hetal.parmar@ei.study | BR16: Hetal parmar | BS16: Saloni Shah | BU16: 2024-06-08 17:38:19, 2024-07-13 18:19:51 | BV16: Ms. Ruchita . | BX16: viceprincipal@birlaschoolkalyan.com | BY16: +919820776655 | BZ16: contact@birlaschoolkalyan.com | CA16: Ms.Ruchita | CB16: viceprincipal@birlaschoolkalyan.com | CC16: +919820776655 | CD16: Ms.Ruchita | CE16: viceprincipal@birlaschoolkalyan.com | CF16: +919820776655 | CG16: 0 | CH16: B K Birla College Road, Near Rto, Kalyan West, | CJ16: 421304 | CK16: B K Birla College Road, Near Rto, Kalyan West, | CL16: Kalyan | CM16: Maharashtra | CN16: 421304 | CO16: PNEK06448B | CP16: B K Birla College Road, Near Rto, Kalyan West, | CQ16: B K Birla College Road, Near Rto, Kalyan West,
A17: Retention School | B17: 12539 | C17: Mahadevi Birla World Academy (Junior Wing) | D17: =VLOOKUP(B17,'2025'!B:C,2,0) -> Lopamudra Das | F17: 2024 | G17: 2024-02-21 00:00:00 | H17: Ei CARES, Ei Mindspark | I17: Regular | J17: IN-2022001540, IN-2022001541 | K17: Approved By Logistic Team | L17: 3166135 | M17: 3582955 | N17: 0 | O17: 0 | Q17: 850468 | R17: 630 | S17: 1350 | T17: 2315667 | U17: 1035 | V17: 2237 | W17: 0 | X17: Installments | Y17: 2 | AA17: 2024-03-30 00:00:00 | AB17: 1366244, 425234 | AC17: 2024-09-30 00:00:00 | AD17: 1366244, 425234 | AE17: 2000-01-01 00:00:00 | AF17: 0 | AG17: 2000-01-01 00:00:00 | AH17: 0 | AI17: 24654, 40518 | AJ17: 2024-04-02 00:00:00, 2024-10-23 00:00:00 | AK17: 2024-10-23 00:00:00 | AL17: 2732488, 850468 | AM17: 1429960.21, 2193743.31 | AN17: -1383793, 1277874 | AO17: 0.5926, 0.6143 | AP17: 0.5926, 0.6143 | AU17: 0 | AW17: 0, 4 | AX17: MCQ | AY17: Printing By EI | AZ17: OMR | BA17: Online | BB17: CBSE | BC17: Kolkata | BD17: West Bengal | BE17: East | BF17: West Bengal | BG17: National Sales | BH17: 2024-04-02 00:00:00, 2024-04-15 00:00:00 | BI17: 2025-03-27 00:00:00, 2025-03-31 00:00:00 | BJ17: Regular School: Active school with student count and rate per student defined | BK17: 22028000021161100, 22028000021161152 | BL17: 51788000002728599 | BM17: zcrm_51788000265501025, zcrm_51788000265501166 | BN17: 2024-02-21 00:00:00 | BO17: lopamudra.das_eiindia1 | BP17: mitul.patel_ei1 | BQ17: lopamudra.das@ei.study | BR17: Lopamudra das | BS17: Lopamudra Das | BU17: 2024-03-19 10:01:07, 2024-03-19 15:05:15 | BV17: Mr. Vikram Ruia | BX17: administrator@mbwa.org.in | BY17: +919830295876 | BZ17: principal@mbwa.org.in | CA17: Ms Anjana Saha | CB17: principal@mbwa.org.in | CD17: Basundhara Bhattacharya (CARES) | CE17: coordinator.mid@mbwa.org.in | CF17: +919903595193 | CG17: 0 | CH17: 17 A, Darga Road, Park Circus | CJ17: 700017 | CK17: 17 A, Darga Road, Park Circus | CL17: Kolkata | CM17: West Bengal | CN17: 700017 | CO17: CALM01347D | CP17: 17 A, Darga Road, Park Circus | CQ17: 17 A, Darga Road, Park Circus
A18: New School | B18: 1271232 | C18: Rishikul Vidyapeeth, Rishikul Vidyapeeth School | D18: =VLOOKUP(B18,'2025'!B:C,2,0) -> Sudhi | F18: 2024 | G18: 2024-02-25 00:00:00, 2025-05-06 00:00:00 | H18: Ei ASSET, Ei CARES | I18: Group School - Centralize Invoicing | J18: IN-2022001549, IN-2022003466 | K18: Approved By Logistic Team | L18: 1648206 | M18: 1648206 | N18: 0 | O18: 346 | P18: 0 | Q18: 1648206 | R18: 1030 | S18: 1600 | T18: 0 | U18: 0 | W18: 0 | X18: Full Payment, Installments | Y18: 2 | Z18: 2024-12-30 00:00:00 | AA18: 2000-01-01 00:00:00, 2024-04-15 00:00:00 | AB18: 0, 824103 | AC18: 2000-01-01 00:00:00, 2024-08-16 00:00:00 | AD18: 0, 824103 | AE18: 2000-01-01 00:00:00 | AF18: 0 | AG18: 2000-01-01 00:00:00 | AH18: 0 | AI18: 0 | AJ18: 2024-02-23 00:00:00 | AK18: 2024-11-20 00:00:00 | AL18: 0, 1648206 | AM18: 0, 720090 | AN18: 0, 928116 | AO18: 0.5428000000000001, 1 | AP18: 0.4928, 1 | AR18: 0.05 | AU18: 0, Winter Round | AV18: OMR | AW18: 0, 4 | AX18: MCQ | AY18: Printing By EI | AZ18: OMR | BB18: CBSE | BC18: Sonepat | BD18: Haryana | BE18: North | BF18: Delhi/Haryana | BG18: National Sales | BH18: 2024-04-01 00:00:00 | BI18: 2025-03-31 00:00:00 | BJ18: Regular School: Active school with student count and rate per student defined | BK18: 22028000021209392, 22028000029865060 | BL18: 51788000002751831 | BM18: zcrm_51788000255131686, zcrm_51788000288555651 | BN18: 2024-02-25 00:00:00, 2025-05-06 00:00:00 | BO18: vikas.shukla_ei | BP18: fagun.saraiya_eiindia1, maruf.shaikh1 | BQ18: vikas.shukla@ei.study | BR18: Vikas shukla | BS18: Sudhi Malhotra | BU18: 2024-03-02 10:52:25, 2025-05-06 10:30:49 | BV18: Dheeraj Sharma | BW18: School Owner | BX18: Dheeraj.sharma@rishikulvidyapeeth.edu.in, dheeraj.sharma@rishikulvidyapeeth.edu.in | BY18: +919991114140 | BZ18: dheeraj.sharma@rishikulvidyapeeth.edu.in | CA18: Dheeraj Sharma | CB18: dheeraj.sharma@rishikulvidyapeeth.edu.in, dheerajsharma@rishikulvidyapeeth.edu.in | CC18: +919991114140 | CD18: Dheeraj Sharma, Nisha | CE18: dheerajsharma@rishikulvidyapeeth.edu.in, nisha@rishikulvidyapeeth.edu.in | CF18: +919416524444, +919991114140 | CG18: 44000 | CH18: Devru Road, Devru Road, Jeeva vihar | CJ18: 131001 | CK18: Devru Road, Jeeva vihar, Devru Road, Jeevan Vihar | CL18: Sonepat | CM18: Haryana | CN18: 131001 | CP18: Devru Road, Jeeva vihar | CQ18: Devru Road, Jeevan Vihar
A19: Key Account | B19: 128171 | C19: Navrachana School, Sama | D19: =VLOOKUP(B19,'2025'!B:C,2,0) -> Ishita Jethwa | F19: 2024 | G19: 2024-04-16 00:00:00 | H19: Ei CARES | I19: Regular | J19: IN-2022001918 | K19: Approved By Logistic Team | L19: 1797563 | M19: 1797563 | N19: 0 | O19: 0 | Q19: 1797563 | R19: 1924 | S19: 934 | T19: 0 | U19: 0 | W19: 0 | X19: Installments | Y19: 2 | AA19: 2024-04-20 00:00:00 | AB19: 898782 | AC19: 2024-11-01 00:00:00 | AD19: 898782 | AE19: 2000-01-01 00:00:00 | AF19: 0 | AG19: 2000-01-01 00:00:00 | AH19: 0 | AI19: 35868 | AJ19: 2024-06-28 00:00:00 | AK19: 2024-11-26 00:00:00 | AL19: 1797564 | AM19: 1757508 | AN19: 4188 | AO19: 0.7137 | AP19: 0.6137 | AR19: 0.05 | AT19: 0.05 | AU19: 0 | AW19: 4 | AX19: MCQ | AY19: Printing By EI | AZ19: OMR | BB19: CBSE | BC19: Vadodara | BD19: Gujarat | BE19: West | BF19: Gujarat | BG19: National Sales | BH19: 2024-04-01 00:00:00 | BI19: 2025-03-31 00:00:00 | BJ19: Regular School: Active school with student count and rate per student defined | BK19: 22028000022100080 | BL19: 51788000002732079 | BM19: zcrm_51788000267509650 | BN19: 2024-04-16 00:00:00 | BO19: heena.kumar_ei | BP19: fagun.saraiya_eiindia1 | BQ19: heena.kumar@ei.study | BR19: Heena kumar | BS19: Heena Kumar | BU19: 2024-05-03 10:58:47 | BV19: Ms. Suprabha Menon | BW19: Principal | BX19: suprabham@navrachana.edu.in | BY19: +919925260895 | BZ19: navrachanasama@navrachana.edu.in | CA19: Ms. Suprabha Menon | CB19: suprabham@navrachana.edu.in | CC19: +919925260895 | CD19: Ms. Gayatri Devliyal | CE19: gayatrid@navrachana.edu.in | CF19: +917016014240 | CG19: 100300 | CH19: Sama Road | CJ19: 390024 | CK19: Sama Road, Near GIPCL Circle | CL19: Vadodara | CM19: Gujarat | CN19: 390024 | CO19: BRDN01995A | CP19: Sama Road | CQ19: Sama Road, Near GIPCL Circle
A20: Retention School | B20: 1312595 | C20: KLE M. R. Sakhare State School, Hubballi | F20: 2024 | G20: 2024-06-16 00:00:00 | H20: Ei ASSET, Ei Mindspark | I20: Regular | J20: IN-2022002212, IN-2022002236 | K20: Approved By Logistic Team | L20: 440692 | M20: 490128 | N20: 166047 | O20: 534 | P20: 311 | Q20: 0 | R20: 0 | T20: 274645 | U20: 540 | V20: 509 | W20: 0 | X20: Installments | Y20: 2 | AA20: 2024-07-15 00:00:00 | AB20: 162041, 83024 | AC20: 2024-11-15 00:00:00, 2024-12-15 00:00:00 | AD20: 162041, 83024 | AE20: 2000-01-01 00:00:00 | AF20: 0 | AG20: 2000-01-01 00:00:00 | AH20: 0 | AI20: 16794, 27458 | AJ20: 2024-09-05 00:00:00, 2024-09-18 00:00:00 | AK20: 2025-01-17 00:00:00 | AL20: 166048, 324082 | AM20: 151146, 296544 | AN20: -1892, 80 | AO20: 0.7927, 0.8332999999999999 | AP20: 0.7927, 0.8332999999999999 | AU20: 0, Winter Round | AV20: OMR | AW20: 0 | AX20: MCQ | BA20: Offline | BB20: State Board | BC20: Hubli | BD20: Karnataka | BE20: South | BF20: Karnataka/Kerala | BG20: National Sales | BH20: 2024-06-01 00:00:00 | BI20: 2025-04-30 00:00:00, 2025-05-31 00:00:00 | BJ20: Regular School: Active school with student count and rate per student defined | BK20: 22028000023002488, 22028000023033448 | BL20: 51788000002752617 | BM20: zcrm_51788000270598683, zcrm_51788000270690525 | BN20: 2024-06-16 00:00:00 | BO20: vineet.upadhye_ei | BP20: mitul.patel_ei1 | BQ20: vineet.upadhye@ei.study | BR20: Vineet upadhye | BS20: Nisha Murali | BU20: 2024-06-18 10:43:12, 2024-06-18 10:43:30 | BV20: Maruf Shaikh | BX20: maruf.shaikh@ei.study | BY20: +919016039311 | BZ20: klemrsakharestate@gmail.com | CG20: 0 | CH20: Vidyanagar, Hubballi, Unkal Cross | CJ20: 580031 | CK20: Vidyanagar, Hubballi, Unkal Cross | CL20: Hubli | CM20: Karnataka | CN20: 580031 | CO20: BLRK04875D | CP20: Vidyanagar, Hubballi, Unkal Cross | CQ20: Vidyanagar, Hubballi, Unkal Cross
A21: Retention School | B21: 1315210 | C21: KLE School, Manjunath Nagar, Hubballi | F21: 2024 | G21: 2024-06-16 00:00:00 | H21: Ei ASSET, Ei Mindspark | I21: Regular | J21: IN-2022002214, IN-2022002235 | K21: Approved By Logistic Team | L21: 610369 | M21: 678481 | N21: 231969 | O21: 746 | P21: 311 | Q21: 0 | R21: 0 | T21: 378400 | U21: 744 | V21: 509 | W21: 0 | X21: Installments | Y21: 2 | AA21: 2024-07-15 00:00:00 | AB21: 115985, 223256 | AC21: 2024-11-15 00:00:00, 2024-12-15 00:00:00 | AD21: 115985, 223256 | AE21: 2000-01-01 00:00:00 | AF21: 0 | AG21: 2000-01-01 00:00:00 | AH21: 0 | AI21: 23325, 38136 | AJ21: 2024-09-05 00:00:00, 2024-09-18 00:00:00 | AK21: 2025-01-17 00:00:00 | AL21: 231970, 446512 | AM21: 209925, 411864 | AN21: -1280, -3488 | AO21: 0.7927, 0.8332999999999999 | AP21: 0.7927, 0.8332999999999999 | AU21: 0, Winter Round | AV21: OMR | AW21: 0 | AX21: MCQ | BA21: Online | BB21: CBSE | BC21: Hubli | BD21: Karnataka | BE21: South | BF21: Karnataka/Kerala | BG21: National Sales | BH21: 2024-06-01 00:00:00 | BI21: 2025-04-30 00:00:00, 2025-05-31 00:00:00 | BJ21: Regular School: Active school with student count and rate per student defined | BK21: 22028000023002568, 22028000023033408 | BL21: 51788000002752639 | BM21: zcrm_51788000270598543, zcrm_51788000270633910 | BN21: 2024-06-16 00:00:00 | BO21: vineet.upadhye_ei | BP21: mitul.patel_ei1 | BQ21: vineet.upadhye@ei.study | BR21: Vineet upadhye | BS21: Nisha Murali | BU21: 2024-06-18 10:42:47, 2024-06-18 10:44:49 | BV21: Maruf Shaikh | BX21: maruf.shaikh@ei.study | BY21: +919016039311 | BZ21: kleschool_man@yahoo.com | CG21: 0 | CH21: Gokul Road, Manjunath Nagar, | CJ21: 580030 | CK21: Gokul Road, Manjunath Nagar, HUBBALLI | CL21: Hubli | CM21: Karnataka | CN21: 580030 | CO21: BLRK04875D | CP21: Gokul Road, Manjunath Nagar, | CQ21: Gokul Road, Manjunath Nagar, HUBBALLI
A22: Retention School | B22: 1316481 | C22: KLE School, Gadag | F22: 2024 | G22: 2024-06-16 00:00:00 | H22: Ei ASSET, Ei Mindspark | I22: Regular | J22: IN-2022002216, IN-2022002232 | K22: Approved By Logistic Team | L22: 684044 | M22: 760212 | N22: 260887 | O22: 839 | P22: 311 | Q22: 0 | R22: 0 | T22: 423157 | U22: 832 | V22: 509 | W22: 0 | X22: Installments | Y22: 2 | AA22: 2024-07-15 00:00:00 | AB22: 130444, 249663 | AC22: 2024-11-15 00:00:00, 2024-12-15 00:00:00 | AD22: 130444, 249663 | AE22: 2000-01-01 00:00:00 | AF22: 0 | AG22: 2000-01-01 00:00:00 | AH22: 0 | AI22: 26061.8, 42610 | AJ22: 2024-09-05 00:00:00, 2024-09-18 00:00:00 | AK22: 2025-01-17 00:00:00 | AL22: 260888, 499326 | AM22: 234556.2, 460190 | AN22: -3474, 270 | AO22: 0.7927, 0.8332999999999999 | AP22: 0.7927, 0.8332999999999999 | AU22: 0, Winter Round | AV22: OMR | AW22: 0 | AX22: MCQ | BA22: Offline | BB22: CBSE | BC22: Gadag | BD22: Karnataka | BE22: South | BF22: Karnataka/Kerala | BG22: National Sales | BH22: 2024-06-01 00:00:00 | BI22: 2025-04-30 00:00:00, 2025-05-31 00:00:00 | BJ22: Regular School: Active school with student count and rate per student defined | BK22: 22028000023002648, 22028000023033288 | BL22: 51788000002752651 | BM22: zcrm_51788000270598125, zcrm_51788000270633787 | BN22: 2024-06-16 00:00:00 | BO22: vineet.upadhye_ei | BP22: mitul.patel_ei1 | BQ22: vineet.upadhye@ei.study | BR22: Vineet upadhye | BS22: Nisha Murali | BU22: 2024-06-18 10:40:44, 2024-06-18 10:48:43 | BV22: Maruf Shaikh | BX22: maruf.shaikh@ei.study | BY22: +919016039311 | BZ22: klesgdg@gmail.com | CG22: 0 | CH22: J T College Campus, Hatalgeri Naka Gadag | CJ22: 582101 | CK22: J T College Campus, Hatalgeri Naka Gadag | CL22: Gadag | CM22: Karnataka | CN22: 582101 | CO22: BLRK04875D | CP22: J T College Campus, Hatalgeri Naka Gadag | CQ22: J T College Campus, Hatalgeri Naka Gadag
A23: New School | B23: 1324480 | C23: The Century School | D23: =VLOOKUP(B23,'2025'!B:C,2,0) -> Tanya | F23: 2024 | G23: 2024-06-07 00:00:00, 2024-11-20 00:00:00 | H23: Ei ASSET, Ei Mindspark | I23: Regular | J23: IN-2022002178, IN-2022002609 | K23: Approved By Logistic Team | L23: 1282258 | M23: 1450060 | N23: 350025 | O23: 500 | P23: 700 | Q23: 0 | R23: 0 | T23: 932233 | U23: 500 | V23: 1864 | W23: 0 | X23: Installments | Y23: 2, 4 | AA23: 2024-06-15 00:00:00, 2024-11-30 00:00:00 | AB23: 175013, 275009 | AC23: 2024-08-31 00:00:00, 2024-12-10 00:00:00 | AD23: 175013, 275009 | AE23: 2000-01-01 00:00:00, 2024-10-31 00:00:00 | AF23: 0, 275009 | AG23: 2000-01-01 00:00:00, 2024-12-31 00:00:00 | AH23: 0, 275009 | AI23: 0 | AJ23: 2024-07-19 00:00:00, 2024-11-30 00:00:00 | AK23: 2024-12-31 00:00:00, 2025-05-13 00:00:00 | AL23: 1100036, 350026 | AM23: 200000, 958832 | AN23: 141204, 150026 | AO23: 0.3889, 0.5333 | AP23: 0.3889, 0.5333 | AU23: 0, Winter Round | AV23: OMR | AW23: 0 | AX23: MCQ | BA23: Online | BB23: CBSE | BC23: Karnal | BD23: Haryana | BE23: North | BF23: Delhi/Haryana | BG23: National Sales | BH23: 2024-03-01 00:00:00, 2024-06-24 00:00:00 | BI23: 2025-03-31 00:00:00 | BJ23: Regular School: Active school with student count and rate per student defined | BK23: 22028000022873236, 22028000026329168 | BL23: 51788000002752831 | BM23: zcrm_51788000270363462, zcrm_51788000277767578 | BN23: 2024-06-07 00:00:00, 2024-11-20 00:00:00 | BO23: vikas.shukla_ei | BP23: fagun.saraiya_eiindia1 | BQ23: vikas.shukla@ei.study | BR23: Vikas shukla | BS23: Vikas Shukla | BT23: Tanya Marina Brooks | BU23: 2024-06-12 11:51:42, 2024-12-02 10:19:54 | BV23: Mr. Ankur Jindal | BW23: School Owner | BX23: director@thecenturyschool.com | BY23: +919416032976 | BZ23: thecenturyschool@rediffmail.com | CA23: Dr. Karuna Arora | CB23: drkarunaarora@gmail.com | CC23: +919416266294 | CD23: Dr. Karuna Arora | CE23: drkarunaarora@gmail.com | CF23: +919416266294 | CG23: 8000 | CH23: G T Road Karnal Side Gharaunda Distt Karnal Haryana | CJ23: 132114 | CK23: G T Road Karnal Side Gharaunda Distt Karnal Haryana | CL23: Karnal | CM23: Haryana | CN23: 132114 | CP23: G T Road Karnal Side Gharaunda Distt Karnal Haryana | CQ23: G T Road Karnal Side Gharaunda Distt Karnal Haryana
A24: Retention School | B24: 1330320 | C24: KLE Mahadevappanna Munavalli School, Gokak | F24: 2024 | G24: 2024-06-16 00:00:00 | H24: Ei ASSET, Ei Mindspark | I24: Regular | J24: IN-2022002215, IN-2022002233 | K24: Approved By Logistic Team | L24: 753983 | M24: 840222 | N24: 274880 | O24: 884 | P24: 311 | Q24: 0 | R24: 0 | T24: 479103 | U24: 942 | V24: 509 | W24: 0 | X24: Installments | Y24: 2 | AA24: 2024-07-15 00:00:00 | AB24: 137440, 282671 | AC24: 2024-11-15 00:00:00, 2024-12-15 00:00:00 | AD24: 137440, 282671 | AE24: 2000-01-01 00:00:00 | AF24: 0 | AG24: 2000-01-01 00:00:00 | AH24: 0 | AI24: 27803.4, 45458 | AJ24: 2024-09-05 00:00:00, 2024-09-18 00:00:00 | AK24: 2025-01-17 00:00:00 | AL24: 274880, 565342 | AM24: 250230.6, 490942 | AN24: -3154, 28942 | AO24: 0.7927, 0.8332999999999999 | AP24: 0.7927, 0.8332999999999999 | AU24: 0, Winter Round | AV24: OMR | AW24: 0 | AX24: MCQ | BA24: Online | BB24: CBSE | BC24: Gokak | BD24: Karnataka | BE24: South | BF24: Karnataka/Kerala | BG24: National Sales | BH24: 2024-06-01 00:00:00 | BI24: 2025-04-30 00:00:00, 2025-05-31 00:00:00 | BJ24: Regular School: Active school with student count and rate per student defined | BK24: 22028000023002608, 22028000023033328 | BL24: 51788000002752887 | BM24: zcrm_51788000270598265, zcrm_51788000270690263 | BN24: 2024-06-16 00:00:00 | BO24: vineet.upadhye_ei | BP24: mitul.patel_ei1 | BQ24: vineet.upadhye@ei.study | BR24: Vineet upadhye | BS24: Nisha Murali | BU24: 2024-06-18 10:41:32, 2024-06-18 10:52:16 | BV24: Maruf Shaikh | BX24: maruf.shaikh@ei.study | BY24: +919016039311 | BZ24: klesgokak@gmail.com | CG24: 0 | CH24: Opp. Umrani^S Hospital, K.L.E. Campus Main Road, Dist. Gokak | CJ24: 591307 | CK24: Opp. Umrani^S Hospital, K.L.E. Campus Main Road, Dist. Gokak | CL24: Gokak | CM24: Karnataka | CN24: 591307 | CO24: BLRK04875D | CP24: Opp. Umrani^S Hospital, K.L.E. Campus Main Road, Dist. Gokak | CQ24: Opp. Umrani^S Hospital, K.L.E. Campus Main Road, Dist. Gokak
A25: Retention School | B25: 1337248 | C25: The Sivakasi Lions Matriculation Higher Secondary School | F25: 2024 | G25: 2024-06-03 00:00:00 | H25: Ei Mindspark | I25: Regular | J25: IN-2022002148 | K25: Approved By Logistic Team | L25: 480456 | M25: 566938 | N25: 0 | O25: 0 | Q25: 0 | R25: 0 | T25: 480456 | U25: 378 | V25: 1271 | W25: 0 | X25: Installments | Y25: 4 | AA25: 2024-06-05 00:00:00 | AB25: 141735 | AC25: 2024-09-10 00:00:00 | AD25: 141735 | AE25: 2024-12-10 00:00:00 | AF25: 141735 | AG25: 2024-12-31 00:00:00 | AH25: 141735 | AI25: 5306 | AJ25: 2024-06-13 00:00:00 | AK25: 2025-03-21 00:00:00 | AL25: 566940 | AM25: 570409 | AN25: -8775 | AO25: 0.5834 | AP25: 0.5834 | AU25: 0 | AW25: 0 | AX25: MCQ | BA25: Online | BB25: CBSE | BC25: Sivakasi | BD25: Tamil Nadu | BE25: South | BF25: Tamil Nadu | BG25: National Sales | BH25: 2024-06-05 00:00:00 | BI25: 2025-05-31 00:00:00 | BJ25: Regular School: Active school with student count and rate per student defined | BK25: 22028000022758828 | BL25: 51788000002753055 | BM25: zcrm_51788000270232074 | BN25: 2024-06-03 00:00:00 | BO25: vineeth.v_ei | BP25: hakim.kanchwala_eiindia1 | BQ25: vineeth.v@ei.study | BR25: Vineeth v | BS25: Vineeth T V | BU25: 2024-06-12 14:40:43 | BV25: Mr. Lion Ramesh Kumar J | BX25: correspondent@thesivakasilionsschool.in | BY25: +919486027172 | BZ25: principal@thesivakasilionsschool.in | CG25: 0 | CH25: 2/754-A Virudhunagar Road, Anaikuttam Post, Sivakasi | CJ25: 626189 | CK25: 2/754-A Virudhunagar Road, Anaikuttam Post, Sivakasi | CL25: Sivakasi | CM25: Tamil Nadu | CN25: 626189 | CO25: MRIT01544E | CP25: 2/754-A Virudhunagar Road, Anaikuttam Post, Sivakasi | CQ25: 2/754-A Virudhunagar Road, Anaikuttam Post, Sivakasi
A26: New School | B26: 14129 | C26: St. Hilda'S School | E26: Dropped | F26: 2024 | G26: 2023-11-23 00:00:00 | H26: Ei ASSET | I26: Regular | J26: IN-2022001289 | K26: Approved By Logistic Team | L26: 409200 | M26: 409200 | N26: 409200 | O26: 341 | P26: 1200 | Q26: 0 | R26: 0 | T26: 0 | U26: 0 | W26: 0 | X26: Installments | Y26: 2 | AA26: 2023-11-30 00:00:00 | AB26: 81840 | AC26: 2024-06-15 00:00:00 | AD26: 327360 | AE26: 2000-01-01 00:00:00 | AF26: 0 | AG26: 2000-01-01 00:00:00 | AH26: 0 | AI26: 0 | AJ26: 2023-12-05 00:00:00 | AK26: 2024-07-19 00:00:00 | AL26: 409200 | AM26: 404400 | AN26: 4800 | AO26: 0.2 | AP26: 0.2 | AU26: Summer Round | AV26: OMR | AW26: 0 | AX26: MCQ | BB26: CISCE | BC26: Ooty | BD26: Tamil Nadu | BE26: South | BF26: Tamil Nadu | BG26: National Sales | BH26: 2024-07-01 00:00:00 | BI26: 2024-07-31 00:00:00 | BJ26: Regular School: Active school with student count and rate per student defined | BK26: 22028000020060192 | BL26: 51788000002728613 | BM26: zcrm_51788000260939144 | BN26: 2023-11-23 00:00:00 | BO26: praveenkumar.rajamanickam_ei | BP26: sourabh.mehta_eiindia | BQ26: praveenkumar.rajamanickam@ei.study | BR26: Praveenkumar rajamanickam | BS26: Praveenkumar Rajamanickam | BT26: Dipti Jain | BU26: 2023-11-28 11:14:19 | BV26: Ms PAMELA RODRICKS . | BW26: Principal | BX26: sthildasprincipal@gmail.com | BY26: +919943241432 | BZ26: hildas_school@hotmail.com | CA26: Ms PAMELA RODRICKS . | CB26: sthildasprincipal@gmail.com | CC26: +919943241432 | CD26: Mr Ajay | CE26: sthildasprincipal@gmail.com | CF26: +919943241432 | CG26: 100000 | CH26: Sheddon Rd, Pudumund, Ooty, Tamil Nadu 643001 | CJ26: 643001 | CK26: Sheddon Rd, Pudumund, Ooty, Tamil Nadu 643001 | CL26: Ooty | CM26: Tamil Nadu | CN26: 643001 | CP26: Sheddon Rd, Pudumund, Ooty, Tamil Nadu 643001 | CQ26: Sheddon Rd, Pudumund, Ooty, Tamil Nadu 643001
A27: Retention School | B27: 1424516 | C27: JSS Public School, HSR Layout | F27: 2024 | G27: 2024-07-11 00:00:00 | H27: Ei ASSET | I27: Regular | J27: IN-2022002337 | K27: Approved By Logistic Team | L27: 911281 | M27: 911281 | N27: 911281 | O27: 1110 | P27: 821 | Q27: 0 | R27: 0 | T27: 0 | U27: 0 | W27: 0 | X27: Installments | Y27: 2 | AA27: 2024-07-31 00:00:00 | AB27: 273384 | AC27: 2024-11-30 00:00:00 | AD27: 637897 | AE27: 2000-01-01 00:00:00 | AF27: 0 | AG27: 2000-01-01 00:00:00 | AH27: 0 | AI27: 0 | AJ27: 2024-08-30 00:00:00 | AK27: 2025-05-31 00:00:00 | AL27: 911281 | AM27: 911280 | AN27: 1 | AO27: 0.5423 | AP27: 0.5423 | AU27: Winter Round | AV27: OMR | AW27: 0 | AX27: MCQ | BB27: CBSE | BC27: Bengaluru | BD27: Karnataka | BE27: South | BF27: Karnataka/Kerala | BG27: National Sales | BH27: 2024-08-01 00:00:00 | BI27: 2025-03-31 00:00:00 | BJ27: Regular School: Active school with student count and rate per student defined | BK27: 22028000023476100 | BL27: 51788000002754706 | BM27: zcrm_51788000271722001 | BN27: 2024-07-11 00:00:00 | BO27: dipti.jain_ei | BP27: mitul.patel_ei1 | BQ27: dipti.jain@ei.study | BR27: Dipti jain | BS27: Jasper Jessie | BU27: 2024-08-23 15:06:10 | BV27: Mrs. Lily Sahay | BW27: Principal | BX27: jss_hsrps@yahoo.com | BY27: +919731777112 | BZ27: jss_hsrps@yahoo.com | CG27: 0 | CH27: #4/A, 14Th Main, 6Th Sector, H.S.R. Layout, Adjacent To Bda Complex, | CJ27: 560102 | CK27: #4/A, 14Th Main, 6Th Sector, H.S.R. Layout, Adjacent To Bda Complex, | CL27: Bengaluru | CM27: Karnataka | CN27: 560102 | CP27: #4/A, 14Th Main, 6Th Sector, H.S.R. Layout, Adjacent To Bda Complex, | CQ27: #4/A, 14Th Main, 6Th Sector, H.S.R. Layout, Adjacent To Bda Complex,
A28: Retention School | B28: 1429114 | C28: Subbiah Central School | F28: 2024 | G28: 2024-06-17 00:00:00, 2024-06-24 00:00:00 | H28: Ei ASSET, Ei CARES | I28: Regular | J28: IN-2022002242, IN-2022002268, IN-2022002271 | K28: Approved By Logistic Team | L28: 1018600 | M28: 1018600 | N28: 269800 | O28: 284 | P28: 950 | Q28: 748800 | R28: 346 | S28: 1300, 2600 | T28: 0 | U28: 0 | W28: 0 | X28: Installments | Y28: 3, 4 | AA28: 2024-06-01 00:00:00, 2024-06-19 00:00:00 | AB28: 149500, 37700, 91732 | AC28: 2024-09-01 00:00:00, 2024-09-19 00:00:00 | AD28: 149500, 37700, 89034 | AE28: 2024-11-01 00:00:00, 2024-12-01 00:00:00 | AF28: 149500, 37700, 89034 | AG28: 2000-01-01 00:00:00, 2024-12-31 00:00:00 | AH28: 0, 149500, 37700 | AI28: 0 | AJ28: 2025-03-05 00:00:00 | AK28: 2025-10-13 00:00:00 | AL28: 150800, 269800, 598000 | AM28: 0, 1033875 | AN28: -764075, 150800, 598000 | AO28: 0, 0.5 | AP28: 0.5 | AU28: 0, Winter Round | AV28: OMR | AW28: 0, 2, 4 | AX28: MCQ | AY28: Printing By EI | AZ28: OMR | BB28: CBSE | BC28: Tirupur | BD28: Tamil Nadu | BE28: South | BF28: Tamil Nadu | BG28: National Sales | BH28: 2024-06-01 00:00:00 | BI28: 2025-03-31 00:00:00 | BJ28: Regular School: Active school with student count and rate per student defined | BK28: 22028000023033760, 22028000023124952, 22028000023126540 | BL28: 51788000002754853 | BM28: zcrm_51788000270417181, zcrm_51788000271066068, zcrm_51788000271132113 | BN28: 2024-06-17 00:00:00, 2024-06-24 00:00:00 | BO28: jasper.jessie_ei | BP28: hakim.kanchwala_eiindia1, sourabh.mehta_eiindia | BQ28: jasper.jessie@ei.study | BR28: Jasper jessie | BS28: Vineeth T V | BU28: 2024-07-05 11:51:55, 2024-07-05 11:54:13, 2024-07-05 11:55:14 | BV28: Jerald Arockia | BX28: principalscs@subbiahschools.org | BY28: +914212245252 | BZ28: info@subbiahschools.org | CG28: 0 | CH28: No-1, College Road, | CJ28: 641602 | CK28: No-1, College Road, | CL28: Tirupur | CM28: Tamil Nadu | CN28: 641602 | CP28: No-1, College Road, | CQ28: No-1, College Road,
A29: Retention School | B29: 147 | C29: Nath Valley School | E29: Dropped | F29: 2024 | G29: 2024-07-02 00:00:00 | H29: Ei ASSET | I29: Regular | J29: IN-2022002303 | K29: Approved By Logistic Team | L29: 263400 | M29: 263400 | N29: 263400 | O29: 439 | P29: 600 | Q29: 0 | R29: 0 | T29: 0 | U29: 0 | W29: 0 | X29: Installments | Y29: 3 | AA29: 2024-08-31 00:00:00 | AB29: 89556 | AC29: 2024-09-30 00:00:00 | AD29: 86922 | AE29: 2024-10-31 00:00:00 | AF29: 86922 | AG29: 2000-01-01 00:00:00 | AH29: 0 | AI29: 0 | AJ29: 2024-08-29 00:00:00 | AK29: 2025-01-14 00:00:00 | AL29: 263400 | AM29: 263400 | AN29: 0 | AO29: 0.6 | AP29: 0.6 | AU29: Winter Round | AV29: OMR | AW29: 0 | AX29: MCQ | BB29: CBSE | BC29: Aurangabad | BD29: Maharashtra | BE29: West | BF29: Rest of Maharashtra and Goa | BG29: National Sales | BH29: 2024-07-10 00:00:00 | BI29: 2025-05-31 00:00:00 | BJ29: Regular School: Active school with student count and rate per student defined | BK29: 22028000023275356 | BL29: 51788000002728395 | BM29: zcrm_51788000271349468 | BN29: 2024-07-02 00:00:00 | BO29: aarti.iyer_ei | BP29: hakim.kanchwala_eiindia1 | BQ29: aarti.iyer@ei.study | BR29: Aarti iyer | BS29: Nainesh Bhise | BT29: Aarti Iyer | BU29: 2024-07-05 12:07:22 | BV29: Dr. Sharda Gupta | BW29: Principal | BX29: contact@nathvalleyschool.com | BY29: +919673304848 | BZ29: contact@nathvalleyschool.com | CG29: 0 | CH29: P O Box 567, Cantonment Post Office, Satara Village, Paithan Road | CJ29: 431002 | CK29: P O Box 567, Cantonment Post Office, Satara Village, Paithan Road | CL29: Aurangabad | CM29: Maharashtra | CN29: 431002 | CP29: P O Box 567, Cantonment Post Office, Satara Village, Paithan Road | CQ29: P O Box 567, Cantonment Post Office, Satara Village, Paithan Road
A30: 1-year School | B30: 1482482 | C30: Pathania Public School | D30: =VLOOKUP(B30,'2025'!B:C,2,0) -> Anushka | F30: 2024 | G30: 2024-04-09 00:00:00 | H30: Ei CARES | I30: Regular | J30: IN-2022001887 | K30: Approved By Logistic Team | L30: 540004 | M30: 540004 | N30: 0 | O30: 0 | Q30: 540004 | R30: 750 | S30: 720 | T30: 0 | U30: 0 | W30: 0 | X30: Full Payment | Z30: 2024-03-29 00:00:00 | AA30: 2000-01-01 00:00:00 | AB30: 0 | AC30: 2000-01-01 00:00:00 | AD30: 0 | AE30: 2000-01-01 00:00:00 | AF30: 0 | AG30: 2000-01-01 00:00:00 | AH30: 0 | AI30: 10800 | AJ30: 2024-03-29 00:00:00 | AK30: 2024-03-29 00:00:00 | AL30: 540004 | AM30: 529200 | AN30: 4 | AO30: 0.467 | AP30: 0.41700000000000004 | AQ30: 0.05 | AU30: 0 | AW30: 2 | AX30: MCQ | AY30: Printing By EI | AZ30: OMR | BB30: CBSE | BC30: Rohtak | BD30: Haryana | BE30: North | BF30: Delhi/Haryana | BG30: National Sales | BH30: 2024-04-01 00:00:00 | BI30: 2025-03-31 00:00:00 | BJ30: Regular School: Active school with student count and rate per student defined | BK30: 22028000022000032 | BL30: 51788000002755871 | BM30: zcrm_51788000266942147 | BN30: 2024-04-09 00:00:00 | BO30: vikas.shukla_ei | BP30: fagun.saraiya_eiindia1 | BQ30: vikas.shukla@ei.study | BR30: Vikas shukla | BS30: Anushka Gupta | BU30: 2024-04-10 10:14:10 | BV30: Mr. Anshul Pathania | BX30: patanshul@gmail.com | BY30: +919991599935 | BZ30: ppsrohtak@gmail.com | CA30: Tanvi Pathania | CB30: patanshul@gmail.com | CC30: +919991599935 | CD30: Rajni Gulati | CE30: rajnigulati16091985@gmail.com | CF30: +919416518727 | CG30: 54000 | CH30: 8th K.M. STONE, GOHANA ROAD , ROHTAK | CJ30: 124001 | CK30: 8th K.M. STONE, GOHANA ROAD , ROHTAK | CL30: Rohtak | CM30: Haryana | CN30: 124001 | CO30: RTKP03269A | CP30: Sector 34, Suncity Township-I, Rohtak, Haryana 124001 | CQ30: Sector 34, Suncity Township-I, Rohtak, Haryana 124001
A31: Retention School | B31: 1524162 | C31: SAI International School | D31: =VLOOKUP(B31,'2025'!B:C,2,0) -> Sumit Rana | F31: 2024 | G31: 2024-05-09 00:00:00, 2024-06-05 00:00:00 | H31: Ei ASSET, Ei Mindspark | I31: Regular | J31: IN-2022002034, IN-2022002171 | K31: Approved By Logistic Team | L31: 1578982 | M31: 1683667 | N31: 997400 | O31: 1995 | P31: 500 | Q31: 0 | R31: 0 | T31: 581582 | U31: 600 | V31: 969 | W31: 0 | X31: Full Payment, Installments | Y31: 4 | Z31: 2024-07-01 00:00:00 | AA31: 2000-01-01 00:00:00, 2024-05-11 00:00:00 | AB31: 0, 171567 | AC31: 2000-01-01 00:00:00, 2024-07-05 00:00:00 | AD31: 0, 171567 | AE31: 2000-01-01 00:00:00, 2024-10-05 00:00:00 | AF31: 0, 171567 | AG31: 2000-01-01 00:00:00, 2024-12-31 00:00:00 | AH31: 0, 171567 | AI31: 0, 33938 | AJ31: 2024-10-18 00:00:00, 2024-10-19 00:00:00 | AK31: 2024-10-19 00:00:00, 2025-01-30 00:00:00 | AL31: 686268, 997400 | AM31: 600520, 991757 | AN31: 51810, 5643 | AO31: 0.6667000000000001, 0.6823 | AP31: 0.6667000000000001, 0.6823 | AU31: 0, Summer Round | AV31: OMR | AW31: 0 | AX31: MCQ | BA31: Online | BB31: CBSE | BC31: Bhubaneswar | BD31: Odisha | BE31: East | BF31: Odisha | BG31: National Sales | BH31: 2024-05-10 00:00:00, 2024-06-05 00:00:00 | BI31: 2025-03-31 00:00:00, 2025-04-30 00:00:00 | BJ31: Regular School: Active school with student count and rate per student defined | BK31: 22028000022429064, 22028000022845064 | BL31: 51788000002756667 | BM31: zcrm_51788000269102204, zcrm_51788000270347275 | BN31: 2024-05-09 00:00:00, 2024-06-05 00:00:00 | BO31: lopamudra.das_eiindia1 | BP31: mitul.patel_ei1 | BQ31: lopamudra.das@ei.study | BR31: Lopamudra das | BS31: Lopamudra Das | BU31: 2024-05-09 12:17:02, 2024-06-08 10:02:33 | BV31: Mr. Dipak Somani | BW31: Admin | BX31: dipak@sai.edu.in | BY31: +918598097405 | BZ31: info@saiinternationalschool.com | CA31: Neelkantha Panigrahi | CB31: srprincipal@saiinternational.edu.in | CC31: +918598097404 | CD31: Prakash Sahoo | CE31: principalsecondary@saiinternational.edu.in | CF31: +919910573303 | CG31: 0 | CH31: Plot No 5A, Chandaka Industrial Estate, 1-B Infocity Road,, Bhubaneswar, Odisha | CJ31: 751024 | CK31: Plot No 5A, Chandaka Industrial Estate, 1-B Infocity Road,, Bhubaneswar, Odisha | CL31: Bhubaneswar | CM31: Odisha | CN31: 751024 | CO31: BBNS09089D | CP31: SECUREWAYS LOGISTICS PRIVATE LIMITED (STUDENT GALLERY) Plot No : N / 33 & 34, Chandka Industrial Estate, Near OTV office, Bhubaneswar - 751024, Odisha | CQ31: SAI INTERNATIONAL SCHOOL,PLOT NO-5A, Chandaka I.E, INFOCITY ROAD, PATIA, BHUBANESWAR, Odisha, 751024
A32: New School | B32: 153114 | C32: Scindia Kanya Vidyalaya | E32: Dropped | F32: 2024 | G32: 2024-03-23 00:00:00 | H32: Ei CARES | I32: Regular | J32: IN-2022001726 | K32: Approved By Logistic Team | L32: 509562 | M32: 509562 | N32: 0 | O32: 0 | Q32: 509562 | R32: 237 | S32: 2150 | T32: 0 | U32: 0 | W32: 0 | X32: Full Payment | Z32: 2024-03-23 00:00:00 | AA32: 2000-01-01 00:00:00 | AB32: 0 | AC32: 2000-01-01 00:00:00 | AD32: 0 | AE32: 2000-01-01 00:00:00 | AF32: 0 | AG32: 2000-01-01 00:00:00 | AH32: 0 | AI32: 50311 | AJ32: 2024-05-03 00:00:00 | AK32: 2024-05-03 00:00:00 | AL32: 509562 | AM32: 452801 | AN32: 6450 | AO32: 0.3857 | AP32: 0.3857 | AU32: 0 | AW32: 4 | AX32: MCQ | AY32: Printing By EI | AZ32: OMR | BB32: CBSE | BC32: Gwalior | BD32: Madhya Pradesh | BE32: North | BF32: MP/Chattisgarh | BG32: National Sales | BH32: 2024-05-01 00:00:00 | BI32: 2025-03-31 00:00:00 | BJ32: Regular School: Active school with student count and rate per student defined | BK32: 22028000021703208 | BL32: 51788000002732260 | BM32: zcrm_51788000255563643 | BN32: 2024-03-23 00:00:00 | BO32: sanjay.rai_eiindia1 | BP32: fagun.saraiya_eiindia1 | BQ32: sanjay.rai@ei.study | BR32: Sanjay rai | BS32: Sanjay Rai | BT32: Rohit Kumar | BU32: 2024-04-01 15:25:14 | BV32: Mrs. Garima Sandhu | BX32: viceprincipal@skvgwalior.org | BY32: +917512322137 | BZ32: skvgwl@gmail.com | CG32: 400000 | CH32: Moti Mahal Road, | CJ32: 474007 | CK32: Moti Mahal Road, | CL32: Gwalior | CM32: Madhya Pradesh | CN32: 474007 | CP32: Moti Mahal Road, | CQ32: Moti Mahal Road,
A33: Retention School | B33: 153271 | C33: Seth M. R. Jaipuria School | D33: =VLOOKUP(B33,'2025'!B:C,2,0) -> Shruti | F33: 2024 | G33: 2024-04-05 00:00:00, 2024-04-11 00:00:00 | H33: Ei ASSET,Ei CARES,Ei Mindspark, Ei Mindspark | I33: Regular | J33: IN-2022001866, IN-2022001896 | K33: Approved By Logistic Team | L33: 4094899 | M33: 4563309 | N33: 639695 | O33: 1942 | P33: 329 | Q33: 852926 | R33: 1942 | S33: 439 | T33: 2602278 | U33: 2128 | V33: 0, 1340 | W33: 0 | X33: Full Payment, Installments | Y33: 4 | Z33: 2024-04-02 00:00:00 | AA33: 2000-01-01 00:00:00, 2024-04-01 00:00:00 | AB33: 0, 1140827 | AC33: 2000-01-01 00:00:00, 2024-07-01 00:00:00 | AD33: 0, 1140827 | AE33: 2000-01-01 00:00:00, 2024-10-01 00:00:00 | AF33: 0, 1140827 | AG33: 2000-01-01 00:00:00, 2024-12-01 00:00:00 | AH33: 0, 1140827 | AI33: 0, 312494 | AJ33: 2023-11-23 00:00:00 | AK33: 2025-04-16 00:00:00 | AL33: 0, 4563308 | AM33: 0, 4432732 | AN33: -181918, 0 | AO33: 0.7804000000000001, 1 | AP33: 0.6304, 1 | AR33: 0.05 | AS33: 0.05 | AT33: 0.05 | AU33: 0, Winter Round | AV33: OMR | AW33: 0, 2 | AX33: MCQ | AZ33: Online | BA33: Online | BB33: CISCE | BC33: Lucknow | BD33: Uttar Pradesh | BE33: North | BF33: UP/Uttarakhand | BG33: National Sales | BH33: 2024-04-01 00:00:00 | BI33: 2025-03-31 00:00:00 | BJ33: Regular School: Active school with student count and rate per student defined | BK33: 22028000021940452, 22028000022033436 | BL33: 51788000002732261 | BM33: zcrm_51788000268018132, zcrm_51788000268224033 | BN33: 2024-04-05 00:00:00, 2024-04-11 00:00:00 | BO33: pooja.kapoor_eiindia1 | BP33: fagun.saraiya_eiindia1 | BQ33: pooja.kapoor@ei.study | BR33: Pooja kapoor | BS33: Pooja Kapoor | BU33: 2024-04-06 14:01:39, 2024-04-12 17:35:48 | BV33: Mrs. Promini Chopra | BW33: Principal | BX33: principal@jaipuria.com | BY33: +919838503807 | BZ33: principal@jaipuria.com | CA33: Mrs. Promini Chopra | CB33: principal@jaipuria.com | CC33: +919838503807 | CG33: 0 | CH33: Vineet Khand-1, Gomti Nagar, | CJ33: 226010 | CK33: Vineet Khand-1, Gomti Nagar, | CL33: Lucknow | CM33: Uttar Pradesh | CN33: 226010 | CO33: AAAT11375E | CP33: Vineet Khand-1, Gomti Nagar, | CQ33: Vineet Khand-1, Gomti Nagar,
A34: Retention School | B34: 1551815 | C34: The Shishukunj International School | D34: =VLOOKUP(B34,'2025'!B:C,2,0) -> Shruti | F34: 2024 | G34: 2024-05-27 00:00:00, 2024-05-29 00:00:00 | H34: Ei ASSET, Ei CARES | I34: Regular | J34: IN-2022002096, IN-2022002123 | K34: Approved By Logistic Team | L34: 4552699 | M34: 4552699 | N34: 1309649 | O34: 2015 | P34: 650 | Q34: 3243050 | R34: 1753 | S34: 1850 | T34: 0 | U34: 0 | W34: 0 | X34: Installments | Y34: 2, 4 | AA34: 2024-05-01 00:00:00, 2024-06-01 00:00:00 | AB34: 810763, 916754 | AC34: 2024-07-01 00:00:00, 2024-12-01 00:00:00 | AD34: 392895, 810763 | AE34: 2000-01-01 00:00:00, 2024-09-01 00:00:00 | AF34: 0, 810763 | AG34: 2000-01-01 00:00:00, 2024-11-01 00:00:00 | AH34: 0, 810763 | AI34: 32644, 58811 | AJ34: 2024-08-22 00:00:00 | AK34: 2024-12-30 00:00:00, 2025-02-20 00:00:00 | AL34: 1309649, 3243052 | AM34: 1290202, 3191030 | AN34: -39364, 19378 | AO34: 0.5667, 0.63 | AP34: 0.5667, 0.63 | AU34: 0, Winter Round | AV34: OMR | AW34: 0, 8 | AX34: MCQ | AY34: Printing By School | AZ34: OMR | BB34: CBSE | BC34: Indore | BD34: Madhya Pradesh | BE34: North | BF34: MP/Chattisgarh | BG34: National Sales | BH34: 2024-04-01 00:00:00 | BI34: 2025-03-31 00:00:00 | BJ34: Regular School: Active school with student count and rate per student defined | BK34: 22028000022674172, 22028000022708128 | BL34: 51788000002757138 | BM34: zcrm_51788000270055325, zcrm_51788000270055857 | BN34: 2024-05-27 00:00:00, 2024-05-29 00:00:00 | BO34: shruti.chauhan_ei | BP34: fagun.saraiya_eiindia1 | BQ34: shruti.chauhan@ei.study | BR34: Shruti chauhan | BS34: Shruti Chauhan | BU34: 2024-06-03 14:01:12, 2024-06-11 12:43:39 | BV34: Dr.(Mrs) Lalita Singh | BW34: Principal | BX34: lalita.singh@shishukunj.in | BY34: +918966001814 | BZ34: info@shishukunjindore.in | CA34: Dr.(Mrs) Lalita Singh | CB34: lalita.singh@shishukunj.in | CC34: +918966001814 | CD34: Sandhya Bhargava | CE34: sandhya.bhargava@shishukunj.in | CF34: +919713009585 | CG34: 0 | CH34: Jhalaria,Bypass Road | CJ34: 452016 | CK34: Jhalaria,Bypass Road | CL34: Indore | CM34: Madhya Pradesh | CN34: 452016 | CO34: BPLS23960G | CP34: Jhalaria,Bypass Road | CQ34: Jhalaria,Bypass Road
A35: 1-year School | B35: 1553466 | C35: ODM Sapphire Global School | D35: =VLOOKUP(B35,'2025'!B:C,2,0) -> Sumit Rana | F35: 2024 | G35: 2024-03-23 00:00:00 | H35: Ei CARES | I35: Regular | J35: IN-2022001725 | K35: Approved By Logistic Team | L35: 595566 | M35: 595566 | N35: 0 | O35: 0 | Q35: 595566 | R35: 318 | S35: 1873 | T35: 0 | U35: 0 | W35: 0 | X35: Installments | Y35: 4 | AA35: 2024-05-06 00:00:00 | AB35: 148892 | AC35: 2024-08-12 00:00:00 | AD35: 148892 | AE35: 2024-11-12 00:00:00 | AF35: 148892 | AG35: 2024-12-31 00:00:00 | AH35: 148892 | AI35: 2229 | AJ35: 2024-07-06 00:00:00 | AK35: 2025-07-04 00:00:00 | AL35: 595568 | AM35: 569296 | AN35: 24043 | AO35: 0.46490000000000004 | AP35: 0.46490000000000004 | AU35: 0 | AW35: 4 | AX35: MCQ + Subjective | AY35: Printing By EI | AZ35: OMR | BB35: CBSE | BC35: Ranchi | BD35: Jharkhand | BE35: East | BF35: Bihar/Jharkhand | BG35: National Sales | BH35: 2024-04-08 00:00:00 | BI35: 2025-03-31 00:00:00 | BJ35: Regular School: Active school with student count and rate per student defined | BK35: 22028000021707120 | BL35: 51788000002757153 | BM35: zcrm_51788000267470001 | BN35: 2024-03-23 00:00:00 | BO35: ratnabali.mukherjee_eiindia | BP35: mitul.patel_ei1 | BQ35: ratnabali.mukherjee@ei.study | BR35: Ratnabali mukherjee | BS35: Srikanta Kumar Rout | BU35: 2024-05-09 10:51:32 | BV35: Mr. Sourav Dutta | BX35: sourav.dutta@odmegroup.org | BY35: +919861177444 | BZ35: principal@sisranchi.com | CA35: Amt Singh | CB35: principal.osgs@odmegroup.org | CC35: +918406000223 | CD35: Kundan Singh | CE35: academic-admin-coordinator.osgs@odmegroup.org | CF35: +919504120032 | CG35: 346000 | CH35: 12Th Milestone Ranchi-Khunti Road, Hardag, Ranchi, Jharkhand | CJ35: 835221 | CK35: 12Th Milestone Ranchi-Khunti Road, Hardag, Ranchi, Jharkhand | CL35: Ranchi | CM35: Jharkhand | CN35: 835221 | CO35: BBNE01451C | CP35: Hardag, Ranchi, Jharkhand | CQ35: 12th Milestone Ranchi-Khunti Road, Hardag, Ranchi, Jharkhand
A36: New School | B36: 1558441 | C36: Emmanuel Mission High School | E36: Dropped | F36: 2024 | G36: 2024-05-19 00:00:00 | H36: Ei CARES | I36: Regular | J36: IN-2022002060 | K36: Approved By Logistic Team | L36: 626717 | M36: 626717 | N36: 0 | O36: 0 | Q36: 626717 | R36: 497 | S36: 1261 | T36: 0 | U36: 0 | W36: 0 | X36: Installments | Y36: 4 | AA36: 2024-05-20 00:00:00 | AB36: 156679 | AC36: 2024-07-20 00:00:00 | AD36: 156679 | AE36: 2024-09-20 00:00:00 | AF36: 156679 | AG36: 2024-12-20 00:00:00 | AH36: 156679 | AI36: 0 | AJ36: 2024-06-15 00:00:00 | AK36: 2025-03-25 00:00:00 | AL36: 626716 | AM36: 626717 | AN36: -1 | AO36: 0.515 | AP36: 0.515 | AU36: 0 | AW36: 4 | AX36: MCQ | AY36: Printing By EI | AZ36: OMR | BB36: CBSE | BC36: Siwan | BD36: Bihar | BE36: East | BF36: Bihar/Jharkhand | BG36: National Sales | BH36: 2024-04-01 00:00:00 | BI36: 2025-03-31 00:00:00 | BJ36: Regular School: Active school with student count and rate per student defined | BK36: 22028000022569756 | BL36: 51788000002757304 | BM36: zcrm_51788000269808509 | BN36: 2024-05-19 00:00:00 | BO36: satvinder.singh_ei | BP36: mitul.patel_ei1 | BQ36: satvinder.singh@ei.study | BR36: Satvinder singh | BS36: Satvinder Singh | BU36: 2024-05-28 10:21:58 | BV36: Prince Sam Abraham | BW36: School Owner | BX36: prince@emmanuel.co.in | BY36: +919900385257 | BZ36: info@emmanuel.co.in | CG36: 5000 | CH36: Emmanuel nagar, Hardia more, Chapra Siwan road | CJ36: 841226 | CK36: Emmanuel nagar, Hardia more, Chapra Siwan road | CL36: Siwan | CM36: Bihar | CN36: 841226 | CP36: Emmanuel Office, 1st Floor , M.M. Clinic, Ali Nagar Gate No 2, Near Alinagar Masjid, Anishabad | CQ36: Emmanuel Office, 1st Floor , M.M. Clinic, Ali Nagar Gate No 2, Near Alinagar Masjid, Anishabad,
A37: Retention School | B37: 1558722 | C37: Alma Mater School | D37: =VLOOKUP(B37,'2025'!B:C,2,0) -> Anushka | F37: 2024 | G37: 2024-05-25 00:00:00, 2024-05-28 00:00:00 | H37: Ei ASSET, Ei Mindspark | I37: Regular | J37: IN-2022002094, IN-2022002095, IN-2022002118, IN-2022002119 | K37: Approved By Logistic Team | L37: 678084 | M37: 768179 | N37: 177554 | O37: 161 | P37: 0, 1233 | Q37: 0 | R37: 0 | T37: 500530 | U37: 204 | V37: 0, 2720 | W37: 0 | X37: Full Payment, Installments | Y37: 4 | Z37: 2024-12-31 00:00:00 | AA37: 2000-01-01 00:00:00, 2024-06-10 00:00:00 | AB37: 0, 147656, 44389 | AC37: 2000-01-01 00:00:00, 2024-08-20 00:00:00, 2024-08-21 00:00:00 | AD37: 0, 147656, 44389 | AE37: 2000-01-01 00:00:00, 2024-10-21 00:00:00 | AF37: 0, 147656, 44389 | AG37: 2000-01-01 00:00:00, 2024-12-31 00:00:00 | AH37: 0, 147656, 44389 | AI37: 0, 12513, 3997 | AJ37: 2024-08-20 00:00:00 | AK37: 2025-05-15 00:00:00, 2025-07-16 00:00:00 | AL37: 0, 177556, 590624 | AM37: 0, 235970.53, 527568.88 | AN37: -62412, 0, 50542 | AO37: 0.499, 0.5542, 1 | AP37: 0.499, 0.5542, 1 | AU37: 0, Winter Round | AV37: OMR | AW37: 0 | AX37: MCQ | BA37: Online | BB37: IGCSE | BC37: Jodhpur | BD37: Rajasthan | BE37: North | BF37: Rajasthan | BG37: National Sales | BH37: 2024-06-01 00:00:00 | BI37: 2025-03-31 00:00:00, 2025-05-31 00:00:00 | BJ37: Regular School: Active school with student count and rate per student defined | BK37: 22028000022642908, 22028000022642956, 22028000022680344, 22028000022680376 | BL37: 51788000002757307 | BM37: zcrm_51788000270037029, zcrm_51788000270037166, zcrm_51788000270037303, zcrm_51788000270037437 | BN37: 2024-05-25 00:00:00, 2024-05-28 00:00:00 | BO37: anshul.nagpal_ei | BP37: fagun.saraiya_eiindia1 | BQ37: anshul.nagpal@ei.study | BR37: Anshul nagpal | BS37: Anushka Gupta | BU37: 2024-05-27 10:47:51, 2024-05-28 11:02:42, 2024-05-28 16:13:08, 2024-06-03 10:55:05 | BV37: Mr. Vaibhav Doshi | BW37: School Owner | BX37: vaibhav@almamater.education | BY37: +919983321066 | BZ37: connect@almamater.education | CD37: Ms. Arpita Mehta | CE37: arpita@almamater.education | CF37: +919784294701 | CG37: 0 | CH37: New Power House Rd, Section 7 Extension | CJ37: 342003 | CK37: New Power House Rd, Section 7 Extension | CL37: Jodhpur | CM37: Rajasthan | CN37: 342003 | CO37: JDHD05695E | CP37: New Power House Rd, Section 7 Extension | CQ37: New Power House Rd, Section 7 Extension
A38: Retention School | B38: 1581683 | C38: Fazlani L'Academie Globale | D38: =VLOOKUP(B38,'2025'!B:C,2,0) -> Hetal Parmar | F38: 2024 | G38: 2024-05-31 00:00:00, 2024-09-26 00:00:00 | H38: Ei ASSET, Ei Mindspark | I38: Regular | J38: IN-2022002133, IN-2022002494 | K38: Approved By Logistic Team | L38: 697553 | M38: 810630 | N38: 69349 | O38: 99 | P38: 700 | Q38: 0 | R38: 0 | T38: 628204 | U38: 218 | V38: 2882 | W38: 0 | X38: Full Payment, Installments | Y38: 2 | Z38: 2024-10-01 00:00:00 | AA38: 2000-01-01 00:00:00, 2024-06-30 00:00:00 | AB38: 0, 185320 | AC38: 2000-01-01 00:00:00, 2024-09-30 00:00:00 | AD38: 0, 555961 | AE38: 2000-01-01 00:00:00 | AF38: 0 | AG38: 2000-01-01 00:00:00 | AH38: 0 | AI38: 63108, 6935 | AJ38: 2024-07-17 00:00:00, 2024-10-09 00:00:00 | AK38: 2024-10-09 00:00:00, 2024-10-10 00:00:00 | AL38: 69349, 741281 | AM38: 62415, 681572 | AN38: -1, -3399 | AO38: 0.43329999999999996, 0.5329999999999999 | AP38: 0.43329999999999996, 0.5329999999999999 | AU38: 0, Winter Round | AV38: OMR | AW38: 0 | AX38: MCQ | BA38: Online | BB38: IGCSE | BC38: Mumbai | BD38: Maharashtra | BE38: West | BF38: Mumbai | BG38: National Sales | BH38: 2024-06-01 00:00:00, 2024-07-01 00:00:00 | BI38: 2025-05-31 00:00:00 | BJ38: Regular School: Active school with student count and rate per student defined | BK38: 22028000022750088, 22028000025100376 | BL38: 51788000002757733 | BM38: zcrm_51788000270126065, zcrm_51788000274789001 | BN38: 2024-05-31 00:00:00, 2024-09-26 00:00:00 | BO38: hetal.parmar_ei | BP38: hakim.kanchwala_eiindia1 | BQ38: hetal.parmar@ei.study | BR38: Hetal parmar | BS38: Hetal Parmar | BU38: 2024-06-17 12:51:55, 2024-10-03 16:15:43 | BV38: Mr. Maruf Shaikh, Ms. Mahera Goel | BW38: Other, Principal | BX38: maruf.shaikh@ei.study, principales@flag.org.in | BY38: +912223732730, +918160731829 | BZ38: principales@flag.org.in | CA38: Ms. Mahera Goel | CB38: principales@flag.org.in | CC38: +919930884618 | CD38: Ms.Fatima | CE38: fatima.shaikh@flag.org.in | CF38: +919987337110 | CG38: 0 | CH38: Opp. Wallace Fortuna Off Hancock Bridge, S.C. Marg, Mazagaon | CJ38: 400009 | CK38: Opp. Wallace Fortuna Off Hancock Bridge, S.C. Marg, Mazagaon | CL38: Mumbai | CM38: Maharashtra | CN38: 400009 | CO38: MUMS57362E | CP38: Opp. Wallace Fortuna Off Hancock Bridge, S.C. Marg, Mazagaon | CQ38: Opp. Wallace Fortuna Off Hancock Bridge, S.C. Marg, Mazagaon
A39: New School | B39: 158773 | C39: St Joseph'S Boys High School | D39: =VLOOKUP(B39,'2025'!B:C,2,0) -> Jasper Jessie | F39: 2024 | G39: 2024-06-26 00:00:00 | H39: Ei ASSET | I39: Regular | J39: IN-2022002277 | K39: Approved By Logistic Team | L39: 213587 | M39: 213587 | N39: 213587 | O39: 267 | P39: 800 | Q39: 0 | R39: 0 | T39: 0 | U39: 0 | W39: 0 | X39: Installments | Y39: 2 | AA39: 2024-07-15 00:00:00 | AB39: 106794 | AC39: 2024-07-31 00:00:00 | AD39: 106794 | AE39: 2000-01-01 00:00:00 | AF39: 0 | AG39: 2000-01-01 00:00:00 | AH39: 0 | AI39: 0 | AJ39: 2024-07-18 00:00:00 | AK39: 2025-02-11 00:00:00 | AL39: 213588 | AM39: 211450 | AN39: 2138 | AO39: 0.4667 | AP39: 0.4667 | AU39: Summer Round | AV39: OMR | AW39: 0 | AX39: MCQ | BB39: CISCE | BC39: Bengaluru | BD39: Karnataka | BE39: South | BF39: Karnataka/Kerala | BG39: National Sales | BH39: 2024-06-01 00:00:00 | BI39: 2025-04-10 00:00:00 | BJ39: Regular School: Active school with student count and rate per student defined | BK39: 22028000023171340 | BL39: 51788000002732290 | BM39: zcrm_51788000261777932 | BN39: 2024-06-26 00:00:00 | BO39: garima.jain_ei | BP39: mitul.patel_ei1 | BQ39: garima.jain@ei.study | BR39: Garima jain | BS39: Garima Jain | BU39: 2024-06-27 10:15:02 | BV39: Fr. Sunil Fernandes | BW39: Principal | BX39: principal@sjbhs.edu.in | BY39: +919740078338 | BZ39: principal@sjbhs.edu.in | CG39: 73000 | CH39: Museum Road, | CJ39: 560025 | CK39: Museum Road, | CL39: Bengaluru | CM39: Karnataka | CN39: 560025 | CO39: No | CP39: Museum Road, | CQ39: Museum Road,
A40: Retention School | B40: 159527 | C40: St. Mary^s School (ICSE), Mazagaon | D40: =VLOOKUP(B40,'2025'!B:C,2,0) -> Saloni Shah | F40: 2024 | G40: 2024-04-08 00:00:00 | H40: Ei CARES, Ei Mindspark | I40: Regular | J40: IN-2022001880, IN-2022001881 | K40: Approved By Logistic Team | L40: 1949410 | M40: 2046288 | N40: 0 | O40: 0 | Q40: 1411200 | R40: 576 | S40: 2450 | T40: 538210 | U40: 219 | V40: 2458 | W40: 0 | X40: Installments | Y40: 3 | AA40: 2024-06-24 00:00:00 | AB40: 215930, 479808 | AC40: 2024-09-24 00:00:00 | AD40: 209579, 465696 | AE40: 2024-12-24 00:00:00 | AF40: 209579, 465696 | AG40: 2000-01-01 00:00:00 | AH40: 0 | AI40: 142773, 60370 | AJ40: 2024-07-25 00:00:00 | AK40: 2025-02-15 00:00:00 | AL40: 1411200, 635088 | AM40: 1284963, 613140.9 | AN40: -16536, -38423 | AO40: 0.1945, 0.51 | AP40: 0.1945, 0.51 | AU40: 0 | AW40: 0, 8 | AX40: MCQ | AY40: Printing By EI | AZ40: OMR | BA40: Online | BB40: CISCE | BC40: Mumbai | BD40: Maharashtra | BE40: West | BF40: Mumbai | BG40: National Sales | BH40: 2024-04-01 00:00:00 | BI40: 2025-03-31 00:00:00 | BJ40: Regular School: Active school with student count and rate per student defined | BK40: 22028000021981044, 22028000021981088 | BL40: 51788000002732295 | BM40: zcrm_51788000268158001, zcrm_51788000268158132 | BN40: 2024-04-08 00:00:00 | BO40: saloni.shah_ei | BP40: hakim.kanchwala_eiindia1 | BQ40: saloni.shah@ei.study | BR40: Saloni shah | BS40: Shahista Shaikh | BU40: 2024-04-26 16:07:00, 2024-04-26 16:07:08 | BV40: Father Dr. Francis Swamy S.J. | BW40: Principal | BX40: principal@campionmumbai.org | BY40: +919920353009 | BZ40: contact@stmarysicse.com | CA40: Father Dr. Francis Swamy S.J. | CB40: principal@campionmumbai.org | CC40: +919920353009 | CD40: Mr.Elais | CE40: elias@stmarysicse.com | CG40: 0 | CH40: Sardar Balwant Singh Dhody Marg, Mazagaon, | CJ40: 400010 | CK40: Sardar Balwant Singh Dhody Marg, Mazagaon, | CL40: Mumbai | CM40: Maharashtra | CN40: 400010 | CO40: MUMS38726C | CP40: Sardar Balwant Singh Dhody Marg, Mazagaon, | CQ40: Sardar Balwant Singh Dhody Marg, Mazagaon,
A41: Retention School | B41: 1596332 | C41: Sri Shenbaga Vinayagar Matriculation Higher Secondary School | E41: Dropped | F41: 2024 | G41: 2024-06-04 00:00:00 | H41: Ei Mindspark | I41: Regular | J41: IN-2022002158 | K41: Approved By Logistic Team | L41: 503334 | M41: 593934 | N41: 0 | O41: 0 | Q41: 0 | R41: 0 | T41: 503334 | U41: 396 | V41: 1271 | W41: 0 | X41: Installments | Y41: 4 | AA41: 2024-06-05 00:00:00 | AB41: 148484 | AC41: 2024-09-01 00:00:00 | AD41: 148484 | AE41: 2024-12-01 00:00:00 | AF41: 148484 | AG41: 2024-12-31 00:00:00 | AH41: 148484 | AI41: 239708 | AJ41: 2024-09-26 00:00:00 | AK41: 2025-01-02 00:00:00 | AL41: 593936 | AM41: 364271 | AN41: -10043 | AO41: 0.5834 | AP41: 0.5834 | AU41: 0 | AW41: 0 | AX41: MCQ | BA41: Online | BB41: State Board | BC41: Sivakasi | BD41: Tamil Nadu | BE41: South | BF41: Tamil Nadu | BG41: National Sales | BH41: 2024-06-15 00:00:00 | BI41: 2025-03-31 00:00:00 | BJ41: Regular School: Active school with student count and rate per student defined | BK41: 22028000022797152 | BL41: 51788000002758076 | BM41: zcrm_51788000270277373 | BN41: 2024-06-04 00:00:00 | BO41: vineeth.v_ei | BP41: hakim.kanchwala_eiindia1 | BQ41: vineeth.v@ei.study | BR41: Vineeth v | BS41: Vineeth T V | BT41: Vineeth T V | BU41: 2024-06-05 12:22:40 | BV41: Mrs. Mrs. Surya Kumari M | BW41: Principal | BX41: ssvmschool@gmail.com | BY41: +919843564095 | BZ41: ssvmschool@gmail.com | CA41: Mrs. Mrs. Surya Kumari M | CB41: ssvmschool@gmail.com | CC41: +919843564095 | CG41: 0 | CH41: Vembakkottai Road, Teppam, | CJ41: 626123 | CK41: Vembakkottai Road, Teppam, | CL41: Sivakasi | CM41: Tamil Nadu | CN41: 626123 | CO41: MRIS08081D | CP41: Vembakkottai Road, Teppam, | CQ41: Vembakkottai Road, Teppam,
A42: Retention School | B42: 1616619 | C42: Vedavalli Vidyalaya Senior Secondary School | D42: =VLOOKUP(B42,'2025'!B:C,2,0) -> Vineeth T V | F42: 2024 | G42: 2024-06-20 00:00:00 | H42: Ei CARES | I42: Regular | J42: IN-2022002255 | K42: Approved By Logistic Team | L42: 757646 | M42: 757646 | N42: 0 | O42: 0 | Q42: 757646 | R42: 433 | S42: 1750 | T42: 0 | U42: 0 | W42: 0 | X42: Installments | Y42: 4 | AA42: 2024-06-25 00:00:00 | AB42: 189412 | AC42: 2024-09-30 00:00:00 | AD42: 189412 | AE42: 2024-12-10 00:00:00 | AF42: 189412 | AG42: 2024-12-31 00:00:00 | AH42: 189412 | AI42: 18941 | AJ42: 2024-07-19 00:00:00 | AK42: 2025-03-11 00:00:00 | AL42: 757648 | AM42: 686426 | AN42: 52281 | AO42: 0.7265999999999999 | AP42: 0.7265999999999999 | AU42: 0 | AW42: 8 | AX42: MCQ | AZ42: Online | BB42: CBSE | BC42: Walajapet | BD42: Tamil Nadu | BE42: South | BF42: Tamil Nadu | BG42: National Sales | BH42: 2024-06-05 00:00:00 | BI42: 2025-05-31 00:00:00 | BJ42: Regular School: Active school with student count and rate per student defined | BK42: 22028000023070400 | BL42: 51788000002758365 | BM42: zcrm_51788000270797001 | BN42: 2024-06-20 00:00:00 | BO42: vineeth.v_ei | BP42: hakim.kanchwala_eiindia1 | BQ42: vineeth.v@ei.study | BR42: Vineeth v | BS42: Vineeth T V | BU42: 2024-06-25 13:27:37 | BV42: Mr. Anantha Raman M K | BX42: anantharaman@vedavallividyalaya.org | BY42: +914172246013 | BZ42: anantharaman@vedavallividyalaya.org | CG42: 0 | CH42: Chennai Mumbai Trunk Road, Bagaveli, Chennasamudram, T K Thangal Post, Walajapet | CJ42: 632513 | CK42: Chennai Mumbai Trunk Road, Bagaveli, Chennasamudram, T K Thangal Post, Walajapet | CL42: Walajapet | CM42: Tamil Nadu | CN42: 632513 | CO42: CHET03629D | CP42: Chennai Mumbai Trunk Road, Bagaveli, Chennasamudram, T K Thangal Post, Walajapet | CQ42: Chennai Mumbai Trunk Road, Bagaveli, Chennasamudram, T K Thangal Post, Walajapet
A43: New School | B43: 1644219 | C43: ASPAM Scottish School | D43: =VLOOKUP(B43,'2025'!B:C,2,0) -> Sudhi | F43: 2024 | G43: 2024-04-12 00:00:00 | H43: Ei Mindspark | I43: Regular | J43: IN-2022001904 | K43: Approved By Logistic Team | L43: 349848 | M43: 412821 | N43: 0 | O43: 0 | Q43: 0 | R43: 0 | T43: 349848 | U43: 172 | V43: 2034 | W43: 0 | X43: Installments | Y43: 4 | AA43: 2024-04-22 00:00:00 | AB43: 103205 | AC43: 2024-07-01 00:00:00 | AD43: 103205 | AE43: 2024-09-01 00:00:00 | AF43: 103205 | AG43: 2024-12-01 00:00:00 | AH43: 103205 | AI43: 3508 | AJ43: 2024-07-23 00:00:00 | AK43: 2025-04-17 00:00:00 | AL43: 412820 | AM43: 411722 | AN43: -2410 | AO43: 0.6 | AP43: 0.6 | AU43: 0 | AW43: 0 | AX43: MCQ | BA43: Online | BB43: CBSE | BC43: Noida | BD43: Uttar Pradesh | BE43: North | BF43: NCR | BG43: National Sales | BH43: 2024-07-01 00:00:00 | BI43: 2025-06-30 00:00:00 | BJ43: Regular School: Active school with student count and rate per student defined | BK43: 22028000022065116 | BL43: 51788000002758926 | BM43: zcrm_51788000268383052 | BN43: 2024-04-12 00:00:00 | BO43: puneet.khurana_ei | BP43: fagun.saraiya_eiindia1 | BQ43: puneet.khurana@ei.study | BR43: Puneet khurana | BS43: Bhavishya Bansal | BU43: 2024-05-22 14:12:15 | BV43: Mrs. Meenakshi Zarabi | BW43: Principal | BX43: principal@aspamscottish.com | BY43: +919654676964 | BZ43: info@aspamscottish.com | CA43: Mrs. Meenakshi Zarabi | CB43: principal@aspamscottish.com | CC43: +919654676964 | CG43: 99000 | CH43: A – 43 Near SBI Bank, Sector 62, | CJ43: 201301 | CK43: A – 43 Near SBI Bank, Sector 62, | CL43: Noida | CM43: Uttar Pradesh | CN43: 201301 | CO43: DELM12222A | CP43: A – 43 Near SBI Bank, Sector 62, | CQ43: A – 43 Near SBI Bank, Sector 62,
A44: Retention School | B44: 1649456 | C44: Shri Kanwartara Senior Secondary School | D44: =VLOOKUP(B44,'2025'!B:C,2,0) -> Shruti | F44: 2024 | G44: 2024-02-22 00:00:00 | H44: Ei CARES | I44: Regular | J44: IN-2022001544 | K44: Approved By Logistic Team | L44: 716365 | M44: 716365 | N44: 0 | O44: 0 | Q44: 716365 | R44: 573 | S44: 1250 | T44: 0 | U44: 0 | W44: 0 | X44: Installments | Y44: 4 | AA44: 2024-06-01 00:00:00 | AB44: 179091 | AC44: 2024-09-02 00:00:00 | AD44: 179091 | AE44: 2024-11-30 00:00:00 | AF44: 179091 | AG44: 2024-12-31 00:00:00 | AH44: 179091 | AI44: 17500 | AJ44: 2024-06-26 00:00:00 | AK44: 2025-10-31 00:00:00 | AL44: 716364 | AM44: 759273 | AN44: -60409 | AO44: 0.6428 | AP44: 0.5928 | AT44: 0.05 | AU44: 0 | AW44: 4 | AX44: MCQ | AY44: Printing By EI | AZ44: OMR | BB44: CBSE | BC44: Mandleshwar | BD44: Madhya Pradesh | BE44: North | BF44: MP/Chattisgarh | BG44: National Sales | BH44: 2024-06-01 00:00:00 | BI44: 2025-03-31 00:00:00 | BJ44: Regular School: Active school with student count and rate per student defined | BK44: 22028000021180084 | BL44: 51788000002758976 | BM44: zcrm_51788000265621367 | BN44: 2024-02-22 00:00:00 | BO44: shruti.chauhan_ei | BP44: sourabh.mehta_eiindia | BQ44: shruti.chauhan@ei.study | BR44: Shruti chauhan | BS44: Shruti Chauhan | BU44: 2024-02-22 18:08:57 | BV44: Mr. Yogesh Joshi | BW44: Principal | BX44: j.v.yogesh@gmail.com | BY44: +919669696243 | BZ44: shrikanwartaraschool@yahoo.com | CA44: Mr. Yogesh Joshi | CB44: j.v.yogesh@gmail.com | CC44: +919669696243 | CD44: Mahaveer | CE44: j.v.yogesh@gmail.com | CF44: +919981532964 | CG44: 0 | CH44: Shrinagar Colony, Mandleshwar, Dist. Khargone | CJ44: 451221 | CK44: Shrinagar Colony, Mandleshwar, Dist. Khargone | CL44: Mandleshwar | CM44: Madhya Pradesh | CN44: 451221 | CP44: Shrinagar Colony, Mandleshwar, Dist. Khargone | CQ44: Shrinagar Colony, Mandleshwar, Dist. Khargone
A45: Retention School | B45: 165035 | C45: The Scindia School, Fort | D45: =VLOOKUP(B45,'2025'!B:C,2,0) -> Rohit | F45: 2024 | G45: 2024-07-29 00:00:00 | H45: Ei Mindspark | I45: Regular | J45: IN-2022002389 | K45: Approved By Logistic Team | L45: 546068 | M45: 644360 | N45: 0 | O45: 0 | Q45: 0 | R45: 0 | T45: 546068 | U45: 190 | V45: 2874 | W45: 0 | X45: Full Payment | Z45: 2024-08-01 00:00:00 | AA45: 2000-01-01 00:00:00 | AB45: 0 | AC45: 2000-01-01 00:00:00 | AD45: 0 | AE45: 2000-01-01 00:00:00 | AF45: 0 | AG45: 2000-01-01 00:00:00 | AH45: 0 | AI45: 53457 | AJ45: 2024-09-27 00:00:00 | AK45: 2024-09-27 00:00:00 | AL45: 644360 | AM45: 577337 | AN45: 13566 | AO45: 0.057999999999999996 | AP45: 0.057999999999999996 | AU45: 0 | AW45: 0 | AX45: MCQ | BA45: Online | BB45: CBSE | BC45: Gwalior | BD45: Madhya Pradesh | BE45: North | BF45: MP/Chattisgarh | BG45: National Sales | BH45: 2024-07-01 00:00:00 | BI45: 2025-03-31 00:00:00 | BJ45: Regular School: Active school with student count and rate per student defined | BK45: 22028000023795676 | BL45: 51788000002732431 | BM45: zcrm_51788000272308003 | BN45: 2024-07-29 00:00:00 | BO45: shruti.chauhan_ei | BP45: fagun.saraiya_eiindia1 | BQ45: shruti.chauhan@ei.study | BR45: Shruti chauhan | BS45: Rohit Kumar | BU45: 2024-08-13 17:46:23 | BV45: Dhirendra Srivastava | BW45: Other | BX45: SaraswatiHigerSecondarySchool-1120898@gmail.com | BY45: +919407566952 | BZ45: office@scindia.edu | CG45: 0 | CH45: Fort, Vinay Nagar, | CJ45: 474008 | CK45: Fort, Vinay Nagar, | CL45: Gwalior | CM45: Madhya Pradesh | CN45: 474008 | CP45: Fort, Vinay Nagar, | CQ45: Fort, Vinay Nagar,
A46: Retention School | B46: 1650530 | C46: Paramount Academy, Kasrawad | D46: =VLOOKUP(B46,'2025'!B:C,2,0) -> Shruti | F46: 2024 | G46: 2024-02-19 00:00:00 | H46: Ei CARES | I46: Regular | J46: IN-2022001519 | K46: Approved By Logistic Team | L46: 246543 | M46: 246543 | N46: 0 | O46: 0 | Q46: 246543 | R46: 145 | S46: 1700 | T46: 0 | U46: 0 | W46: 0 | X46: Installments | Y46: 4 | AA46: 2024-03-20 00:00:00 | AB46: 61636 | AC46: 2024-07-15 00:00:00 | AD46: 61636 | AE46: 2024-09-15 00:00:00 | AF46: 61636 | AG46: 2024-12-15 00:00:00 | AH46: 61636 | AI46: 0 | AJ46: 2024-06-21 00:00:00 | AK46: 2025-01-11 00:00:00 | AL46: 246544 | AM46: 210367 | AN46: 36177 | AO46: 0.5142 | AP46: 0.4642 | AT46: 0.05 | AU46: 0 | AW46: 4 | AX46: MCQ | AY46: Printing By EI | AZ46: OMR | BB46: CBSE | BC46: Khargaon | BD46: Madhya Pradesh | BE46: North | BF46: MP/Chattisgarh | BG46: National Sales | BH46: 2024-04-01 00:00:00 | BI46: 2025-03-31 00:00:00 | BJ46: Regular School: Active school with student count and rate per student defined | BK46: 22028000021131380 | BL46: 51788000002759089 | BM46: zcrm_51788000265336687 | BN46: 2024-02-19 00:00:00 | BO46: shruti.chauhan_ei | BP46: fagun.saraiya_eiindia1 | BQ46: shruti.chauhan@ei.study | BR46: Shruti chauhan | BS46: Shruti Chauhan | BU46: 2024-02-21 10:47:55 | BV46: Akhilesh Patidar | BW46: Principal | BX46: akhilesh.patidar13134@gmail.com | BY46: +919926013134 | BZ46: paramountkasrawad@gmail.com | CA46: Akhilesh Patidar | CB46: akhilesh.patidar13134@gmail.com | CC46: +919926013134 | CG46: 0 | CH46: Khargaon Road Kasrawad | CJ46: 451228 | CK46: Khargaon Road Kasrawad | CL46: Khargaon | CM46: Madhya Pradesh | CN46: 451228 | CO46: BPLS11215B | CP46: Khargaon Road Kasrawad | CQ46: Khargaon Road Kasrawad
A47: Retention School | B47: 168210 | C47: Vivekananda Mission School | D47: =VLOOKUP(B47,'2025'!B:C,2,0) -> Gargi Ghosh | F47: 2024 | G47: 2024-06-10 00:00:00 | H47: Ei ASSET, Ei CARES | I47: Regular | J47: IN-2022002188, IN-2022002189 | K47: Approved By Logistic Team | L47: 2421922 | M47: 2421922 | N47: 184200 | O47: 307 | P47: 600 | Q47: 2237722 | R47: 1963 | S47: 1140 | T47: 0 | U47: 0 | W47: 0 | X47: Full Payment, Installments | Y47: 4 | Z47: 2024-06-28 00:00:00 | AA47: 2000-01-01 00:00:00, 2024-06-28 00:00:00 | AB47: 0, 559431 | AC47: 2000-01-01 00:00:00, 2024-09-30 00:00:00 | AD47: 0, 559431 | AE47: 2000-01-01 00:00:00, 2024-11-30 00:00:00 | AF47: 0, 559431 | AG47: 2000-01-01 00:00:00, 2024-12-31 00:00:00 | AH47: 0, 559431 | AI47: 3684, 44755 | AJ47: 2024-08-06 00:00:00 | AK47: 2024-08-06 00:00:00, 2025-03-28 00:00:00 | AL47: 184200, 2237724 | AM47: 180516, 2192965.9699999997 | AN47: 0, 3 | AO47: 0.6, 0.6743000000000001 | AP47: 0.6, 0.6743000000000001 | AU47: 0, Summer Round | AV47: Online | AW47: 0, 4 | AX47: MCQ | AY47: Printing By EI | AZ47: OMR | BB47: CISCE | BC47: Kolkata | BD47: West Bengal | BE47: East | BF47: West Bengal | BG47: National Sales | BH47: 2024-06-10 00:00:00 | BI47: 2025-03-31 00:00:00 | BJ47: Regular School: Active school with student count and rate per student defined | BK47: 22028000022883348, 22028000022883408 | BL47: 51788000002732448 | BM47: zcrm_51788000270481155, zcrm_51788000270481292 | BN47: 2024-06-10 00:00:00 | BO47: lopamudra.das_eiindia1 | BP47: mitul.patel_ei1 | BQ47: lopamudra.das@ei.study | BR47: Lopamudra das | BS47: Lopamudra Das | BU47: 2024-06-10 14:53:57, 2024-06-10 15:00:44 | BV47: Arnab Chandra | BW47: School Owner | BX47: arnab.chandra@vms.edu.in | BY47: +919903263000 | BZ47: principal@vms.edu.in | CG47: 0 | CH47: Vivek Ville | CJ47: 700104 | CK47: Vivek Ville | CL47: Kolkata | CM47: West Bengal | CN47: 700104 | CO47: CALV02119F | CP47: Vivek Ville | CQ47: Vivek Ville
A48: Retention School | B48: 169040 | C48: Young Horizons School | D48: =VLOOKUP(B48,'2025'!B:C,2,0) -> Lopa | F48: 2024 | G48: 2024-05-24 00:00:00 | H48: Ei CARES | I48: Regular | J48: IN-2022002084, IN-2022002085 | K48: Approved By Logistic Team | L48: 698078 | M48: 698078 | N48: 0 | O48: 0 | Q48: 698078 | R48: 461 | S48: 1351, 1648 | T48: 0 | U48: 0 | W48: 0 | X48: Installments | Y48: 4 | AA48: 2024-05-27 00:00:00 | AB48: 104268, 70252 | AC48: 2024-08-27 00:00:00 | AD48: 104268, 70252 | AE48: 2024-10-28 00:00:00 | AF48: 104268, 70252 | AG48: 2024-12-31 00:00:00 | AH48: 104268, 70252 | AI48: 1405, 2085 | AJ48: 2024-04-29 00:00:00, 2024-06-28 00:00:00 | AK48: 2025-03-25 00:00:00 | AL48: 281008, 417072 | AM48: 279732, 493911 | AN48: -129, -78924 | AO48: 0.529, 0.614 | AP48: 0.529, 0.614 | AU48: 0 | AW48: 4 | AX48: MCQ + Subjective | AY48: Printing By EI | AZ48: OMR | BB48: CISCE | BC48: Kolkata | BD48: West Bengal | BE48: East | BF48: West Bengal | BG48: National Sales | BH48: 2024-04-01 00:00:00 | BI48: 2025-03-31 00:00:00 | BJ48: Regular School: Active school with student count and rate per student defined | BK48: 22028000022641080, 22028000022641144 | BL48: 51788000002732451 | BM48: zcrm_51788000269950001, zcrm_51788000269950138 | BN48: 2024-05-24 00:00:00 | BO48: lopamudra.das_eiindia1 | BP48: maruf.shaikh1, megha.m_ei | BQ48: lopamudra.das@ei.study | BR48: Lopamudra das | BS48: Lopamudra Das | BU48: 2024-05-30 10:07:21, 2024-05-30 10:08:05 | BV48: Ms. Sarmistha Sen | BW48: Principal | BX48: official@younghorizonsschool.com | BY48: +919830494565 | BZ48: official@younghorizonsschool.com | CG48: 30000 | CH48: 220, Barakhola, Kalikapur, E.M. Bypass | CJ48: 700099 | CK48: 220, Barakhola, Kalikapur, E.M. Bypass | CL48: Kolkata | CM48: West Bengal | CN48: 700099 | CP48: 220, Barakhola, Kalikapur, E.M. Bypass | CQ48: 220, Barakhola, Kalikapur, E.M. Bypass
A49: Retention School | B49: 17080 | C49: EDUADVAITA (C/O KAMALANIKETAN MONTESSORI SCHOOL) | D49: =VLOOKUP(B49,'2025'!B:C,2,0) -> Vineeth T V | F49: 2024 | G49: 2024-08-07 00:00:00 | H49: Ei Mindspark | I49: Regular | J49: IN-2022002408 | K49: Approved By Logistic Team | L49: 2266334 | M49: 2674274 | N49: 0 | O49: 0 | Q49: 0 | R49: 0 | T49: 2266334 | U49: 1494 | V49: 1517 | W49: 0 | X49: Installments | Y49: 2 | AA49: 2024-08-12 00:00:00 | AB49: 1337137 | AC49: 2024-12-31 00:00:00 | AD49: 1337137 | AE49: 2000-01-01 00:00:00 | AF49: 0 | AG49: 2000-01-01 00:00:00 | AH49: 0 | AI49: 53141 | AJ49: 2024-06-21 00:00:00 | AK49: 2025-06-20 00:00:00 | AL49: 2674274 | AM49: 3058214 | AN49: -437081 | AO49: 0.7514 | AP49: 0.7514 | AU49: 0 | AW49: 0 | AX49: MCQ | BA49: Online | BB49: CBSE | BC49: Trichy | BD49: Tamil Nadu | BE49: South | BF49: Tamil Nadu | BG49: National Sales | BH49: 2024-06-01 00:00:00 | BI49: 2025-05-31 00:00:00 | BJ49: Regular School: Active school with student count and rate per student defined | BK49: 22028000023970692 | BL49: 51788000002728636 | BM49: zcrm_51788000272583027 | BN49: 2024-08-07 00:00:00 | BO49: vineeth.v_ei | BP49: hakim.kanchwala_eiindia1 | BQ49: vineeth.v@ei.study | BR49: Vineeth v | BS49: Vineeth T V | BU49: 2024-09-23 10:22:42 | BV49: Mr. Sathiamoorthy Sir | BW49: Other | BX49: sathia_55@yahoo.com | BY49: +917373791041 | BZ49: office@kamalaniketan.com | CD49: Bhuwaneswari G | CE49: bhuvaneswari.g@kamalaniketan.com | CF49: +917373791037 | CG49: 0 | CH49: maris avenue, collector office road | CJ49: 620001 | CK49: maris avenue, collector office road | CL49: Trichy | CM49: Tamil Nadu | CN49: 620001 | CO49: CHEE07743B | CP49: maris avenue, collector office road | CQ49: maris avenue, collector office road
A50: New School | B50: 1720050 | C50: S H N V Matriculation School | F50: 2024 | G50: 2024-04-02 00:00:00 | H50: Ei Mindspark | I50: Regular | J50: IN-2022001814 | K50: Approved By Logistic Team | L50: 833869 | M50: 983965 | N50: 0 | O50: 0 | Q50: 0 | R50: 0 | T50: 833869 | U50: 755 | V50: 1104 | W50: 0 | X50: Installments | Y50: 4 | AA50: 2024-05-24 00:00:00 | AB50: 245991 | AC50: 2024-07-25 00:00:00 | AD50: 245991 | AE50: 2024-11-25 00:00:00 | AF50: 245991 | AG50: 2024-12-25 00:00:00 | AH50: 245991 | AI50: 20847 | AJ50: 2024-06-19 00:00:00 | AK50: 2024-12-30 00:00:00 | AL50: 983964 | AM50: 923540 | AN50: 39577 | AO50: 0.638 | AP50: 0.638 | AU50: 0 | AW50: 0 | AX50: MCQ | BA50: Online | BB50: State Board | BC50: Sivakasi | BD50: Tamil Nadu | BE50: South | BF50: Tamil Nadu | BG50: National Sales | BH50: 2024-06-01 00:00:00 | BI50: 2025-05-31 00:00:00 | BJ50: Regular School: Active school with student count and rate per student defined | BK50: 22028000021885272 | BL50: 51788000002760362 | BM50: zcrm_51788000267834796 | BN50: 2024-04-02 00:00:00 | BO50: clement.navamani_ei | BP50: hakim.kanchwala_eiindia1 | BQ50: clement.navamani@ei.study | BR50: Clement navamani | BS50: Clement John Navamani V Navamani | BU50: 2024-04-03 23:40:12 | BV50: Mr Mathavan | BW50: School Owner | BX50: shnvmathss@gmail.com | BY50: +919442324292 | BZ50: SHNVMatriculationHigherSecondarySchool_1720050@gmail.com | CD50: Manjula | CE50: shnvmthss@gmail.com | CF50: +919385820241 | CG50: 40000 | CH50: No. 10 A, Chairman Shanmugam Salai, | CJ50: 626123 | CK50: No. 10 A, Chairman Shanmugam Salai, | CL50: Sivakasi | CM50: Tamil Nadu | CN50: 626123 | CO50: MRIT00822D | CP50: No. 10 A, Chairman Shanmugam Salai, | CQ50: No. 10 A, Chairman Shanmugam Salai,
A51: Retention School | B51: 1722766 | C51: Harvest Public School | F51: 2024 | G51: 2024-04-22 00:00:00 | H51: Ei CARES | I51: Regular | J51: IN-2022001952 | K51: Approved By Logistic Team | L51: 859818 | M51: 859818 | N51: 0 | O51: 0 | Q51: 859818 | R51: 600 | S51: 1433 | T51: 0 | U51: 0 | W51: 0 | X51: Installments | Y51: 4 | AA51: 2024-05-15 00:00:00 | AB51: 214955 | AC51: 2024-08-15 00:00:00 | AD51: 214955 | AE51: 2024-10-15 00:00:00 | AF51: 214955 | AG51: 2024-12-15 00:00:00 | AH51: 214955 | AI51: 0 | AJ51: 2024-09-04 00:00:00 | AK51: 2025-04-23 00:00:00 | AL51: 859820 | AM51: 888468 | AN51: -28648 | AO51: 0.5779 | AP51: 0.5779 | AU51: 0 | AW51: 4 | AX51: MCQ | AY51: Printing By School | AZ51: OMR | BB51: CBSE | BC51: Khammam | BD51: Telangana | BE51: South | BF51: AP/Telangana | BG51: National Sales | BH51: 2024-06-01 00:00:00 | BI51: 2025-03-31 00:00:00 | BJ51: Regular School: Active school with student count and rate per student defined | BK51: 22028000022189576 | BL51: 51788000002760389 | BM51: zcrm_51788000268704370 | BN51: 2024-04-22 00:00:00 | BO51: chaitanya.kolluri_ei | BP51: sourabh.mehta_eiindia | BQ51: chaitanya.kolluri@ei.study | BR51: Chaitanya kolluri | BS51: Jasper Jessie | BU51: 2024-04-26 13:17:57 | BV51: R Parvathi Reddy | BW51: Other | BX51: nagarajuharvest@gmail.com | BY51: +917981396926 | BZ51: harvestkhammam@gmail.com | CA51: R Parvathi Reddy | CB51: ramasahayamparvathi@gmail.com | CC51: +919848503589 | CD51: Mr. K Nagaraju | CE51: nagarajuharvest@gmail.com | CF51: +917981396926 | CG51: 0 | CH51: 5-7-200/11, Near Mamata General Hospital, Pakabanda Bazar, | CJ51: 507002 | CK51: 5-7-200/11, Near Mamata General Hospital, Pakabanda Bazar, | CL51: Khammam | CM51: Telangana | CN51: 507002 | CP51: 5-7-200/11, Near Mamata General Hospital, Pakabanda Bazar, | CQ51: 5-7-200/11, Near Mamata General Hospital, Pakabanda Bazar,
A52: Retention School | B52: 173767 | C52: Modern High School For Girls | D52: =VLOOKUP(B52,'2025'!B:C,2,0) -> Lopamudra Das | F52: 2024 | G52: 2024-05-07 00:00:00 | H52: Ei Mindspark | I52: Regular | J52: IN-2022002026 | K52: Approved By Logistic Team | L52: 1951776 | M52: 2303096 | N52: 0 | O52: 0 | Q52: 0 | R52: 0 | T52: 1951776 | U52: 811 | V52: 2407 | W52: 0 | X52: Installments | Y52: 4 | AA52: 2024-05-09 00:00:00 | AB52: 575774 | AC52: 2024-06-25 00:00:00 | AD52: 575774 | AE52: 2024-09-25 00:00:00 | AF52: 575774 | AG52: 2024-12-31 00:00:00 | AH52: 575774 | AI52: 178913 | AJ52: 2024-05-22 00:00:00 | AK52: 2025-02-06 00:00:00 | AL52: 2303096 | AM52: 1932261 | AN52: 191922 | AO52: 0.2112 | AP52: 0.2112 | AU52: 0 | AW52: 0 | AX52: MCQ | BA52: Online | BB52: CISCE | BC52: Kolkata | BD52: West Bengal | BE52: East | BF52: West Bengal | BG52: National Sales | BH52: 2024-05-09 00:00:00 | BI52: 2025-03-31 00:00:00 | BJ52: Regular School: Active school with student count and rate per student defined | BK52: 22028000022385968 | BL52: 51788000002732487 | BM52: zcrm_51788000269357003 | BN52: 2024-05-07 00:00:00 | BO52: lopamudra.das_eiindia1 | BP52: mitul.patel_ei1 | BQ52: lopamudra.das@ei.study | BR52: Lopamudra das | BS52: Lopamudra Das | BU52: 2024-05-09 15:46:56 | BV52: Mrs. Damayanti Mukherjee | BW52: Admin | BX52: principal@mhsforgirls.edu.in | BY52: +913322875326 | BZ52: principal@mhsforgirls.edu.in | CG52: 0 | CH52: 78, Syed Amir Ali Ave, Beck Bagan, Ballygunge | CJ52: 700019 | CK52: 78, Syed Amir Ali Ave, Beck Bagan, Ballygunge | CL52: Kolkata | CM52: West Bengal | CN52: 700019 | CO52: CALM04380F | CP52: Beck Bagan, Ballygunge | CQ52: 78, Syed Amir Ali Ave, Beck Bagan, Ballygunge
A53: New School | B53: 174661 | C53: The Bombay International School | E53: Dropped | F53: 2024 | G53: 2024-01-06 00:00:00, 2024-02-01 00:00:00 | H53: Ei ASSET, Ei Mindspark | I53: Regular | J53: IN-2022001384, IN-2022001457 | K53: Approved By Logistic Team | L53: 162366 | M53: 183233 | N53: 46440 | O53: 43 | P53: 1080 | Q53: 0 | R53: 0 | T53: 115926 | U53: 38 | V53: 3051 | W53: 0 | X53: Full Payment, Installments | Y53: 2 | Z53: 2024-01-10 00:00:00 | AA53: 2000-01-01 00:00:00, 2024-02-08 00:00:00 | AB53: 0, 41038 | AC53: 2000-01-01 00:00:00, 2024-10-01 00:00:00 | AD53: 0, 95755 | AE53: 2000-01-01 00:00:00 | AF53: 0 | AG53: 2000-01-01 00:00:00 | AH53: 0 | AI53: 12203, 4104 | AJ53: 2024-01-20 00:00:00, 2024-04-15 00:00:00 | AK53: 2024-01-20 00:00:00, 2024-10-11 00:00:00 | AL53: 136793, 46440 | AM53: 131790, 36936 | AN53: -7200, 5400 | AO53: 0.0001, 0.1 | AP53: 0.0001, 0.1 | AU53: 0, Winter Round | AV53: Online | AW53: 0 | AX53: MCQ | BA53: Online | BB53: IGSCE | BC53: Mumbai | BD53: Maharashtra | BE53: West | BF53: Mumbai | BG53: National Sales | BH53: 2024-01-01 00:00:00, 2024-07-01 00:00:00 | BI53: 2024-08-29 00:00:00, 2025-06-30 00:00:00 | BJ53: Regular School: Active school with student count and rate per student defined | BK53: 22028000020542216, 22028000020886208 | BL53: 51788000002732495 | BM53: zcrm_51788000263014086, zcrm_51788000264456151 | BN53: 2024-01-06 00:00:00, 2024-02-01 00:00:00 | BO53: manjeetsingh.ladhad | BP53: sourabh.mehta_eiindia | BQ53: manjeetsingh.ladhad@ei.study | BR53: Manjeetsingh ladhad | BS53: Manjeetsingh Ladhad | BT53: Hetal Parmar | BU53: 2024-01-10 17:38:31, 2024-02-16 11:24:19 | BV53: Cyrus Vakil, Mr. Cyrus Vakil | BW53: Principal | BX53: cyrus.vakil@bis.edu.in | BY53: +912223648206, +919820009512 | BZ53: cyrus.vakil@bis.edu.in | CA53: Cyrus Vakil | CB53: cyrus.vakil@bis.edu.in | CC53: +912236482206 | CD53: Rupal Thaker | CE53: rupal.thaker@bis.edu.in | CF53: +919930933228 | CG53: 17500 | CH53: Babulnath 2nd Cross Road,, Gilbert Building, Babulnath 2nd Cross Road, | CJ53: 400007 | CK53: Gilbert Building, Babulnath 2nd Cross Road, | CL53: Mumbai | CM53: Maharashtra | CN53: 400007 | CP53: Babulnath 2nd Cross Road, | CQ53: Gilbert Building, Babulnath 2nd Cross Road,
A54: New School | B54: 174867 | C54: Vidya Mandir Senior Secondary School | D54: =VLOOKUP(B54,'2025'!B:C,2,0) -> Vineeth T V | F54: 2024 | G54: 2024-02-14 00:00:00 | H54: Ei ASSET | I54: Regular | J54: IN-2022001493 | K54: Approved By Logistic Team | L54: 832200 | M54: 832200 | N54: 832200 | O54: 760 | P54: 1095 | Q54: 0 | R54: 0 | T54: 0 | U54: 0 | W54: 0 | X54: Installments | Y54: 2 | AA54: 2024-06-03 00:00:00 | AB54: 416100 | AC54: 2024-08-30 00:00:00 | AD54: 416100 | AE54: 2000-01-01 00:00:00 | AF54: 0 | AG54: 2000-01-01 00:00:00 | AH54: 0 | AI54: 83220 | AJ54: 2024-06-27 00:00:00 | AK54: 2024-09-24 00:00:00 | AL54: 832200 | AM54: 748980 | AN54: 0 | AO54: 0.27 | AP54: 0.27 | AU54: Summer Round | AV54: OMR | AW54: 0 | AX54: MCQ | BB54: CBSE | BC54: Chennai | BD54: Tamil Nadu | BE54: South | BF54: Tamil Nadu | BG54: National Sales | BH54: 2024-04-01 00:00:00 | BI54: 2025-03-31 00:00:00 | BJ54: Regular School: Active school with student count and rate per student defined | BK54: 22028000021062284 | BL54: 51788000002732497 | BM54: zcrm_51788000257680504 | BN54: 2024-02-14 00:00:00 | BO54: sriram.subramaniam_ei | BP54: hakim.kanchwala_eiindia1 | BQ54: sriram.subramaniam@ei.study | BR54: Sriram subramaniam | BS54: Makara Jyothi | BU54: 2024-02-24 13:16:37 | BV54: Ms. Mala Kanchana | BW54: Other | BX54: vidyamandirchennai@gmail.com | BY54: +919884083448 | BZ54: vidyamandirchennai@gmail.com | CA54: Kanchana (VP) | CB54: vidyamandirchennai@gmail.com | CC54: +919884083448 | CD54: Kanchana Mala | CE54: vidyamandirchennai@gmail.com | CF54: +919884083448 | CG54: 85000 | CH54: 124, Royapettah High Rd, Vinayagar Kovil, Mylapore, Chennai, Tamil Nadu 600004 | CJ54: 600004 | CK54: 124, Royapettah High Rd, Vinayagar Kovil, Mylapore, Chennai, Tamil Nadu 600004 | CL54: Chennai | CM54: TAMIL NADU | CN54: 600004 | CO54: CHEV00406A | CP54: 124, Royapettah High Rd, Vinayagar Kovil, Mylapore, Chennai, Tamil Nadu 600004 | CQ54: 124, Royapettah High Rd, Vinayagar Kovil, Mylapore, Chennai, Tamil Nadu 600004
A55: Key Account | B55: 1752 | C55: S N Kansagra School | D55: =VLOOKUP(B55,'2025'!B:C,2,0) -> Unnati Sharma | F55: 2024 | G55: 2024-06-29 00:00:00, 2024-07-01 00:00:00, 2024-07-22 00:00:00 | H55: Ei ASSET, Ei ASSET,Ei Mindspark, Ei Mindspark | I55: Regular | J55: IN-2022002290, IN-2022002299, IN-2022002368 | K55: Approved By Logistic Team | L55: 3967583 | M55: 4542021 | N55: 776264 | O55: 1094 | P55: 678, 710 | Q55: 0 | R55: 0 | T55: 3191319 | U55: 2216 | V55: 1379, 1441 | W55: 0 | X55: Full Payment | Z55: 2024-12-16 00:00:00 | AA55: 2000-01-01 00:00:00 | AB55: 0 | AC55: 2000-01-01 00:00:00 | AD55: 0 | AE55: 2000-01-01 00:00:00 | AF55: 0 | AG55: 2000-01-01 00:00:00 | AH55: 0 | AI55: 0, 90000 | AJ55: 2024-11-27 00:00:00 | AK55: 2025-02-12 00:00:00 | AL55: 3733211, 46106, 762704 | AM55: 0, 3472136 | AN55: 171075, 46106, 762704 | AO55: 0.5278, 0.5479999999999999, 0.5867 | AP55: 0.4278, 0.4868, 0.498 | AR55: 0.0499, 0.05 | AT55: 0.05 | AU55: 0, Winter Round | AV55: OMR | AW55: 0 | AX55: MCQ | BA55: Online | BB55: CISCE | BC55: Rajkot | BD55: Gujarat | BE55: West | BF55: Gujarat | BG55: National Sales | BH55: 2024-07-01 00:00:00 | BI55: 2025-06-30 00:00:00 | BJ55: Regular School: Active school with student count and rate per student defined | BK55: 22028000023209880, 22028000023251120, 22028000023684228 | BL55: 51788000002728408 | BM55: zcrm_51788000271061001, zcrm_51788000271352001 | BN55: 2024-06-29 00:00:00, 2024-07-01 00:00:00, 2024-07-22 00:00:00 | BO55: pooja.joshi_eiindia1 | BP55: fagun.saraiya_eiindia1, maruf.shaikh1 | BQ55: pooja.joshi@ei.study | BR55: Pooja joshi | BS55: Heena Kumar | BT55: Aarti Iyer | BU55: 2024-07-01 11:08:41, 2024-07-01 14:53:11, 2024-07-23 09:52:21 | BV55: Mr. Gokul Paravoor, Pooja Joshi | BW55: Other | BX55: gokul.paravoor@tges.org, pooja.joshi@ei.study | BY55: +919737756790, +919909998141 | BZ55: info@tges.org | CG55: 61200 | CH55: Aakashwani Chowk, University Road, Near HP Fuel Station | CJ55: 360005 | CK55: Aakashwani Chowk, University Road, Near HP Fuel Station | CL55: Rajkot | CM55: Gujarat | CN55: 360005 | CP55: Aakashwani Chowk, University Road, Near HP Fuel Station | CQ55: Aakashwani Chowk, University Road, Near HP Fuel Station
A56: Retention School | B56: 175250 | C56: The TVS School | D56: =VLOOKUP(B56,'2025'!B:C,2,0) -> Nisha Murali | F56: 2024 | G56: 2024-03-01 00:00:00 | H56: Ei ASSET,Ei CARES,Ei Mindspark | I56: Regular | J56: IN-2022001580 | K56: Approved By Logistic Team | L56: 5030694 | M56: 5317384 | N56: 775607 | O56: 2293 | P56: 338 | Q56: 2662366 | R56: 2315 | S56: 1150 | T56: 1592721 | U56: 2315 | V56: 688 | W56: 0 | X56: Installments | Y56: 4 | AA56: 2024-06-01 00:00:00 | AB56: 1329346 | AC56: 2024-09-01 00:00:00 | AD56: 1329346 | AE56: 2024-12-01 00:00:00 | AF56: 1329346 | AG56: 2024-12-31 00:00:00 | AH56: 1329346 | AI56: 507904 | AJ56: 2024-07-22 00:00:00 | AK56: 2025-01-28 00:00:00 | AL56: 5317384 | AM56: 4785241 | AN56: 24239 | AO56: 0.7745000000000001 | AP56: 0.7745000000000001 | AU56: Winter Round | AV56: OMR | AW56: 6 | AX56: MCQ | AY56: Printing By EI | AZ56: OMR | BA56: Online | BB56: State Board | BC56: Madurai | BD56: Tamil Nadu | BE56: South | BF56: Tamil Nadu | BG56: National Sales | BH56: 2024-05-23 00:00:00 | BI56: 2025-06-04 00:00:00 | BJ56: Regular School: Active school with student count and rate per student defined | BK56: 22028000021314460 | BL56: 51788000002732500 | BM56: zcrm_51788000266144001 | BN56: 2024-03-01 00:00:00 | BO56: nisha.murali_eiindia | BP56: hakim.kanchwala_eiindia1 | BQ56: nisha.murali@ei.study | BR56: Nisha murali | BS56: Nisha Murali | BU56: 2024-04-06 07:38:49 | BV56: Mrs. Aruna Kumari | BW56: Principal | BX56: arunakumari@tvslvs.com | BY56: +919585544050 | BZ56: thetvsschool@tvslvs.com | CA56: Mrs. Aruna Kumari | CB56: arunakumari@tvslvs.com | CC56: +919585544050 | CD56: Jeyasree V | CE56: jeyasree.thetvs.as@gmail.com | CF56: +919894970145 | CG56: 0 | CH56: TVS School | CJ56: 625003 | CK56: TVS School | CL56: Madurai | CM56: Tamil Nadu | CN56: 625003 | CO56: MRIL00055G | CP56: TVS School | CQ56: TVS School
A57: 1-year School | B57: 1754962 | C57: The Ashok Leyland School | E57: Dropped | F57: 2024 | G57: 2024-04-04 00:00:00 | H57: Ei Mindspark | I57: Regular | J57: IN-2022001837 | K57: Approved By Logistic Team | L57: 751369 | M57: 886615 | N57: 0 | O57: 0 | Q57: 0 | R57: 0 | T57: 751369 | U57: 591 | V57: 1271 | W57: 0 | X57: Installments | Y57: 4 | AA57: 2024-03-25 00:00:00 | AB57: 221654 | AC57: 2024-07-01 00:00:00 | AD57: 221654 | AE57: 2024-10-01 00:00:00 | AF57: 221654 | AG57: 2024-12-01 00:00:00 | AH57: 221654 | AI57: 11151 | AJ57: 2024-03-30 00:00:00 | AK57: 2024-12-11 00:00:00 | AL57: 886616 | AM57: 857582 | AN57: 17883 | AO57: 0.5832999999999999 | AP57: 0.5832999999999999 | AU57: 0 | AW57: 0 | AX57: MCQ | BA57: Online | BB57: CBSE | BC57: Hosur | BD57: Tamil Nadu | BE57: South | BF57: Karnataka/Kerala | BG57: National Sales | BH57: 2024-04-01 00:00:00 | BI57: 2025-03-31 00:00:00 | BJ57: Regular School: Active school with student count and rate per student defined | BK57: 22028000021910820 | BL57: 51788000002761102 | BM57: zcrm_51788000266958231 | BN57: 2024-04-04 00:00:00 | BO57: praveenkumar.rajamanickam_ei | BP57: sourabh.mehta_eiindia | BQ57: praveenkumar.rajamanickam@ei.study | BR57: Praveenkumar rajamanickam | BS57: Mohammadi Zohra | BT57: Mohammadi Zohra | BU57: 2024-04-04 12:15:30 | BV57: Mrs. Poorna Durachi | BW57: Principal | BX57: poorna@thealschool.org | BZ57: alshosur@gmail.com | CA57: Mrs. Poorna Durachi | CB57: poorna@thealschool.org | CG57: 0 | CH57: E - 1, SIPCOT Industrial Complex,Phase II | CJ57: 635130 | CK57: E - 1, SIPCOT Industrial Complex,Phase II | CL57: Hosur | CM57: Tamil Nadu | CN57: 635130 | CP57: E - 1, SIPCOT Industrial Complex,Phase II | CQ57: E - 1, SIPCOT Industrial Complex,Phase II
A58: Retention School | B58: 175733 | C58: Lokhandwala Foundation School | E58: Dropped | F58: 2024 | G58: 2024-06-15 00:00:00 | H58: Ei ASSET | I58: Regular | J58: IN-2022002207 | K58: Approved By Logistic Team | L58: 65526 | M58: 65526 | N58: 65526 | O58: 72 | P58: 910 | Q58: 0 | R58: 0 | T58: 0 | U58: 0 | W58: 0 | X58: Full Payment | Z58: 2024-06-15 00:00:00 | AA58: 2000-01-01 00:00:00 | AB58: 0 | AC58: 2000-01-01 00:00:00 | AD58: 0 | AE58: 2000-01-01 00:00:00 | AF58: 0 | AG58: 2000-01-01 00:00:00 | AH58: 0 | AI58: 0 | AJ58: 2024-07-16 00:00:00 | AK58: 2024-07-16 00:00:00 | AL58: 65526 | AM58: 65526 | AN58: 0 | AO58: 0.2416 | AP58: 0.2416 | AU58: Summer Round | AV58: Online | AW58: 0 | AX58: MCQ | BB58: CISCE | BC58: Mumbai | BD58: Maharashtra | BE58: West | BF58: Mumbai | BG58: National Sales | BH58: 2024-06-01 00:00:00 | BI58: 2025-05-31 00:00:00 | BJ58: Regular School: Active school with student count and rate per student defined | BK58: 22028000023005292 | BL58: 51788000002732504 | BM58: zcrm_51788000270687025 | BN58: 2024-06-15 00:00:00 | BO58: hetal.parmar_ei | BP58: hakim.kanchwala_eiindia1 | BQ58: hetal.parmar@ei.study | BR58: Hetal parmar | BS58: Manjeetsingh Ladhad | BU58: 2024-06-22 13:18:16 | BV58: Ms. Arti Desai | BW58: Principal | BX58: info@lokhandwalaschool.org | BY58: +919821795516 | BZ58: Info@lokhandwalaschool.org | CG58: 0 | CH58: Plot Bearing CTS No. 171/1A/28, Lokhandwala Township, Akurli Road, Kandivali (East) | CJ58: 400101 | CK58: Plot Bearing CTS No. 171/1A/28, Lokhandwala Township, Akurli Road, Kandivali (East), | CL58: Mumbai | CM58: Maharashtra | CN58: 400101 | CP58: Plot Bearing CTS No. 171/1A/28, Lokhandwala Township, Akurli Road, Kandivali (East) | CQ58: Plot Bearing CTS No. 171/1A/28, Lokhandwala Township, Akurli Road, Kandivali (East),
A59: New School | B59: 177663 | C59: St. James^ School | D59: =VLOOKUP(B59,'2025'!B:C,2,0) -> Pooja | F59: 2024 | G59: 2024-02-18 00:00:00 | H59: Ei ASSET | I59: Regular | J59: IN-2022001514 | K59: Approved By Logistic Team | L59: 1057500 | M59: 1057500 | N59: 1057500 | O59: 1410 | P59: 750 | Q59: 0 | R59: 0 | T59: 0 | U59: 0 | W59: 0 | X59: Installments | Y59: 3 | AA59: 2024-02-27 00:00:00 | AB59: 264375 | AC59: 2024-06-07 00:00:00 | AD59: 264375 | AE59: 2024-08-02 00:00:00 | AF59: 528750 | AG59: 2000-01-01 00:00:00 | AH59: 0 | AI59: 102476 | AJ59: 2024-03-05 00:00:00 | AK59: 2024-11-26 00:00:00 | AL59: 1057500 | AM59: 922274 | AN59: 32750 | AO59: 0.5 | AP59: 0.45 | AR59: 0.05 | AU59: Summer Round | AV59: OMR | AW59: 0 | AX59: MCQ | BB59: CISCE | BC59: Kolkata | BD59: West Bengal | BE59: East | BF59: West Bengal | BG59: National Sales | BH59: 2024-04-15 00:00:00 | BI59: 2025-01-31 00:00:00 | BJ59: Regular School: Active school with student count and rate per student defined | BK59: 22028000021093788 | BL59: 51788000002732621 | BM59: zcrm_51788000263911161 | BN59: 2024-02-18 00:00:00 | BO59: mayukh.chowdhury_ei1 | BP59: mitul.patel_ei1 | BQ59: mayukh.chowdhury@ei.study | BR59: Mayukh chowdhury | BS59: Nishu Rani | BU59: 2024-02-19 14:18:40 | BV59: T.H Ireland | BW59: Principal | BX59: sjkolkata1864@gmail.com | BY59: +913322841546 | BZ59: sjskolkata1864@gmail.com | CA59: T.H Ireland | CB59: sjkolkata1864@gmail.com | CC59: +913322841546 | CD59: Dhruba Dhar | CE59: sjkolkata1864@gmail.com | CG59: 48000 | CH59: 165, Acharya Jagadish Chandra Bose Rd, Entally, | CJ59: 700014 | CK59: 165, Acharya Jagadish Chandra Bose Rd, Entally, | CL59: Kolkata | CM59: West Bengal | CN59: 700014 | CO59: CALS00749A | CP59: 165, Acharya Jagadish Chandra Bose Rd, Entally, | CQ59: 165, Acharya Jagadish Chandra Bose Rd, Entally,
A60: 1-year School | B60: 179667 | C60: Dolna Day School | E60: Dropped | F60: 2024 | G60: 2024-04-24 00:00:00 | H60: Ei CARES | I60: Regular | J60: IN-2022001961 | K60: Approved By Logistic Team | L60: 454889 | M60: 454889 | N60: 0 | O60: 0 | Q60: 454889 | R60: 263 | S60: 1730 | T60: 0 | U60: 0 | W60: 0 | X60: Installments | Y60: 4 | AA60: 2024-04-29 00:00:00 | AB60: 113722 | AC60: 2024-07-25 00:00:00 | AD60: 113722 | AE60: 2024-09-25 00:00:00 | AF60: 113722 | AG60: 2024-12-30 00:00:00 | AH60: 113722 | AI60: 0 | AJ60: 2024-04-29 00:00:00 | AK60: 2025-02-03 00:00:00 | AL60: 454888 | AM60: 454889.05000000005 | AN60: -1 | AO60: 0.6676000000000001 | AP60: 0.6676000000000001 | AU60: 0 | AW60: 4 | AX60: MCQ | AY60: Printing By EI | AZ60: OMR | BB60: CISCE | BC60: Kolkata | BD60: West Bengal | BE60: East | BF60: West Bengal | BG60: National Sales | BH60: 2024-04-27 00:00:00 | BI60: 2025-03-25 00:00:00 | BJ60: Regular School: Active school with student count and rate per student defined | BK60: 22028000022249112 | BL60: 51788000002732636 | BM60: zcrm_51788000268843021 | BN60: 2024-04-24 00:00:00 | BO60: ratnabali.mukherjee_eiindia | BP60: sourabh.mehta_eiindia | BQ60: ratnabali.mukherjee@ei.study | BR60: Ratnabali mukherjee | BS60: Soumodeep Ghosh | BU60: 2024-04-27 14:40:37 | BV60: Mrs Madhura Bhattacharya | BW60: Principal | BX60: dolnaday@gmail.com | BY60: +913324424102 | BZ60: dolnaday@gmail.com | CA60: Mrs Madhura Bhattacharya | CB60: dolnaday@gmail.com | CC60: +913324424102 | CD60: Mr. Balaji | CE60: dolnaday@gmail.com | CF60: +919831059786 | CG60: 0 | CH60: P-V. Cit Scheme Kasba III | CJ60: 700042 | CK60: P-V. Cit Scheme Kasba III | CL60: Kolkata | CM60: West Bengal | CN60: 700042 | CP60: P-V. Cit Scheme 47,Kasba III | CQ60: P-V. Cit Scheme Kasba III
A61: Retention School | B61: 1797713 | C61: Virudhunagar T S M Manickamnadar Janakiamamal Higher Secondary School | F61: 2024 | G61: 2024-03-21 00:00:00, 2024-03-24 00:00:00 | H61: Ei CARES,Ei Mindspark, Ei Mindspark | I61: Regular | J61: IN-2022001713, IN-2022001732 | K61: Approved By Logistic Team | L61: 572441 | M61: 648251 | N61: 0 | O61: 0 | Q61: 151273 | R61: 180 | S61: 840 | T61: 421168 | U61: 360 | V61: 1068, 1271 | W61: 0 | X61: Full Payment | Z61: 2024-03-31 00:00:00 | AA61: 2000-01-01 00:00:00 | AB61: 0 | AC61: 2000-01-01 00:00:00 | AD61: 0 | AE61: 2000-01-01 00:00:00 | AF61: 0 | AG61: 2000-01-01 00:00:00 | AH61: 0 | AI61: 0 | AJ61: 2024-06-05 00:00:00 | AK61: 2024-06-05 00:00:00 | AL61: 270057, 378194 | AM61: 270057, 378194 | AN61: 0 | AO61: 0.7868, 0.8656999999999999 | AP61: 0.7368000000000001, 0.8157 | AQ61: 0.05 | AU61: 0 | AW61: 8 | AX61: MCQ | AZ61: Online | BA61: Online | BB61: CISCE | BC61: Madurai | BD61: Tamil Nadu | BE61: South | BF61: Tamil Nadu | BG61: National Sales | BH61: 2024-06-01 00:00:00 | BI61: 2025-04-30 00:00:00 | BJ61: Regular School: Active school with student count and rate per student defined | BK61: 22028000021670072, 22028000021704872 | BL61: 51788000002761919 | BM61: zcrm_51788000267394001, zcrm_51788000267395283 | BN61: 2024-03-21 00:00:00, 2024-03-24 00:00:00 | BO61: zohra.khan_ei | BP61: hakim.kanchwala_eiindia1, megha.m_ei | BQ61: zohra.khan@ei.study | BR61: Zohra khan | BS61: Vineeth T V | BU61: 2024-05-10 16:12:54, 2024-05-10 16:12:57 | BV61: Mr. D Dhivyan Dayallan | BW61: Other | BX61: vmjschool@gmail.com | BY61: +919894104343 | BZ61: vmjschool@gmail.com | CG61: 0 | CH61: Door No. 100, New Ramanad Road, | CJ61: 625009 | CK61: Door No. 100, New Ramanad Road, | CL61: Madurai | CM61: Tamil Nadu | CN61: 625009 | CP61: Door No. 100, New Ramanad Road, | CQ61: Door No. 100, New Ramanad Road,
A62: Retention School | B62: 1805376 | C62: KLE English Medium School, Solapur | F62: 2024 | G62: 2024-06-16 00:00:00 | H62: Ei ASSET, Ei Mindspark | I62: Regular | J62: IN-2022002208, IN-2022002240 | K62: Approved By Logistic Team | L62: 819665 | M62: 911122 | N62: 311572 | O62: 1002 | P62: 311 | Q62: 0 | R62: 0 | T62: 508093 | U62: 999 | V62: 509 | W62: 0 | X62: Installments | Y62: 2 | AA62: 2024-07-15 00:00:00 | AB62: 155786, 299775 | AC62: 2024-11-15 00:00:00, 2024-12-15 00:00:00 | AD62: 155786, 299775 | AE62: 2000-01-01 00:00:00 | AF62: 0 | AG62: 2000-01-01 00:00:00 | AH62: 0 | AI62: 31068.9, 50796 | AJ62: 2024-09-05 00:00:00, 2024-09-18 00:00:00 | AK62: 2025-01-17 00:00:00 | AL62: 311572, 599550 | AM62: 279620.1, 548602 | AN62: 152, 883 | AO62: 0.7927, 0.8332999999999999 | AP62: 0.7927, 0.8332999999999999 | AU62: 0, Winter Round | AV62: OMR | AW62: 0 | AX62: MCQ | BA62: Online | BB62: CBSE | BC62: Solapur | BD62: Maharashtra | BE62: West | BF62: Rest of Maharashtra and Goa | BG62: National Sales | BH62: 2024-06-01 00:00:00 | BI62: 2025-04-30 00:00:00, 2025-05-31 00:00:00 | BJ62: Regular School: Active school with student count and rate per student defined | BK62: 22028000023002328, 22028000023033608 | BL62: 51788000002761991 | BM62: zcrm_51788000270604456, zcrm_51788000270692303 | BN62: 2024-06-16 00:00:00 | BO62: vineet.upadhye_ei | BP62: mitul.patel_ei1 | BQ62: vineet.upadhye@ei.study | BR62: Vineet upadhye | BS62: Nainesh Bhise | BU62: 2024-06-18 10:39:18, 2024-06-18 10:45:52 | BV62: Maruf Shaikh | BX62: maruf.shaikh@ei.study | BY62: +919016039311 | CG62: 0 | CH62: Narsimha Nagar, near D-mart, Jule, Solapur | CJ62: 413003 | CK62: Narsimha Nagar, near D-mart, Jule, Solapur | CL62: Solapur | CM62: Maharashtra | CN62: 413003 | CO62: BLRK04875D | CP62: Narsimha Nagar, near D-mart, Jule, Solapur | CQ62: Narsimha Nagar, near D-mart, Jule, Solapur
A63: Retention School | B63: 1810177 | C63: Birla Divya Jyoti | E63: Dropped | F63: 2024 | G63: 2024-03-06 00:00:00 | H63: Ei Mindspark | I63: Regular | J63: IN-2022001591 | K63: Approved By Logistic Team | L63: 729189 | M63: 860443 | N63: 0 | O63: 0 | Q63: 0 | R63: 0 | T63: 729189 | U63: 478 | V63: 1526 | W63: 0 | X63: Installments | Y63: 2 | AA63: 2024-04-01 00:00:00 | AB63: 430222 | AC63: 2024-09-30 00:00:00 | AD63: 430222 | AE63: 2000-01-01 00:00:00 | AF63: 0 | AG63: 2000-01-01 00:00:00 | AH63: 0 | AI63: 74940 | AJ63: 2024-05-03 00:00:00 | AK63: 2025-01-10 00:00:00 | AL63: 860444 | AM63: 809352.53 | AN63: -23849 | AO63: 0.5 | AP63: 0.5 | AU63: 0 | AW63: 0 | AX63: MCQ | BA63: Online | BB63: CBSE | BC63: Siliguri | BD63: West Bengal | BE63: East | BF63: West Bengal | BG63: National Sales | BH63: 2024-04-01 00:00:00 | BI63: 2025-03-31 00:00:00 | BJ63: Regular School: Active school with student count and rate per student defined | BK63: 22028000021382188 | BL63: 51788000002762139 | BM63: zcrm_51788000266077001 | BN63: 2024-03-06 00:00:00 | BO63: gargi.ghosh_ei | BP63: mitul.patel_ei1 | BQ63: gargi.ghosh@ei.study | BR63: Gargi ghosh | BS63: Gargi Ghosh | BT63: Gargi Ghosh | BU63: 2024-03-07 14:38:20 | BV63: Shweta Tewari | BW63: Principal | BX63: shwetiv06@gmail.com | BY63: +917001450195 | BZ63: info@birladivyajyoti.com | CA63: Shweta Tewari | CB63: shwetiv06@yahoo.com | CC63: +917001450195 | CD63: Saojini Gurung | CE63: sarojinigurung123@gmail.com | CF63: +917478422423 | CG63: 0 | CH63: Uttarayan Township, Zone-F, National Highway - 31, P.O. Matigara, ,Siliguri,West Bengal - 734010 | CJ63: 734010 | CK63: Uttarayan Township, Zone-F, National Highway - 31, P.O. Matigara, ,Siliguri,West Bengal - 734010 | CL63: Siliguri | CM63: West Bengal | CN63: 734010 | CO63: CALB14092B | CP63: Uttarayan Township, Zone-F, National Highway - 31, P.O. Matigara, ,Siliguri,West Bengal - 734010 | CQ63: Uttarayan Township, Zone-F, National Highway - 31, P.O. Matigara, ,Siliguri,West Bengal - 734010
A64: New School | B64: 1811278 | C64: Mlrt Gala Pioneer English School | E64: Dropped | F64: 2024 | G64: 2024-06-27 00:00:00 | H64: Ei CARES | I64: Regular | J64: IN-2022002280 | K64: Approved By Logistic Team | L64: 113737 | M64: 113737 | N64: 0 | O64: 0 | Q64: 113737 | R64: 65 | S64: 1750 | T64: 0 | U64: 0 | W64: 0 | X64: Installments | Y64: 2 | AA64: 2024-06-26 00:00:00 | AB64: 34121 | AC64: 2024-09-26 00:00:00 | AD64: 79616 | AE64: 2000-01-01 00:00:00 | AF64: 0 | AG64: 2000-01-01 00:00:00 | AH64: 0 | AI64: 2380 | AJ64: 2024-07-25 00:00:00 | AK64: 2024-10-31 00:00:00 | AL64: 113737 | AM64: 116607 | AN64: -5250 | AO64: 0.327 | AP64: 0.327 | AU64: 0 | AW64: 4 | AX64: MCQ | AY64: Printing By School | AZ64: Online | BB64: State Board | BC64: Mumbai | BD64: Maharashtra | BE64: West | BF64: Mumbai | BG64: National Sales | BH64: 2024-07-15 00:00:00 | BI64: 2025-04-15 00:00:00 | BJ64: Regular School: Active school with student count and rate per student defined | BK64: 22028000023177392 | BL64: 51788000002762150 | BM64: zcrm_51788000270628430 | BN64: 2024-06-27 00:00:00 | BO64: manjeetsingh.ladhad | BP64: maruf.shaikh1 | BQ64: manjeetsingh.ladhad@ei.study | BR64: Manjeetsingh ladhad | BS64: Manjeetsingh Ladhad | BU64: 2024-07-01 18:00:19 | BV64: Prakash Nalawade | BW64: School Owner | BX64: pioneerseducationtrust@yahoo.in | BY64: +919892666333 | BZ64: principalmlrt@gmail.com | CG64: 3200 | CH64: Kandivali (East), Akoli Road, | CJ64: 400101 | CK64: Kandivali (East), Akoli Road, | CL64: Mumbai | CM64: Maharashtra | CN64: 400101 | CP64: Kandivali (East), Akoli Road, | CQ64: Kandivali (East), Akoli Road,
A65: 1-year School | B65: 181976 | C65: St. Paul's Academy | D65: =VLOOKUP(B65,'2025'!B:C,2,0) -> Tanya | F65: 2024 | G65: 2024-03-20 00:00:00 | H65: Ei CARES | I65: Regular | J65: IN-2022001703 | K65: Approved By Logistic Team | L65: 875885 | M65: 875885 | N65: 0 | O65: 0 | Q65: 875885 | R65: 1225 | S65: 715 | T65: 0 | U65: 0 | W65: 0 | X65: Installments | Y65: 2 | AA65: 2024-03-19 00:00:00 | AB65: 437943 | AC65: 2024-10-16 00:00:00 | AD65: 437943 | AE65: 2000-01-01 00:00:00 | AF65: 0 | AG65: 2000-01-01 00:00:00 | AH65: 0 | AI65: 43785 | AJ65: 2024-03-20 00:00:00 | AK65: 2024-10-23 00:00:00 | AL65: 875886 | AM65: 788212 | AN65: 43889 | AO65: 0.5884 | AP65: 0.5384 | AR65: 0.05 | AU65: 0 | AW65: 2 | AX65: MCQ + Subjective | AY65: Printing By EI | AZ65: OMR | BB65: ICSE | BC65: Ghaziabad | BD65: Uttar Pradesh | BE65: North | BF65: NCR | BG65: National Sales | BH65: 2024-04-01 00:00:00 | BI65: 2025-03-31 00:00:00 | BJ65: Regular School: Active school with student count and rate per student defined | BK65: 22028000021642436 | BL65: 51788000002732651 | BM65: zcrm_51788000266374140 | BN65: 2024-03-20 00:00:00 | BO65: puneet.khurana_ei | BP65: fagun.saraiya_eiindia1 | BQ65: puneet.khurana@ei.study | BR65: Puneet khurana | BS65: Tanya Marina Brooks | BU65: 2024-03-22 12:04:31 | BV65: Mr. Fr. Byju Peruvan | BW65: Principal | BX65: stpacademy@rediffmail.com | BY65: +919759967579 | BZ65: stpsacademy@gmail.com | CA65: Mr. Fr. Byju Peruvan | CB65: stpacademy@rediffmail.com | CC65: +919759967579 | CD65: Ms Anshu | CE65: anshugulati21@gmail.com | CF65: +919810085551 | CG65: 48000 | CH65: Sector 9, Raj Nagar, | CJ65: 201002 | CK65: Sec - 9, Raj Nagar, | CL65: Ghaziabad | CM65: Uttar Pradesh | CN65: 201002 | CO65: MRTS02491G | CP65: Sector 9, Raj Nagar, | CQ65: Sec - 9, Raj Nagar,
A66: New School | B66: 1822220 | C66: Kasiga School | D66: =VLOOKUP(B66,'2025'!B:C,2,0) -> Tanya | F66: 2024 | G66: 2024-05-29 00:00:00 | H66: Ei ASSET | I66: Regular | J66: IN-2022002122 | K66: Approved By Logistic Team | L66: 231336 | M66: 231336 | N66: 231336 | O66: 204 | P66: 1134 | Q66: 0 | R66: 0 | T66: 0 | U66: 0 | W66: 0 | X66: Full Payment | Z66: 2024-03-31 00:00:00 | AA66: 2000-01-01 00:00:00 | AB66: 0 | AC66: 2000-01-01 00:00:00 | AD66: 0 | AE66: 2000-01-01 00:00:00 | AF66: 0 | AG66: 2000-01-01 00:00:00 | AH66: 0 | AI66: 23134 | AJ66: 2024-05-24 00:00:00 | AK66: 2024-05-24 00:00:00 | AL66: 231336 | AM66: 208202 | AN66: 0 | AO66: 0.26 | AP66: 0.16 | AQ66: 0.1 | AU66: Summer Round | AV66: OMR | AW66: 0 | AX66: MCQ | BB66: CBSE | BC66: Dehradun | BD66: Uttarakhand | BE66: North | BF66: UP/Uttarakhand | BG66: National Sales | BH66: 2024-04-01 00:00:00 | BI66: 2025-03-31 00:00:00 | BJ66: Regular School: Active school with student count and rate per student defined | BK66: 22028000022690112 | BL66: 51788000002762359 | BM66: zcrm_51788000270048584 | BN66: 2024-05-29 00:00:00 | BO66: girish.arya_ei | BP66: fagun.saraiya_eiindia1 | BQ66: girish.arya@ei.study | BR66: Girish arya | BS66: Prabhjit Singh | BT66: Vaishali Yadav | BU66: 2024-06-28 10:31:50 | BV66: Maruf shaikh | BW66: Admin | BX66: maruf.shaikh@ei-india.com | BY66: +919016039311 | BZ66: secyprincipal@kasigaschool.com | CG66: 1004000 | CH66: Village Purkul Off Dehradun-Mussoorie Highway, | CJ66: 248009 | CK66: Village Purkul Off Dehradun â Mussoorie Highway Dehradun â 248 009 | CL66: Dehradun | CM66: Uttarakhand | CN66: 248009 | CO66: na | CP66: Village Purkul Off Dehradun-Mussoorie Highway, | CQ66: Village Purkul Off Dehradun â Mussoorie Highway Dehradun â 248 009
A67: Retention School | B67: 1823562 | C67: Roopnagar Public School | D67: =VLOOKUP(B67,'2025'!B:C,2,0) -> Rohit | F67: 2024 | G67: 2024-02-07 00:00:00, 2024-12-16 00:00:00 | H67: Ei ASSET, Ei Mindspark | I67: Regular | J67: IN-2022001476, IN-2022002699 | K67: Approved By Logistic Team | L67: 787483 | M67: 920846 | N67: 46575 | O67: 69 | P67: 675 | Q67: 0 | R67: 0 | T67: 740908 | U67: 437 | V67: 1695 | W67: 0 | X67: Full Payment, Installments | Y67: 4 | Z67: 2024-12-18 00:00:00 | AA67: 2000-01-01 00:00:00, 2024-04-30 00:00:00 | AB67: 0, 218568 | AC67: 2000-01-01 00:00:00, 2024-07-30 00:00:00 | AD67: 0, 218568 | AE67: 2000-01-01 00:00:00, 2024-10-30 00:00:00 | AF67: 0, 218568 | AG67: 2000-01-01 00:00:00, 2024-12-30 00:00:00 | AH67: 0, 218568 | AI67: 0, 3408 | AJ67: 2024-09-14 00:00:00, 2024-12-18 00:00:00 | AK67: 2024-12-18 00:00:00, 2025-04-14 00:00:00 | AL67: 46575, 874272 | AM67: 45643, 811648 | AN67: 59216, 932 | AO67: 0.4443, 0.55 | AP67: 0.3943, 0.5 | AT67: 0.05 | AU67: 0, Winter Round | AV67: OMR | AW67: 0 | AX67: MCQ | BA67: Online | BB67: CBSE | BC67: Jhalawar | BD67: Rajasthan | BE67: North | BF67: Rajasthan | BG67: National Sales | BH67: 2024-04-01 00:00:00, 2024-12-02 00:00:00 | BI67: 2025-03-31 00:00:00 | BJ67: Regular School: Active school with student count and rate per student defined | BK67: 22028000020956256, 22028000026876700 | BL67: 51788000002762372 | BM67: zcrm_51788000264396029, zcrm_51788000279272516 | BN67: 2024-02-07 00:00:00, 2024-12-16 00:00:00 | BO67: pooja.kapoor_eiindia1, rohit.kumar_ei | BP67: fagun.saraiya_eiindia1 | BQ67: pooja.kapoor@ei.study, rohit.kumar@ei.study | BR67: Pooja kapoor, Rohit kumar | BS67: Rohit Kumar | BU67: 2024-02-09 14:47:32, 2024-12-18 14:31:32 | BV67: Mr. Benudhar Rout, Rahul Sharma | BW67: Accounts, Admin | BX67: accountsdesk@rpsjhalawar.com | BY67: +918107310228, +918949247356 | BZ67: rpsjhalawar@yahoo.in | CA67: Mr. Sharma | CB67: principal@rpsjhalawar.com | CC67: +918107310228 | CD67: Mr. Sharma | CE67: principal@rpsjhalawar.com | CF67: +918107310228 | CG67: 0 | CH67: NH 52, Kota Road, Jhalawar, Roopnagar Colony | CJ67: 326001 | CK67: NH 52, Kota Road, Jhalawar, Roopnagar Colony | CL67: Jhalawar | CM67: Rajasthan | CN67: 326001 | CO67: JDHR05782A | CP67: NH 52, Kota Road, Jhalawar, Roopnagar Colony | CQ67: NH 52, Kota Road, Jhalawar, Roopnagar Colony
A68: 1-year School | B68: 1837151 | C68: Shri Rama Bharati School - Sainik Nagar | D68: =VLOOKUP(B68,'2025'!B:C,2,0) -> Anushka | F68: 2024 | G68: 2023-12-28 00:00:00 | H68: Ei ASSET,Ei CARES | I68: Regular | J68: IN-2022001373 | K68: Approved By Logistic Team | L68: 2216214 | M68: 2216214 | N68: 687414 | O68: 1259 | P68: 546 | Q68: 1528800 | R68: 1200 | S68: 1274 | T68: 0 | U68: 0 | W68: 0 | X68: Full Payment | Z68: 2024-01-15 00:00:00 | AA68: 2000-01-01 00:00:00 | AB68: 0 | AC68: 2000-01-01 00:00:00 | AD68: 0 | AE68: 2000-01-01 00:00:00 | AF68: 0 | AG68: 2000-01-01 00:00:00 | AH68: 0 | AI68: 225200 | AJ68: 2024-01-15 00:00:00 | AK68: 2025-09-24 00:00:00 | AL68: 2216214 | AM68: 2094230 | AN68: -103216 | AO68: 0.636 | AP68: 0.536 | AR68: 0.05 | AS68: 0.05 | AU68: Summer Round | AV68: OMR | AW68: 4 | AX68: MCQ | AY68: Printing By EI | AZ68: OMR | BB68: CBSE | BC68: Bahadurgarh | BD68: Haryana | BE68: North | BF68: Delhi/Haryana | BG68: National Sales | BH68: 2024-04-01 00:00:00 | BI68: 2025-03-31 00:00:00 | BJ68: Regular School: Active school with student count and rate per student defined | BK68: 22028000020435312 | BL68: 51788000002762606 | BM68: zcrm_51788000262254472 | BN68: 2023-12-28 00:00:00 | BO68: vikas.shukla_ei | BP68: fagun.saraiya_eiindia1 | BQ68: vikas.shukla@ei.study | BR68: Vikas shukla | BS68: Anushka Gupta | BU68: 2024-01-17 17:37:40 | BV68: Deepak Gupta | BW68: School Owner | BX68: info@srbps.com | BY68: +919891069693 | BZ68: info@srbps.com | CA68: Priya Sangwan | CB68: info.sn@srbps.com | CC68: +917027100388 | CD68: Deeksha Kaushik | CE68: info@srbps.com | CF68: +919992555109 | CG68: 4400 | CH68: Sainik Nagar, Near Sector-06,Bahadurgarh,Haryana - 124507 | CJ68: 124507 | CK68: Sainik Nagar, Near Sector-06,Bahadurgarh,Haryana - 124507 | CL68: Bahadurgarh | CM68: Haryana | CN68: 124507 | CO68: RTKS09920B | CP68: Sainik Nagar, Near Sector-06,Bahadurgarh,Haryana - 124507 | CQ68: Sainik Nagar, Near Sector-06,Bahadurgarh,Haryana - 124507
A69: Retention School | B69: 18460 | C69: Abhinav Bharati High School | D69: =VLOOKUP(B69,'2025'!B:C,2,0) -> Gargi Ghosh | F69: 2024 | G69: 2024-02-08 00:00:00 | H69: Ei Mindspark | I69: Regular | J69: IN-2022001480 | K69: Approved By Logistic Team | L69: 615495 | M69: 726284 | N69: 0 | O69: 0 | Q69: 0 | R69: 0 | T69: 615495 | U69: 365 | V69: 1686 | W69: 0 | X69: Installments | Y69: 4 | AA69: 2024-04-03 00:00:00 | AB69: 181571 | AC69: 2024-07-03 00:00:00 | AD69: 181571 | AE69: 2024-10-03 00:00:00 | AF69: 181571 | AG69: 2024-12-31 00:00:00 | AH69: 181571 | AI69: 10893 | AJ69: 2024-04-17 00:00:00 | AK69: 2025-01-09 00:00:00 | AL69: 726284 | AM69: 711760 | AN69: 3631 | AO69: 0.4473 | AP69: 0.4473 | AU69: 0 | AW69: 0 | AX69: MCQ | BA69: Online | BB69: CBSE | BC69: Kolkata | BD69: West Bengal | BE69: East | BF69: West Bengal | BG69: National Sales | BH69: 2024-04-08 00:00:00 | BI69: 2025-03-31 00:00:00 | BJ69: Regular School: Active school with student count and rate per student defined | BK69: 22028000020984048 | BL69: 51788000002728649 | BM69: zcrm_51788000264801045 | BN69: 2024-02-08 00:00:00 | BO69: lopamudra.das_eiindia1 | BP69: mitul.patel_ei1 | BQ69: lopamudra.das@ei.study | BR69: Lopamudra das | BS69: Lopamudra Das | BU69: 2024-03-18 17:05:18 | BV69: Mrs. Moumita Rakshit | BW69: Admin | BX69: abhsprimary@gmail.com | BY69: +917980545291 | BZ69: abhsprimary@gmai.com | CA69: Rosy | CB69: abhsprimary@gmail.com | CC69: +919836151146 | CD69: Sreya Paul | CE69: sreyap012@gmail.com | CF69: +917980776282 | CG69: 0 | CH69: 11, Pretoria St, Elgin | CJ69: 700071 | CK69: 11, Pretoria St, Elgin | CL69: Kolkata | CM69: West Bengal | CN69: 700071 | CO69: CALA04545C | CP69: 11, Pretoria St, Elgin | CQ69: 11, Pretoria St, Elgin
A70: Key Account | B70: 185882 | C70: J S S Public School | D70: =VLOOKUP(B70,'2025'!B:C,2,0) -> Jasper Jessie | F70: 2024 | G70: 2024-04-16 00:00:00 | H70: Ei ASSET | I70: Regular | J70: IN-2022001915 | K70: Approved By Logistic Team | L70: 594930 | M70: 594930 | N70: 594930 | O70: 700 | P70: 850 | Q70: 0 | R70: 0 | T70: 0 | U70: 0 | W70: 0 | X70: Installments | Y70: 2 | AA70: 2024-04-24 00:00:00 | AB70: 297465 | AC70: 2024-07-01 00:00:00 | AD70: 297465 | AE70: 2000-01-01 00:00:00 | AF70: 0 | AG70: 2000-01-01 00:00:00 | AH70: 0 | AI70: 0 | AJ70: 2024-08-03 00:00:00 | AK70: 2024-08-03 00:00:00 | AL70: 594930 | AM70: 594150 | AN70: 780 | AO70: 0.4334 | AP70: 0.4334 | AU70: Summer Round | AV70: OMR | AW70: 0 | AX70: MCQ | BB70: CBSE | BC70: Bengaluru | BD70: Karnataka | BE70: South | BF70: Karnataka/Kerala | BG70: National Sales | BH70: 2024-05-22 00:00:00 | BI70: 2025-03-12 00:00:00 | BJ70: Regular School: Active school with student count and rate per student defined | BK70: 22028000022062736 | BL70: 51788000002732683 | BM70: zcrm_51788000268551381 | BN70: 2024-04-16 00:00:00 | BO70: garima.jain_ei | BP70: sourabh.mehta_eiindia | BQ70: garima.jain@ei.study | BR70: Garima jain | BS70: Garima Jain | BU70: 2024-04-16 16:58:28 | BV70: Mrs. Gowri . | BW70: Principal | BX70: jsspsbsk@gmail.com | BY70: +919686677270 | BZ70: jsspsbsk@gmail.com | CA70: Mrs. Gowri . | CB70: jsspsbsk@gmail.com | CC70: +919686677270 | CD70: Mrs. Gowri . | CE70: jsspsbsk@gmail.com | CF70: +919686677270 | CG70: 78200 | CH70: 31, 15th Main, 22nd Cross,Siddanna Layout,Banashankari 2nd Stage | CJ70: 560070 | CK70: 31, 15th Main, 22nd Cross,Siddanna Layout,Banashankari 2nd Stage | CL70: Bengaluru | CM70: Karnataka | CN70: 560070 | CO70: 0 | CP70: 31, 15th Main, 22nd Cross,Siddanna Layout,Banashankari 2nd Stage | CQ70: 31, 15th Main, 22nd Cross,Siddanna Layout,Banashankari 2nd Stage
A71: Retention School | B71: 1873384 | C71: G G International School | D71: =VLOOKUP(B71,'2025'!B:C,2,0) -> Aarti Iyer | F71: 2024 | G71: 2024-06-24 00:00:00 | H71: Ei ASSET | I71: Regular | J71: IN-2022002269 | K71: Approved By Logistic Team | L71: 563545 | M71: 563545 | N71: 563545 | O71: 1127 | P71: 500 | Q71: 0 | R71: 0 | T71: 0 | U71: 0 | W71: 0 | X71: Full Payment | Z71: 2024-03-31 00:00:00 | AA71: 2000-01-01 00:00:00 | AB71: 0 | AC71: 2000-01-01 00:00:00 | AD71: 0 | AE71: 2000-01-01 00:00:00 | AF71: 0 | AG71: 2000-01-01 00:00:00 | AH71: 0 | AI71: 0 | AJ71: 2024-06-29 00:00:00 | AK71: 2024-06-29 00:00:00 | AL71: 563545 | AM71: 563545 | AN71: 0 | AO71: 0.7295999999999999 | AP71: 0.6296 | AQ71: 0.1 | AU71: Summer Round | AV71: OMR | AW71: 0 | AX71: MCQ | BB71: CBSE | BC71: Pune | BD71: Maharashtra | BE71: West | BF71: Rest of Maharashtra and Goa | BG71: National Sales | BH71: 2024-06-25 00:00:00 | BI71: 2025-05-31 00:00:00 | BJ71: Regular School: Active school with student count and rate per student defined | BK71: 22028000023147024 | BL71: 51788000002763360 | BM71: zcrm_51788000271133157 | BN71: 2024-06-24 00:00:00 | BO71: aarti.iyer_ei | BP71: hakim.kanchwala_eiindia1 | BQ71: aarti.iyer@ei.study | BR71: Aarti iyer | BS71: Nainesh Bhise | BU71: 2024-07-01 11:00:06 | BV71: Ms. Bharti Bhagwani | BW71: Principal | BX71: principal@myggis.org | BY71: +919822380391 | BZ71: admin@myggis.org | CG71: 0 | CH71: 174 - 177, Swarganga | CJ71: 411018 | CK71: 174 - 177, Swarganga | CL71: Pune | CM71: Maharashtra | CN71: 411018 | CP71: 174 - 177, Swarganga | CQ71: 174 - 177, Swarganga
A72: Retention School | B72: 1879439 | C72: Christel House India | F72: 2024 | G72: 2024-01-26 00:00:00 | H72: Ei ASSET | I72: Regular | J72: IN-2022001430 | K72: Approved By Logistic Team | L72: 376920 | M72: 376920 | N72: 376920 | O72: 468 | P72: 805 | Q72: 0 | R72: 0 | T72: 0 | U72: 0 | W72: 0 | X72: Full Payment | Z72: 2024-01-31 00:00:00 | AA72: 2000-01-01 00:00:00 | AB72: 0 | AC72: 2000-01-01 00:00:00 | AD72: 0 | AE72: 2000-01-01 00:00:00 | AF72: 0 | AG72: 2000-01-01 00:00:00 | AH72: 0 | AI72: 39461 | AJ72: 2024-02-20 00:00:00 | AK72: 2024-02-20 00:00:00 | AL72: 376920 | AM72: 355144 | AN72: -17685 | AO72: 0.55 | AP72: 0.55 | AU72: Winter Round | AV72: OMR | AW72: 0 | AX72: MCQ | BB72: State Board | BC72: Bengaluru | BD72: Karnataka | BE72: South | BF72: Karnataka/Kerala | BG72: National Sales | BH72: 2024-05-01 00:00:00 | BI72: 2025-03-31 00:00:00 | BJ72: Regular School: Active school with student count and rate per student defined | BK72: 22028000020798228 | BL72: 51788000002763420 | BM72: zcrm_51788000264240049 | BN72: 2024-01-26 00:00:00 | BO72: dipti.jain_ei | BP72: mitul.patel_ei1 | BQ72: dipti.jain@ei.study | BR72: Dipti jain | BS72: Aruna | BU72: 2024-01-29 10:13:36 | BV72: Maya Abhimanyu | BW72: Principal | BX72: mabhimanyu@christelhouseindia.org | BY72: +919448516209 | BZ72: christelhouse@vsnl.com | CA72: Maya Abhimanyu | CB72: mabhimanyu@christelhouseindia.org | CC72: +919448516209 | CD72: Mr Amit Sams | CE72: eaedu@christelhouseindia.org | CG72: 0 | CH72: Bellahalli Road, Off Hennur Road, Kannur Post - Via Bagalur, | CJ72: 562149 | CK72: Bellahalli Road, Off Hennur Road, Kannur Post - Via Bagalur, | CL72: Bengaluru | CM72: Karnataka | CN72: 562149 | CO72: BLRC01661C | CP72: Bellahalli Road, Off Hennur Road, Kannur Post - Via Bagalur, | CQ72: Bellahalli Road, Off Hennur Road, Kannur Post - Via Bagalur,
A73: Retention School | B73: 18922 | C73: Sri Kumaran Children's Home - CBSE | D73: =VLOOKUP(B73,'2025'!B:C,2,0) -> Aruna | F73: 2024 | G73: 2024-05-27 00:00:00 | H73: Ei ASSET, Ei CARES, Ei Mindspark | I73: Regular | J73: IN-2022002113, IN-2022002114, IN-2022002115 | K73: Approved By Logistic Team | L73: 2730297 | M73: 2909913 | N73: 1103293 | O73: 1643 | P73: 672 | Q73: 629137 | R73: 466 | S73: 1350 | T73: 997867 | U73: 471 | V73: 2119 | W73: 0 | X73: Full Payment, Installments | Y73: 4 | Z73: 2024-06-15 00:00:00 | AA73: 2000-01-01 00:00:00, 2024-06-15 00:00:00 | AB73: 0, 157284, 294371 | AC73: 2000-01-01 00:00:00, 2024-08-15 00:00:00 | AD73: 0, 157284, 294371 | AE73: 2000-01-01 00:00:00, 2024-10-15 00:00:00 | AF73: 0, 157284, 294371 | AG73: 2000-01-01 00:00:00, 2024-12-15 00:00:00 | AH73: 0, 157284, 294371 | AI73: 110128, 113983, 62522 | AJ73: 2024-06-11 00:00:00 | AK73: 2024-06-11 00:00:00, 2024-12-20 00:00:00, 2025-01-23 00:00:00 | AL73: 1103293, 1177484, 629136 | AM73: 1077763, 562697, 991148 | AN73: -14262, 2017, 3917 | AO73: 0.3056, 0.5392, 0.5781000000000001 | AP73: 0.3056, 0.4892, 0.5781000000000001 | AR73: 0.05 | AU73: 0, Summer Round | AV73: Online | AW73: 0, 4 | AX73: MCQ | AZ73: Online | BA73: Online | BB73: CBSE | BC73: Bengaluru | BD73: Karnataka | BE73: South | BF73: Karnataka/Kerala | BG73: National Sales | BH73: 2024-06-01 00:00:00 | BI73: 2025-05-31 00:00:00 | BJ73: Regular School: Active school with student count and rate per student defined | BK73: 22028000022677684, 22028000022677728, 22028000022677776 | BL73: 51788000002728654 | BM73: zcrm_51788000269883682, zcrm_51788000269883813, zcrm_51788000269883941 | BN73: 2024-05-27 00:00:00 | BO73: vineet.upadhye_ei | BP73: hakim.kanchwala_eiindia1 | BQ73: vineet.upadhye@ei.study | BR73: Vineet upadhye | BS73: Nisha Murali | BU73: 2024-06-06 17:06:43, 2024-06-07 13:57:53, 2024-06-07 14:36:21 | BV73: Mrs. Pushkala Parasuraman | BW73: Principal | BX73: pushkala.parasuraman@kumarans.org | BY73: +919880285585 | BZ73: cbse@kumarans.org | CA73: Mrs. Pushkala Parasuraman | CB73: pushkala.parasuraman@kumarans.org | CC73: +919880285585 | CG73: 0 | CH73: Survey no.44-50, Malla Sandra Village, Uttarahalli, Hobli, Kanakapura Main Road | CJ73: 560109 | CK73: Survey no.44-50, Malla Sandra Village, Uttarahalli, Hobli, Kanakapura Main Road | CL73: Bengaluru | CM73: Karnataka | CN73: 560109 | CO73: BLRS02358G | CP73: Survey no.44-50, Malla Sandra Village, Uttarahalli, Hobli, Kanakapura Main Road | CQ73: Survey no.44-50, Malla Sandra Village, Uttarahalli, Hobli, Kanakapura Main Road
A74: New School | B74: 19028 | C74: Delhi Public School, R.K. Puram | D74: =VLOOKUP(B74,'2025'!B:C,2,0) -> Chaitanya | F74: 2024 | G74: 2024-04-04 00:00:00, 2024-08-21 00:00:00, 2024-10-12 00:00:00 | H74: Ei ASSET, Ei Teacher Training | I74: Regular | J74: 190282024.00, IN-2022002449, IN-2022002518 | K74: Approved By Logistic Team | L74: 400000 | M74: 472000 | N74: 0 | O74: 1785 | P74: 0 | Q74: 0 | R74: 0 | S74: 0 | T74: 0 | U74: 0 | V74: 0 | W74: 0, 400000 | X74: Full Payment, Installments | Y74: 1, 3 | Z74: 2024-04-04 00:00:00, 2024-10-12 00:00:00 | AA74: 2000-01-01 00:00:00, 2024-04-04 00:00:00, 2024-08-21 00:00:00 | AB74: 0 | AC74: 2000-01-01 00:00:00, 2024-04-04 00:00:00, 2024-11-15 00:00:00 | AD74: 0 | AE74: 2000-01-01 00:00:00, 2024-04-04 00:00:00, 2024-12-23 00:00:00 | AF74: 0 | AG74: 2000-01-01 00:00:00, 2024-04-04 00:00:00 | AH74: 0 | AI74: 0 | AJ74: 2024-04-04 00:00:00 | AK74: 2024-04-04 00:00:00 | AL74: 0, 400000 | AM74: 0 | AN74: 0, 400000 | AO74: 0, 1 | AP74: 0, 1 | AQ74: 0 | AR74: 0 | AS74: 0 | AT74: 0 | AU74: 0, Summer Round, Winter Round | AV74: OMR, Online | AW74: 0 | AX74: MCQ | BB74: CBSE | BC74: New Delhi | BD74: Delhi | BE74: North | BF74: Delhi/Haryana | BG74: National Sales | BH74: 2024-04-01 00:00:00, 2024-04-04 00:00:00, 2024-10-01 00:00:00 | BI74: 2024-04-04 00:00:00, 2025-03-31 00:00:00 | BJ74: Regular School: Active school with student count and rate per student defined, Regular School: Active school with teacher count and rate per teacher defined | BK74: 190282024, 22028000024247204, 22028000025435300 | BL74: 51788000002728655 | BM74: zcrm_51788000272998201 | BN74: 2024-04-04 00:00:00, 2024-08-21 00:00:00, 2024-10-12 00:00:00 | BO74: maruf.shaikh1, maruf.shaikh@ei.study, vibhor.tyagi_ei | BP74: maruf.shaikh1, maruf.shaikh@ei.study, sourabh.mehta_eiindia | BQ74: maruf.shaikh@ei.study, vibhor.tyagi@ei.study | BR74: Maruf shaikh, Vibhor tyagi | BS74: Vibhor Tyagi | BT74: Chaitanya Kolluri, Vibhor Tyagi | BU74: 2024-04-04 00:00:00, 2024-08-21 16:03:32, 2024-10-12 11:36:50 | BV74: Mr. Mukesh Kumar, Padma Srinvisan | BW74: Principal | BX74: maruf.shaikh@ei.study | BY74: +919016039311, +919811685099 | BZ74: principal@dpsrkp.net | CA74: Mr. Mukesh Kumar | CB74: maruf.shaikh@ei.study | CC74: +919811685099 | CD74: Mr. Mukesh Kumar | CE74: maruf.shaikh@ei.study | CF74: +919811685099 | CG74: 0, 107000 | CH74: Sector-XII, R.K. Puram, ,New Delhi,Delhi - 110022 | CJ74: 110022 | CK74: Sector-XII, R.K. Puram, ,New Delhi,Delhi - 110022 | CL74: New Delhi | CM74: DELHI | CN74: 110022 | CP74: Sector-XII, R.K. Puram, ,New Delhi,Delhi - 110022 | CQ74: Sector-XII, R.K. Puram, ,New Delhi,Delhi - 110022
A75: Retention School | B75: 19282 | C75: Sri Kumaran Children^s Home | D75: =VLOOKUP(B75,'2025'!B:C,2,0) -> Aruna | F75: 2024 | G75: 2024-05-27 00:00:00, 2024-08-06 00:00:00 | H75: Ei ASSET, Ei Mindspark | I75: Regular | J75: IN-2022002103, IN-2022002403 | K75: Approved By Logistic Team | L75: 543686 | M75: 596694 | N75: 249199 | O75: 498 | P75: 500 | Q75: 0 | R75: 0 | T75: 294487 | U75: 139 | V75: 2119 | W75: 0 | X75: Full Payment, Installments | Y75: 4 | Z75: 2024-08-06 00:00:00 | AA75: 2000-01-01 00:00:00, 2024-06-15 00:00:00 | AB75: 0, 86874 | AC75: 2000-01-01 00:00:00, 2024-08-15 00:00:00 | AD75: 0, 86874 | AE75: 2000-01-01 00:00:00, 2024-10-15 00:00:00 | AF75: 0, 86874 | AG75: 2000-01-01 00:00:00, 2024-12-15 00:00:00 | AH75: 0, 86874 | AI75: 0, 45893 | AJ75: 2024-08-20 00:00:00 | AK75: 2024-08-20 00:00:00, 2024-12-20 00:00:00 | AL75: 249199, 347496 | AM75: 547082, 78187 | AN75: -245479, 171012 | AO75: 0.3056, 0.583 | AP75: 0.3056, 0.583 | AU75: 0, Summer Round | AV75: Online | AW75: 0 | AX75: MCQ | BA75: Online | BB75: State Board | BC75: Bengaluru | BD75: Karnataka | BE75: South | BF75: Karnataka/Kerala | BG75: National Sales | BH75: 2024-06-01 00:00:00 | BI75: 2025-05-31 00:00:00 | BJ75: Regular School: Active school with student count and rate per student defined | BK75: 22028000022677168, 22028000023978072 | BL75: 51788000002728657 | BM75: zcrm_51788000270080153, zcrm_51788000272593001 | BN75: 2024-05-27 00:00:00, 2024-08-06 00:00:00 | BO75: aruna_ei, vineet.upadhye_ei | BP75: mitul.patel_ei1 | BQ75: aruna@ei.study, vineet.upadhye@ei.study | BR75: Aruna, Vineet upadhye | BS75: Aruna | BU75: 2024-06-06 17:20:39, 2024-08-13 10:28:39 | BV75: Mrs. Nandashree Natarajan | BW75: Principal | BX75: Nandashree.Natarajan@kumarans.org | BY75: +919980922071 | BZ75: jasper.jessie@ei.study | CA75: Mrs. Nandashree Natarajan | CB75: Nandashree.Natarajan@kumarans.org | CC75: +919980922071 | CG75: 0 | CH75: 6Th Main Tata Silk Farm,Basavangudi, Bengaluru, Karnataka | CJ75: 560004 | CK75: 6Th Main Tata Silk Farm,Basavangudi, Bengaluru, Karnataka | CL75: Bengaluru | CM75: Karnataka | CN75: 560004 | CO75: BLRS02358G | CP75: 6Th Main Tata Silk Farm,Basavangudi, Bengaluru, Karnataka | CQ75: 6Th Main Tata Silk Farm,Basavangudi, Bengaluru, Karnataka
A76: Key Account | B76: 1933 | C76: Anand Niketan, Shilaj | D76: =VLOOKUP(B76,'2025'!B:C,2,0) -> Ishita Jethwa | F76: 2024 | G76: 2024-04-24 00:00:00 | H76: Ei CARES | I76: Regular | J76: IN-2022001958 | K76: Approved By Logistic Team | L76: 1739243 | M76: 1739243 | N76: 0 | O76: 0 | Q76: 1739243 | R76: 1023 | S76: 1700 | T76: 0 | U76: 0 | W76: 0 | X76: Installments | Y76: 2 | AA76: 2024-04-30 00:00:00 | AB76: 869622 | AC76: 2024-09-14 00:00:00 | AD76: 869622 | AE76: 2000-01-01 00:00:00 | AF76: 0 | AG76: 2000-01-01 00:00:00 | AH76: 0 | AI76: 261226 | AJ76: 2024-05-06 00:00:00 | AK76: 2024-12-20 00:00:00 | AL76: 1739244 | AM76: 1568380 | AN76: -90362 | AO76: 0.3461 | AP76: 0.3461 | AU76: 0 | AW76: 4 | AX76: MCQ | AY76: Printing By EI | AZ76: OMR | BB76: ICSE | BC76: AHMEDABAD | BD76: Gujarat | BE76: West | BF76: Gujarat | BG76: National Sales | BH76: 2024-06-01 00:00:00 | BI76: 2025-05-31 00:00:00 | BJ76: Regular School: Active school with student count and rate per student defined | BK76: 22028000022235360 | BL76: 51788000002728410 | BM76: zcrm_51788000267879228 | BN76: 2024-04-24 00:00:00 | BO76: nakul.swamy_ei | BP76: fagun.saraiya_eiindia1 | BQ76: nakul.swamy@ei.study | BR76: Nakul swamy | BS76: Heena Kumar | BU76: 2024-04-25 12:48:15 | BV76: Mrs. Lamiya Shums | BW76: School Owner | BX76: lamiya.shums@anandniketan.edu.in | BY76: +919737047625 | BZ76: anshilaj@anandniketan.edu.in | CG76: 70000 | CH76: Plot no. 495, Thaltej-Shilaj Road, Near Ambli Road Railway Crossing, Shilaj, | CJ76: 380054 | CK76: Plot no. 495, Thaltej-Shilaj Road, Near Ambli Road Railway Crossing, Shilaj, | CL76: AHMEDABAD | CM76: GUJARAT | CN76: 380054 | CO76: AHMU00056A | CP76: Plot no. 495, Thaltej-Shilaj Road, Near Ambli Road Railway Crossing, Shilaj, | CQ76: Plot no. 495, Thaltej-Shilaj Road, Near Ambli Road Railway Crossing, Shilaj,
A77: New School | B77: 195591 | C77: Poorna Prajna High School | E77: Dropped | F77: 2024 | G77: 2024-11-19 00:00:00 | H77: Ei ASSET | I77: Regular | J77: IN-2022002595 | K77: Approved By Logistic Team | L77: 224028 | M77: 224028 | N77: 224028 | O77: 280 | P77: 800 | Q77: 0 | R77: 0 | T77: 0 | U77: 0 | W77: 0 | X77: Full Payment | Z77: 2024-11-20 00:00:00 | AA77: 2000-01-01 00:00:00 | AB77: 0 | AC77: 2000-01-01 00:00:00 | AD77: 0 | AE77: 2000-01-01 00:00:00 | AF77: 0 | AG77: 2000-01-01 00:00:00 | AH77: 0 | AI77: 0 | AJ77: 2024-11-26 00:00:00 | AK77: 2024-11-26 00:00:00 | AL77: 224028 | AM77: 219520 | AN77: 4508 | AO77: 0.46659999999999996 | AP77: 0.46659999999999996 | AU77: Winter Round | AV77: OMR | AW77: 0 | AX77: MCQ | BB77: State Board | BC77: Mumbai | BD77: Maharashtra | BE77: West | BF77: Mumbai | BG77: National Sales | BH77: 2024-11-25 00:00:00 | BI77: 2025-03-31 00:00:00 | BJ77: Regular School: Active school with student count and rate per student defined | BK77: 22028000026291472 | BL77: 51788000002732868 | BM77: zcrm_51788000270632183 | BN77: 2024-11-19 00:00:00 | BO77: shahista.shaikh_ei | BP77: hakim.kanchwala_eiindia1 | BQ77: shahista.shaikh@ei.study | BR77: Shahista shaikh | BS77: Manjeetsingh Ladhad | BT77: Saloni Shah | BU77: 2024-11-23 23:09:09 | BV77: Sarvjana Udapa | BW77: Other | BX77: pphsdahisar68@ppec.edu.in | BY77: +919769998810 | BZ77: poornaprajnaec@gmail.com | CA77: Sarvjana Udapa | CB77: sarvajna.udupa@poornaprajna.org | CC77: +919769998810 | CD77: Vandana Gada | CE77: pphsdahisar68@ppec.edu.in | CF77: +918879958868 | CG77: 100000 | CH77: Bharucha Road, Dahisar East | CJ77: 400068 | CK77: Bharucha Road, Dahisar East | CL77: Mumbai | CM77: Maharashtra | CN77: 400068 | CP77: Bharucha Road, Dahisar East | CQ77: Bharucha Road, Dahisar East
A78: Retention School | B78: 19872 | C78: Padma Seshadri Bala Bhavan Senior Secondary School, K.K.Nagar | D78: =VLOOKUP(B78,'2025'!B:C,2,0) -> Vineeth T V | F78: 2024 | G78: 2024-05-31 00:00:00 | H78: Ei ASSET | I78: Regular | J78: IN-2022002131 | K78: Approved By Logistic Team | L78: 1060894 | M78: 1060894 | N78: 1060894 | O78: 2122 | P78: 500 | Q78: 0 | R78: 0 | T78: 0 | U78: 0 | W78: 0 | X78: Installments | Y78: 2 | AA78: 2024-06-10 00:00:00 | AB78: 318268 | AC78: 2024-09-01 00:00:00 | AD78: 742626 | AE78: 2000-01-01 00:00:00 | AF78: 0 | AG78: 2000-01-01 00:00:00 | AH78: 0 | AI78: 106089 | AJ78: 2024-07-09 00:00:00 | AK78: 2024-10-25 00:00:00 | AL78: 1060894 | AM78: 954799 | AN78: 6 | AO78: 0.6667000000000001 | AP78: 0.6667000000000001 | AU78: Summer Round | AV78: OMR | AW78: 0 | AX78: MCQ | BB78: CBSE | BC78: Chennai | BD78: Tamil Nadu | BE78: South | BF78: Tamil Nadu | BG78: National Sales | BH78: 2024-06-01 00:00:00 | BI78: 2025-03-31 00:00:00 | BJ78: Regular School: Active school with student count and rate per student defined | BK78: 22028000022755124 | BL78: 51788000002728663 | BM78: zcrm_51788000270168129 | BN78: 2024-05-31 00:00:00 | BO78: nisha.murali_eiindia | BP78: hakim.kanchwala_eiindia1 | BQ78: nisha.murali@ei.study | BR78: Nisha murali | BS78: Nisha Murali | BU78: 2024-06-07 18:20:01 | BV78: Mr. Mani Narayanan | BW78: Other | BX78: sragmhradmn@psbbschools.ac.in | BY78: +919840411695 | BZ78: psbbkkn@psbbschools.ac.in | CB78: principalkkn@psbbschools.ac.in | CG78: 0 | CH78: No.29, Alagiri Sami Salai, K.K.Nagar, | CJ78: 600078 | CK78: No.29, Alagiri Sami Salai, K.K.Nagar, | CL78: Chennai | CM78: Tamil Nadu | CN78: 600078 | CO78: CHEP07125G | CP78: No.29, Alagiri Sami Salai, K.K.Nagar, | CQ78: No.29, Alagiri Sami Salai, K.K.Nagar,
A79: 1-year School | B79: 199355 | C79: Shiv Ashish School | E79: Dropped | F79: 2024 | G79: 2024-10-23 00:00:00 | H79: Ei ASSET | I79: Regular | J79: IN-2022002546 | K79: Approved By Logistic Team | L79: 79380 | M79: 79380 | N79: 79380 | O79: 147 | P79: 540 | Q79: 0 | R79: 0 | T79: 0 | U79: 0 | W79: 0 | X79: Full Payment | Z79: 2024-11-11 00:00:00 | AA79: 2000-01-01 00:00:00 | AB79: 0 | AC79: 2000-01-01 00:00:00 | AD79: 0 | AE79: 2000-01-01 00:00:00 | AF79: 0 | AG79: 2000-01-01 00:00:00 | AH79: 0 | AI79: 0 | AJ79: 2024-11-29 00:00:00 | AK79: 2024-11-29 00:00:00 | AL79: 79380 | AM79: 79380 | AN79: 0 | AO79: 0.64 | AP79: 0.64 | AU79: Winter Round | AV79: OMR | AW79: 0 | AX79: MCQ | BB79: State Board | BC79: Ahmedabad | BD79: Gujarat | BE79: West | BF79: Gujarat | BG79: National Sales | BH79: 2024-10-23 00:00:00 | BI79: 2025-04-30 00:00:00 | BJ79: Regular School: Active school with student count and rate per student defined | BK79: 22028000025686032 | BL79: 51788000002732901 | BM79: zcrm_51788000275435737 | BN79: 2024-10-23 00:00:00 | BO79: nakul.swamy_ei | BP79: fagun.saraiya_eiindia1 | BQ79: nakul.swamy@ei.study | BR79: Nakul swamy | BS79: Atufa Nagori | BT79: Pooja Joshi | BU79: 2024-11-11 17:41:49 | BV79: Ms. Ashmita Pandya | BW79: Other | BX79: ashmitap@shivashish.com | BY79: +919898159928 | BZ79: ashmitap@shivashish.com | CA79: Ms. Namrata Sheth | CB79: namratas@shivashish.com | CC79: +919824180783 | CD79: Ms. Ashmita Pandya | CE79: ashmitap@shivashish.com | CF79: +919265056802 | CG79: 30000 | CH79: Inside Sterling City, Bopal, | CJ79: 380058 | CK79: Inside Sterling City, Bopal, | CL79: Ahmedabad | CM79: Gujarat | CN79: 380058 | CO79: AHMS17482D | CP79: Inside Sterling City, Bopal, | CQ79: Inside Sterling City, Bopal,
A80: Retention School | B80: 19966 | C80: Padma Seshadri Bala Bhavan Senior Secondary School | D80: =VLOOKUP(B80,'2025'!B:C,2,0) -> Vineeth T V | F80: 2024 | G80: 2024-05-31 00:00:00 | H80: Ei ASSET | I80: Regular | J80: IN-2022002130 | K80: Approved By Logistic Team | L80: 59012 | M80: 59012 | N80: 59012 | O80: 118 | P80: 500 | Q80: 0 | R80: 0 | T80: 0 | U80: 0 | W80: 0 | X80: Installments | Y80: 2 | AA80: 2024-06-10 00:00:00 | AB80: 17704 | AC80: 2024-09-01 00:00:00 | AD80: 41308 | AE80: 2000-01-01 00:00:00 | AF80: 0 | AG80: 2000-01-01 00:00:00 | AH80: 0 | AI80: 1756 | AJ80: 2024-07-30 00:00:00 | AK80: 2024-07-30 00:00:00 | AL80: 59012 | AM80: 15798 | AN80: 41458 | AO80: 0.6666 | AP80: 0.6666 | AU80: Summer Round | AV80: OMR | AW80: 0 | AX80: MCQ | BB80: CBSE | BC80: Chennai | BD80: Tamil Nadu | BE80: South | BF80: Tamil Nadu | BG80: National Sales | BH80: 2024-06-01 00:00:00 | BI80: 2025-03-31 00:00:00 | BJ80: Regular School: Active school with student count and rate per student defined | BK80: 22028000022755084 | BL80: 51788000002728664 | BM80: zcrm_51788000270168257 | BN80: 2024-05-31 00:00:00 | BO80: nisha.murali_eiindia | BP80: hakim.kanchwala_eiindia1 | BQ80: nisha.murali@ei.study | BR80: Nisha murali | BS80: Nisha Murali | BU80: 2024-06-07 18:27:27 | BV80: Mr. Mani Narayanan | BW80: Other | BX80: sragmhradmn@psbbschools.ac.in | BY80: +919840411695 | BZ80: psbbmain@yahoo.com | CB80: psbbmain@yahoo.com | CG80: 0 | CH80: No.15, Lake 1St Main Road,Nungambakkam, Chennai, Tamil Nadu | CJ80: 600034 | CK80: No.15, Lake 1St Main Road,Nungambakkam, Chennai, Tamil Nadu | CL80: Chennai | CM80: Tamil Nadu | CN80: 600034 | CO80: CHEP07125G | CP80: No.15, Lake 1St Main Road,Nungambakkam, Chennai, Tamil Nadu | CQ80: No.15, Lake 1St Main Road,Nungambakkam, Chennai, Tamil Nadu
A81: Retention School | B81: 2009619 | C81: Happy Days School | D81: =VLOOKUP(B81,'2025'!B:C,2,0) -> Rohit | F81: 2024 | G81: 2024-07-22 00:00:00 | H81: Ei CARES | I81: Regular | J81: IN-2022002364 | K81: Approved By Logistic Team | L81: 170483 | M81: 170483 | N81: 0 | O81: 0 | Q81: 170483 | R81: 262 | S81: 651 | T81: 0 | U81: 0 | W81: 0 | X81: Installments | Y81: 3 | AA81: 2024-07-24 00:00:00 | AB81: 57964 | AC81: 2024-09-25 00:00:00 | AD81: 56259 | AE81: 2024-11-30 00:00:00 | AF81: 56259 | AG81: 2000-01-01 00:00:00 | AH81: 0 | AI81: 5626 | AJ81: 2024-09-10 00:00:00 | AK81: 2025-01-31 00:00:00 | AL81: 170482 | AM81: 153434 | AN81: 11422 | AO81: 0.6385000000000001 | AP81: 0.5885 | AT81: 0.05 | AU81: 0 | AW81: 2 | AX81: MCQ + Subjective | AY81: Printing By EI | AZ81: OMR | BB81: CBSE | BC81: Shivpuri | BD81: Madhya Pradesh | BE81: North | BF81: MP/Chattisgarh | BG81: National Sales | BH81: 2024-07-01 00:00:00 | BI81: 2025-04-30 00:00:00 | BJ81: Regular School: Active school with student count and rate per student defined | BK81: 22028000023674080 | BL81: 51788000002766018 | BM81: zcrm_51788000272113181 | BN81: 2024-07-22 00:00:00 | BO81: pooja.joshi_eiindia1 | BP81: fagun.saraiya_eiindia1 | BQ81: pooja.joshi@ei.study | BR81: Pooja joshi | BS81: Rohit Kumar | BU81: 2024-07-30 10:29:06 | BV81: Vatsa Ma'am | BW81: Principal | BX81: infohappydaysschool@gmail.com | BY81: +919407230330 | BZ81: infohappydays@gmail.com | CG81: 0 | CH81: Katha Mill, A B Road Shivpuri Madhya Pradesh | CJ81: 473638 | CK81: Katha Mill, A B Road Shivpuri Madhya Pradesh | CL81: Shivpuri | CM81: Madhya Pradesh | CN81: 473638 | CO81: BPLS23960G | CP81: Katha Mill, A B Road Shivpuri Madhya Pradesh | CQ81: Katha Mill, A B Road Shivpuri Madhya Pradesh
A82: 1-year School | B82: 20191 | C82: Sishya School | D82: =VLOOKUP(B82,'2025'!B:C,2,0) -> Aruna | F82: 2024 | G82: 2024-04-29 00:00:00 | H82: Ei ASSET,Ei CARES,Ei Mindspark | I82: Regular | J82: IN-2022001970 | K82: Approved By Logistic Team | L82: 4383441 | M82: 4784194 | N82: 764356 | O82: 699 | P82: 1093 | Q82: 1392682 | R82: 796 | S82: 1750 | T82: 2226403 | U82: 1001 | V82: 2224 | W82: 0 | X82: Installments | Y82: 3 | AA82: 2024-05-10 00:00:00 | AB82: 1435258 | AC82: 2024-07-10 00:00:00 | AD82: 1674468 | AE82: 2024-11-11 00:00:00 | AF82: 1674468 | AG82: 2000-01-01 00:00:00 | AH82: 0 | AI82: 10701 | AJ82: 2024-06-15 00:00:00 | AK82: 2025-03-24 00:00:00 | AL82: 4784194 | AM82: 4724853 | AN82: 48640 | AO82: 0.271 | AP82: 0.121 | AR82: 0.05 | AS82: 0.05 | AT82: 0.05 | AU82: Winter Round | AV82: OMR | AW82: 4 | AX82: MCQ | AZ82: Online | BA82: Online | BB82: CBSE | BC82: Hosur | BD82: Tamil Nadu | BE82: South | BF82: Karnataka/Kerala | BG82: National Sales | BH82: 2024-04-15 00:00:00 | BI82: 2025-03-31 00:00:00 | BJ82: Regular School: Active school with student count and rate per student defined | BK82: 22028000022258928 | BL82: 51788000002728666 | BM82: zcrm_51788000268543049 | BN82: 2024-04-29 00:00:00 | BO82: aji.thomas_eiindia | BP82: mitul.patel_ei1 | BQ82: aji.thomas@ei.study | BR82: Aji thomas | BS82: Aruna | BU82: 2024-04-30 17:30:34 | BV82: Dr. Vasanthi Thiagarajan | BW82: Principal | BX82: vasanthi_thiag@yahoo.com | BY82: +919443285098 | BZ82: vasanthi_thiag@yahoo.com | CA82: Dr. Vasanthi Thiagarajan | CB82: vasanthi_thiag@yahoo.com | CC82: +919443285098 | CG82: 104000 | CH82: Thally Road, Near Railway Gate, | CJ82: 635109 | CK82: Thally Road, Near Railway Gate, | CL82: Hosur | CM82: Tamil Nadu | CN82: 635109 | CO82: CHES17432C | CP82: Thally Road, Near Railway Gate, | CQ82: Thally Road, Near Railway Gate,
A83: New School | B83: 202033 | C83: Vivekananda Educational Centre | D83: =VLOOKUP(B83,'2025'!B:C,2,0) -> Aruna | F83: 2024 | G83: 2024-02-20 00:00:00 | H83: Ei ASSET | I83: Regular | J83: IN-2022001532 | K83: Approved By Logistic Team | L83: 201600 | M83: 201600 | N83: 201600 | O83: 168 | P83: 1200 | Q83: 0 | R83: 0 | T83: 0 | U83: 0 | W83: 0 | X83: Installments | Y83: 2 | AA83: 2024-05-01 00:00:00 | AB83: 100800 | AC83: 2024-07-31 00:00:00 | AD83: 100800 | AE83: 2000-01-01 00:00:00 | AF83: 0 | AG83: 2000-01-01 00:00:00 | AH83: 0 | AI83: 0 | AJ83: 2024-06-11 00:00:00 | AK83: 2024-12-07 00:00:00 | AL83: 201600 | AM83: 213600 | AN83: -12000 | AO83: 0.2 | AP83: 0.2 | AU83: Summer Round | AV83: OMR | AW83: 0 | AX83: MCQ | BB83: CISCE | BC83: Bengaluru | BD83: Karnataka | BE83: South | BF83: Karnataka/Kerala | BG83: National Sales | BH83: 2024-06-01 00:00:00 | BI83: 2025-04-10 00:00:00 | BJ83: Regular School: Active school with student count and rate per student defined | BK83: 22028000021135664 | BL83: 51788000002733023 | BM83: zcrm_51788000264841071 | BN83: 2024-02-20 00:00:00 | BO83: garima.jain_ei | BP83: sourabh.mehta_eiindia | BQ83: garima.jain@ei.study | BR83: Garima jain | BS83: Garima Jain | BU83: 2024-03-22 10:24:09 | BV83: Mr. Ravi Shankar | BW83: Principal | BX83: principalvecjnr@edu.in | BY83: +919620193734 | BZ83: vec.jnr@gmail.com | CA83: Mr. Ravi Shankar | CB83: principalvecjnr@edu.in | CC83: +919620193734 | CD83: Mr. Ravi Shankar | CE83: principalvecjnr@edu.in | CF83: +919620193734 | CG83: 64000 | CH83: 4Th Block East Jayanagar BENGALURU-560 011 | CJ83: 560011 | CK83: 4Th Block East Jayanagar BENGALURU-560 011 | CL83: Bengaluru | CM83: Karnataka | CN83: 560011 | CP83: 4Th Block East Jayanagar BENGALURU-560 011 | CQ83: 4Th Block East Jayanagar BENGALURU-560 011
A84: Retention School | B84: 20238 | C84: The Daly College | D84: =VLOOKUP(B84,'2025'!B:C,2,0) -> Shruti | F84: 2024 | G84: 2024-05-07 00:00:00 | H84: Ei Mindspark | I84: Regular | J84: IN-2022002025 | K84: Approved By Logistic Team | L84: 1909789 | M84: 2253551 | N84: 0 | O84: 0 | Q84: 0 | R84: 0 | T84: 1909789 | U84: 950 | V84: 2010 | W84: 0 | X84: Full Payment | Z84: 2024-05-01 00:00:00 | AA84: 2000-01-01 00:00:00 | AB84: 0 | AC84: 2000-01-01 00:00:00 | AD84: 0 | AE84: 2000-01-01 00:00:00 | AF84: 0 | AG84: 2000-01-01 00:00:00 | AH84: 0 | AI84: 38157 | AJ84: 2024-09-10 00:00:00 | AK84: 2024-09-10 00:00:00 | AL84: 2253551 | AM84: 2213049 | AN84: 2345 | AO84: 0.3411 | AP84: 0.3411 | AU84: 0 | AW84: 0 | AX84: MCQ | BA84: Online | BB84: CBSE | BC84: Indore | BD84: Madhya Pradesh | BE84: North | BF84: MP/Chattisgarh | BG84: National Sales | BH84: 2024-04-20 00:00:00 | BI84: 2025-03-31 00:00:00 | BJ84: Regular School: Active school with student count and rate per student defined | BK84: 22028000022382800 | BL84: 51788000002728667 | BM84: zcrm_51788000269123172 | BN84: 2024-05-07 00:00:00 | BO84: shruti.chauhan_ei | BP84: fagun.saraiya_eiindia1 | BQ84: shruti.chauhan@ei.study | BR84: Shruti chauhan | BS84: Shruti Chauhan | BU84: 2024-05-08 07:23:43 | BV84: Gurmeet Bindra | BW84: Principal | BX84: fagun.saraiya@ei.study | BY84: +917312719001 | BZ84: principal@dalycollege.org | CA84: Gurmeet Bindra | CB84: fagun.saraiya@ei.study | CC84: +917312719001 | CD84: Naresh Verma | CE84: naresh.verma@dalycollege.org | CF84: +919926993699 | CG84: 0 | CH84: Residency Area, Indore, Madhya Pradesh | CJ84: 452001 | CK84: Residency Area, Indore, Madhya Pradesh | CL84: Indore | CM84: Madhya Pradesh | CN84: 452001 | CO84: BPLT00735A | CP84: Residency Area, Indore, Madhya Pradesh | CQ84: Residency Area, Indore, Madhya Pradesh
A85: New School | B85: 202559 | C85: Amara Jyothi Public School | E85: Dropped | F85: 2024 | G85: 2024-03-20 00:00:00 | H85: Ei ASSET | I85: Regular | J85: IN-2022001704 | K85: Approved By Logistic Team | L85: 243960 | M85: 243960 | N85: 243960 | O85: 271 | P85: 900 | Q85: 0 | R85: 0 | T85: 0 | U85: 0 | W85: 0 | X85: Installments | Y85: 2 | AA85: 2024-03-21 00:00:00 | AB85: 121980 | AC85: 2024-06-24 00:00:00 | AD85: 121980 | AE85: 2000-01-01 00:00:00 | AF85: 0 | AG85: 2000-01-01 00:00:00 | AH85: 0 | AI85: 14458 | AJ85: 2024-03-28 00:00:00 | AK85: 2025-01-24 00:00:00 | AL85: 243960 | AM85: 229501 | AN85: 1 | AO85: 0.5262 | AP85: 0.5262 | AU85: Summer Round | AV85: OMR | AW85: 0 | AX85: MCQ | BB85: CBSE | BC85: Bengaluru | BD85: Karnataka | BE85: South | BF85: Karnataka/Kerala | BG85: National Sales | BH85: 2024-04-01 00:00:00 | BI85: 2025-03-31 00:00:00 | BJ85: Regular School: Active school with student count and rate per student defined | BK85: 22028000021650052 | BL85: 51788000002733026 | BM85: zcrm_51788000262825426 | BN85: 2024-03-20 00:00:00 | BO85: garima.jain_ei | BP85: mitul.patel_ei1 | BQ85: garima.jain@ei.study | BR85: Garima jain | BS85: Nebu Abraham | BT85: Aruna | BU85: 2024-03-28 12:48:50 | BV85: Mrs. Geetha Somanathan | BW85: Principal | BX85: principal@amarajyothipublicschool.edu.in | BY85: +919448074384 | BZ85: principal@amarajyothipublicschool.edu.in | CA85: Mrs. Geetha Somanathan | CB85: principal@amarajyothipublicschool.edu.in | CC85: +919448074384 | CD85: Ms. Anjana Pal | CE85: secondarycoordinator@amarajyothipublicschool.edu.in | CF85: +919986365095 | CG85: 93000 | CH85: Basavanapura Main Road, Devasandra,Near Silicon City College, Krishnarajapura, Bengaluru, Karnataka | CJ85: 560036 | CK85: Basavanapura Main Road, Devasandra,Near Silicon City College, Krishnarajapura, Bengaluru, Karnataka | CL85: Bengaluru | CM85: KARNATAKA | CN85: 560036 | CO85: BLRA11481B | CP85: Basavanapura Main Road, Devasandra,Near Silicon City College, Krishnarajapura, Bengaluru, Karnataka | CQ85: Basavanapura Main Road, Devasandra,Near Silicon City College, Krishnarajapura, Bengaluru, Karnataka
A86: Retention School | B86: 20480 | C86: Queens College | D86: =VLOOKUP(B86,'2025'!B:C,2,0) -> Shruti | F86: 2024 | G86: 2024-05-07 00:00:00 | H86: Ei CARES | I86: Regular | J86: IN-2022002023 | K86: Approved By Logistic Team | L86: 1295640 | M86: 1295640 | N86: 0 | O86: 0 | Q86: 1295640 | R86: 708 | S86: 1830 | T86: 0 | U86: 0 | W86: 0 | X86: Installments | Y86: 3 | AA86: 2024-05-08 00:00:00 | AB86: 440518 | AC86: 2024-07-01 00:00:00 | AD86: 427561 | AE86: 2024-10-01 00:00:00 | AF86: 427561 | AG86: 2000-01-01 00:00:00 | AH86: 0 | AI86: 85648 | AJ86: 2024-06-26 00:00:00 | AK86: 2025-06-19 00:00:00 | AL86: 1295640 | AM86: 1159487 | AN86: 50505 | AO86: 0.634 | AP86: 0.634 | AU86: 0 | AW86: 8 | AX86: MCQ | AY86: Printing By School | AZ86: OMR | BB86: CBSE | BC86: Indore | BD86: Madhya Pradesh | BE86: North | BF86: MP/Chattisgarh | BG86: National Sales | BH86: 2024-04-01 00:00:00 | BI86: 2025-03-31 00:00:00 | BJ86: Regular School: Active school with student count and rate per student defined | BK86: 22028000022382712 | BL86: 51788000002728669 | BM86: zcrm_51788000269123411 | BN86: 2024-05-07 00:00:00 | BO86: shruti.chauhan_ei | BP86: fagun.saraiya_eiindia1 | BQ86: shruti.chauhan@ei.study | BR86: Shruti chauhan | BS86: Shruti Chauhan | BU86: 2024-05-08 09:10:08 | BV86: Geetha Somasekharan | BW86: Principal | BX86: queenscollegeindore@gmail.com | BY86: +917902381681 | BZ86: queenscollegeindore@rediffmail.com | CA86: Geetha Somasekharan | CB86: queenscollegeindore@gmail.com | CC86: +917902381681 | CD86: Sumit Sahu | CE86: sumeet.sahu@queenscollegeindore.org | CF86: +918103405051 | CG86: 0 | CH86: Khandwa Road, Post Kasturba Gram, | CJ86: 452017 | CK86: Khandwa Road, Post Kasturba Gram, | CL86: Indore | CM86: Madhya Pradesh | CN86: 452017 | CO86: BPLD00937G | CP86: Khandwa Road, Post Kasturba Gram, | CQ86: Khandwa Road, Post Kasturba Gram,
A87: Retention School | B87: 205449 | C87: The Riverside School | D87: =VLOOKUP(B87,'2025'!B:C,2,0) -> Ishita Jethwa | F87: 2024 | G87: 2024-02-21 00:00:00, 2024-03-11 00:00:00 | H87: Ei ASSET, Ei Mindspark | I87: Regular | J87: IN-2022001534, IN-2022001602 | K87: Approved By Logistic Team | L87: 547326 | M87: 593457 | N87: 291042 | O87: 240 | P87: 1213 | Q87: 0 | R87: 0 | T87: 256284 | U87: 120 | V87: 2136 | W87: 0 | X87: Installments | Y87: 2, 4 | AA87: 2024-03-11 00:00:00, 2024-03-20 00:00:00 | AB87: 75604, 87313 | AC87: 2024-06-30 00:00:00, 2024-10-31 00:00:00 | AD87: 203729, 75604 | AE87: 2000-01-01 00:00:00, 2024-09-09 00:00:00 | AF87: 0, 75604 | AG87: 2000-01-01 00:00:00, 2024-11-20 00:00:00 | AH87: 0, 75604 | AI87: 3843, 6036 | AJ87: 2024-03-29 00:00:00, 2024-04-10 00:00:00 | AK87: 2024-11-21 00:00:00, 2025-09-12 00:00:00 | AL87: 291042, 302416 | AM87: 295755, 296749 | AN87: -10749, 1824 | AO87: 0.126, 0.3 | AP87: 0.076, 0.25 | AT87: 0.05 | AU87: 0, Winter Round | AV87: Online | AW87: 0 | AX87: MCQ | BA87: Online | BB87: CISCE | BC87: Ahmedabad | BD87: Gujarat | BE87: West | BF87: Gujarat | BG87: National Sales | BH87: 2024-04-01 00:00:00 | BI87: 2025-03-31 00:00:00 | BJ87: Regular School: Active school with student count and rate per student defined | BK87: 22028000021151528, 22028000021468424 | BL87: 51788000002733052 | BM87: zcrm_51788000265590001, zcrm_51788000266645003 | BN87: 2024-02-21 00:00:00, 2024-03-11 00:00:00 | BO87: pooja.joshi_eiindia1 | BP87: fagun.saraiya_eiindia1 | BQ87: pooja.joshi@ei.study | BR87: Pooja joshi | BS87: Ishita Jethwa | BU87: 2024-02-28 17:58:05, 2024-04-01 17:29:23 | BV87: Ritu Agrawal | BW87: Other | BX87: ritu@schoolriverside.com | BY87: +919824804026, +919879475569 | BZ87: inquiry@schoolriverside.com | CG87: 0 | CH87: 307, Behind C.S.D Depot, Off Airport Road, Cantonment | CJ87: 380004 | CK87: 307, Behind C.S.D Depot, Off Airport Road, Cantonment | CL87: Ahmedabad | CM87: Gujarat | CN87: 380004 | CO87: AHMR02519G | CP87: 307, Behind C.S.D Depot, Off Airport Road, Cantonment | CQ87: 307, Behind C.S.D Depot, Off Airport Road, Cantonment
A88: 1-year School | B88: 2057359 | C88: N. H. Goel World School | D88: =VLOOKUP(B88,'2025'!B:C,2,0) -> Rohit | F88: 2024 | G88: 2024-04-16 00:00:00 | H88: Ei CARES | I88: Regular | J88: IN-2022001917 | K88: Approved By Logistic Team | L88: 932910 | M88: 932910 | N88: 0 | O88: 0 | Q88: 932910 | R88: 533 | S88: 1750 | T88: 0 | U88: 0 | W88: 0 | X88: Installments | Y88: 2 | AA88: 2024-04-22 00:00:00 | AB88: 466455 | AC88: 2024-11-25 00:00:00 | AD88: 466455 | AE88: 2000-01-01 00:00:00 | AF88: 0 | AG88: 2000-01-01 00:00:00 | AH88: 0 | AI88: 19463 | AJ88: 2024-06-21 00:00:00 | AK88: 2024-12-17 00:00:00 | AL88: 932910 | AM88: 953704 | AN88: -40257 | AO88: 0.239 | AP88: 0.239 | AU88: 0 | AW88: 4 | AX88: MCQ + Subjective | AY88: Printing By EI | AZ88: OMR | BB88: CBSE | BC88: Raipur | BD88: Chhattisgarh | BE88: North | BF88: MP/Chattisgarh | BG88: National Sales | BH88: 2024-06-01 00:00:00 | BI88: 2025-04-30 00:00:00 | BJ88: Regular School: Active school with student count and rate per student defined | BK88: 22028000022101848 | BL88: 51788000002767001 | BM88: zcrm_51788000268529381 | BN88: 2024-04-16 00:00:00 | BO88: sandeep.jain_eiindia1 | BP88: fagun.saraiya_eiindia1 | BQ88: sandeep.jain@ei.study | BR88: Sandeep jain | BS88: Rohit Kumar | BU88: 2024-04-19 12:42:26 | BV88: Mr. Vinod Sir | BW88: Admin | BX88: nhps@gmail.com | BY88: +919754944903 | BZ88: principal@nhgoel.com | CG88: 18000 | CH88: Post Nardaha, Near Pura Project, Vidhan Sabha Road, | CJ88: 493111 | CK88: Post Nardaha, Near Pura Project, Vidhan Sabha Road, | CL88: Raipur | CM88: Chhattisgarh | CN88: 493111 | CO88: JBPJ01094C | CP88: Post Nardaha, Near Pura Project, Vidhan Sabha Road, | CQ88: Post Nardaha, Near Pura Project, Vidhan Sabha Road,
A89: New School | B89: 20577 | C89: Ahmedabad International School | D89: =VLOOKUP(B89,'2025'!B:C,2,0) -> Unnati Sharma | F89: 2024 | G89: 2024-01-07 00:00:00 | H89: Ei Mindspark | I89: Regular | J89: IN-2022001387 | K89: Approved By Logistic Team | L89: 1058697 | M89: 1249262 | N89: 0 | O89: 0 | Q89: 0 | R89: 0 | T89: 1058697 | U89: 694 | V89: 1526 | W89: 0 | X89: Full Payment | Z89: 2024-04-01 00:00:00 | AA89: 2000-01-01 00:00:00 | AB89: 0 | AC89: 2000-01-01 00:00:00 | AD89: 0 | AE89: 2000-01-01 00:00:00 | AF89: 0 | AG89: 2000-01-01 00:00:00 | AH89: 0 | AI89: 0 | AJ89: 2024-05-27 00:00:00 | AK89: 2024-05-27 00:00:00 | AL89: 1249262 | AM89: 1235654 | AN89: 13608 | AO89: 0.5 | AP89: 0.5 | AU89: 0 | AW89: 0 | AX89: MCQ | BA89: Online | BB89: Cambridge | BC89: Ahmedabad | BD89: Gujarat | BE89: West | BF89: Gujarat | BG89: National Sales | BH89: 2024-06-01 00:00:00 | BI89: 2025-05-31 00:00:00 | BJ89: Regular School: Active school with student count and rate per student defined | BK89: 22028000020549828 | BL89: 51788000002728670 | BM89: zcrm_51788000262266171 | BN89: 2024-01-07 00:00:00 | BO89: nakul.swamy_ei | BP89: fagun.saraiya_eiindia1 | BQ89: nakul.swamy@ei.study | BR89: Nakul swamy | BS89: Nakul Swamy | BU89: 2024-01-08 10:53:49 | BV89: Mr. Deepanshu Arora | BW89: School Owner | BX89: deepanshu@aischool.net | BY89: +919999158550 | BZ89: pradnya.mehta@aisschool.net | CG89: 449000 | CH89: Opposite Rajpath Row House, Behind Kiran Motors, Judges Bunglow Road, Bodakdev, | CJ89: 380054 | CK89: Opposite Rajpath Row House, Behind Kiran Motors, Judges Bunglow Road, Bodakdev, | CL89: Ahmedabad | CM89: Gujarat | CN89: 380054 | CO89: AHMJ00139G | CP89: Opposite Rajpath Row House, Behind Kiran Motors, Judges Bunglow Road, Bodakdev, | CQ89: Opposite Rajpath Row House, Behind Kiran Motors, Judges Bunglow Road, Bodakdev,
A90: New School | B90: 206357 | C90: Delhi Public School, Bangalore - North | E90: Dropped | F90: 2024 | G90: 2024-03-13 00:00:00 | H90: Ei ASSET | I90: Regular | J90: IN-2022001642 | K90: Approved By Logistic Team | L90: 920908 | M90: 920908 | N90: 920908 | O90: 1842 | P90: 500 | Q90: 0 | R90: 0 | T90: 0 | U90: 0 | W90: 0 | X90: Installments | Y90: 2 | AA90: 2024-03-15 00:00:00 | AB90: 276272 | AC90: 2024-11-15 00:00:00 | AD90: 644636 | AE90: 2000-01-01 00:00:00 | AF90: 0 | AG90: 2000-01-01 00:00:00 | AH90: 0 | AI90: 5819 | AJ90: 2024-08-23 00:00:00 | AK90: 2025-02-24 00:00:00 | AL90: 920908 | AM90: 902497 | AN90: 12592 | AO90: 0.6667000000000001 | AP90: 0.6667000000000001 | AU90: Winter Round | AV90: OMR | AW90: 0 | AX90: MCQ | BB90: CBSE | BC90: Bengaluru | BD90: Karnataka | BE90: South | BF90: Karnataka/Kerala | BG90: National Sales | BH90: 2024-04-01 00:00:00 | BI90: 2025-03-31 00:00:00 | BJ90: Regular School: Active school with student count and rate per student defined | BK90: 22028000021544208 | BL90: 51788000002733060 | BM90: zcrm_51788000266748714 | BN90: 2024-03-13 00:00:00 | BO90: aji.thomas_eiindia | BP90: mitul.patel_ei1 | BQ90: aji.thomas@ei.study | BR90: Aji thomas | BS90: Aji Thomas | BT90: Dipti Jain | BU90: 2024-03-16 10:09:21 | BV90: Ms. Manju Balasubramanyam | BW90: Principal | BX90: principal@north.dpsbangalore.edu.in | BY90: +919880340433 | BZ90: manjuarif@gmail.com | CA90: Ms. Manju Balasubramanyam | CB90: principal@north.dpsbangalore.edu.in | CC90: +919880340433 | CG90: 100000 | CH90: Survey No. 35/1, ^A^, Sathanur Village, Post Off Bellary Road, Bagalur, Jala Hobli, Bangalore North, | CJ90: 562149 | CK90: Survey No. 35/1, ^A^, Sathanur Village, Post Off Bellary Road, Bagalur, Jala Hobli, Bangalore North, | CL90: Bengaluru | CM90: KARNATAKA | CN90: 562149 | CO90: BLRK01734F | CP90: Survey No. 35/1, ^A^, Sathanur Village, Post Off Bellary Road, Bagalur, Jala Hobli, Bangalore North, | CQ90: Survey No. 35/1, ^A^, Sathanur Village, Post Off Bellary Road, Bagalur, Jala Hobli, Bangalore North,
A91: 1-year School | B91: 2066385 | C91: Sanghamitra High School | F91: 2024 | G91: 2024-03-22 00:00:00 | H91: Ei CARES | I91: Regular | J91: IN-2022001718 | K91: Approved By Logistic Team | L91: 1046068 | M91: 1046068 | N91: 0 | O91: 0 | Q91: 1046068 | R91: 804 | S91: 1301 | T91: 0 | U91: 0 | W91: 0 | X91: Installments | Y91: 4 | AA91: 2024-06-30 00:00:00 | AB91: 261517 | AC91: 2024-09-30 00:00:00 | AD91: 261517 | AE91: 2024-11-30 00:00:00 | AF91: 261517 | AG91: 2024-12-31 00:00:00 | AH91: 261517 | AI91: 0 | AJ91: 2024-08-23 00:00:00 | AK91: 2025-03-21 00:00:00 | AL91: 1046068 | AM91: 1108193 | AN91: -62125 | AO91: 0.7043 | AP91: 0.7043 | AU91: 0 | AW91: 4 | AX91: MCQ | AY91: Printing By EI | AZ91: OMR | BB91: CBSE | BC91: Zaheerabad | BD91: Telangana | BE91: South | BF91: AP/Telangana | BG91: National Sales | BH91: 2024-06-25 00:00:00 | BI91: 2025-03-31 00:00:00 | BJ91: Regular School: Active school with student count and rate per student defined | BK91: 22028000021670488 | BL91: 51788000002767190 | BM91: zcrm_51788000267248421 | BN91: 2024-03-22 00:00:00 | BO91: pavan.kumar_ei | BP91: hakim.kanchwala_eiindia1 | BQ91: pavan.kumar@ei.study | BR91: Pavan kumar | BS91: Jasper Jessie | BU91: 2024-04-24 11:16:20 | BV91: Mr. Sandeep Reddy | BW91: School Owner | BX91: vanterusabitha@gmail.com | BY91: +919849046131 | BZ91: info@sanghamitraschool.in | CG91: 47600 | CH91: 1-6-108 | CJ91: 502220 | CK91: 1-6-108 | CL91: Zaheerabad | CM91: Telangana | CN91: 502220 | CP91: 1-6-108 | CQ91: 1-6-108
A92: New School | B92: 207093 | C92: Advanced Academy | D92: =VLOOKUP(B92,'2025'!B:C,2,0) -> Shruti | F92: 2024 | G92: 2024-02-19 00:00:00 | H92: Ei CARES | I92: Regular | J92: IN-2022001516 | K92: Approved By Logistic Team | L92: 894596 | M92: 894596 | N92: 0 | O92: 0 | Q92: 894596 | R92: 395 | S92: 2265 | T92: 0 | U92: 0 | W92: 0 | X92: Installments | Y92: 4 | AA92: 2024-02-21 00:00:00 | AB92: 223649 | AC92: 2024-07-02 00:00:00 | AD92: 223649 | AE92: 2024-10-02 00:00:00 | AF92: 223649 | AG92: 2024-12-30 00:00:00 | AH92: 223649 | AI92: 57143 | AJ92: 2024-02-27 00:00:00 | AK92: 2025-01-10 00:00:00 | AL92: 894596 | AM92: 688440 | AN92: 149013 | AO92: 0.40399999999999997 | AP92: 0.40399999999999997 | AU92: 0 | AW92: 6 | AX92: MCQ | AY92: Printing By EI | AZ92: OMR | BB92: CBSE | BC92: Indore | BD92: Madhya Pradesh | BE92: North | BF92: MP/Chattisgarh | BG92: National Sales | BH92: 2024-03-15 00:00:00 | BI92: 2025-03-29 00:00:00 | BJ92: Regular School: Active school with student count and rate per student defined | BK92: 22028000021126168 | BL92: 51788000002733064 | BM92: zcrm_51788000254430449 | BN92: 2024-02-19 00:00:00 | BO92: Laxminarayan Dogayan | BP92: fagun.saraiya_eiindia1 | BQ92: laxminarayan.dogayan@ei.study | BR92: Laxminarayan dogayan | BS92: Laxminarayan Dogayan | BU92: 2024-02-22 11:40:31 | BV92: Usha Tomar | BW92: Principal | BX92: advancedindore@gmail.com | BY92: +917415666686 | BZ92: advancedindore@gmail.com | CA92: Usha Tomar | CB92: advancedindore@gmail.com | CC92: +917415666686 | CD92: Mrs. Swati Gupta | CE92: advancedindore@gmail.com | CF92: +916264289406 | CG92: 71203 | CH92: Isckon Vihar Colony, Nipania Road | CJ92: 452001 | CK92: Isckon Vihar Colony, Nipania Road | CL92: Indore | CM92: Madhya Pradesh | CN92: 452001 | CO92: BPLL02824D | CP92: Isckon Vihar Colony, Nipania Road | CQ92: Isckon Vihar Colony, Nipania Road
A93: Retention School | B93: 207682 | C93: Asian Christian High School | F93: 2024 | G93: 2024-04-22 00:00:00 | H93: Ei ASSET | I93: Regular | J93: IN-2022001955 | K93: Approved By Logistic Team | L93: 540323 | M93: 540323 | N93: 540323 | O93: 1544 | P93: 350 | Q93: 0 | R93: 0 | T93: 0 | U93: 0 | W93: 0 | X93: Full Payment | Z93: 2024-04-15 00:00:00 | AA93: 2000-01-01 00:00:00 | AB93: 0 | AC93: 2000-01-01 00:00:00 | AD93: 0 | AE93: 2000-01-01 00:00:00 | AF93: 0 | AG93: 2000-01-01 00:00:00 | AH93: 0 | AI93: 10715 | AJ93: 2024-04-30 00:00:00 | AK93: 2024-04-30 00:00:00 | AL93: 540323 | AM93: 525058 | AN93: 4550 | AO93: 0.7667 | AP93: 0.7667 | AU93: Winter Round | AV93: OMR | AW93: 0 | AX93: MCQ | BB93: CBSE | BC93: Hosur | BD93: Tamil Nadu | BE93: South | BF93: Karnataka/Kerala | BG93: National Sales | BH93: 2024-06-01 00:00:00 | BI93: 2025-03-31 00:00:00 | BJ93: Regular School: Active school with student count and rate per student defined | BK93: 22028000022195988 | BL93: 51788000002733070 | BM93: zcrm_51788000268697133 | BN93: 2024-04-22 00:00:00 | BO93: dipti.jain_ei | BP93: mitul.patel_ei1 | BQ93: dipti.jain@ei.study | BR93: Dipti jain | BS93: Aruna | BU93: 2024-04-23 10:56:08 | BV93: Mr. Levi Paulos | BW93: Other | BX93: levi.paulos@acaindia.org | BY93: +919999021486 | BZ93: achs@acaindia.org | CA93: Sijumon George | CB93: achs@acaindia.org | CC93: +918144244218 | CD93: Kavita Palanivel | CE93: kavitha.p@acaindia.org | CF93: +919715567465 | CG93: 0 | CH93: Jeemangalam Village, Bagalur P.O., Krishnagiri District | CJ93: 635103 | CK93: Jeemangalam Village, Bagalur P.O., Krishnagiri District | CL93: Hosur | CM93: Tamil Nadu | CN93: 635103 | CP93: Jeemangalam Village, Bagalur P.O., Krishnagiri District | CQ93: Jeemangalam Village, Bagalur P.O., Krishnagiri District
A94: 1-year School | B94: 209833 | C94: Nalanda International School | D94: =VLOOKUP(B94,'2025'!B:C,2,0) -> Ishita Jethwa | F94: 2024 | G94: 2024-04-30 00:00:00, 2024-07-29 00:00:00 | H94: Ei ASSET, Ei ASSET,Ei CARES | I94: Regular | J94: IN-2022001973, IN-2022002390 | K94: Approved By Logistic Team | L94: 1446860 | M94: 1446860 | N94: 296854 | O94: 619 | P94: 0, 813 | Q94: 1150006 | R94: 403 | S94: 2854 | T94: 0 | U94: 0 | W94: 0 | X94: Full Payment | Z94: 2024-06-15 00:00:00, 2024-08-15 00:00:00 | AA94: 2000-01-01 00:00:00 | AB94: 0 | AC94: 2000-01-01 00:00:00 | AD94: 0 | AE94: 2000-01-01 00:00:00 | AF94: 0 | AG94: 2000-01-01 00:00:00 | AH94: 0 | AI94: 0 | AJ94: 2024-06-24 00:00:00 | AK94: 2024-08-12 00:00:00 | AL94: 0, 1446860 | AM94: 0, 1393200 | AN94: 0, 53660 | AO94: 0.4578, 1 | AP94: 0.4078, 1 | AS94: 0.05 | AU94: Summer Round | AV94: OMR | AW94: 0, 4 | AX94: MCQ | AY94: Printing By EI | AZ94: OMR | BB94: CISCE | BC94: Vadodara | BD94: Gujarat | BE94: West | BF94: Gujarat | BG94: National Sales | BH94: 2024-04-01 00:00:00, 2024-05-01 00:00:00 | BI94: 2025-03-31 00:00:00, 2025-04-30 00:00:00 | BJ94: Regular School: Active school with student count and rate per student defined | BK94: 22028000022312264, 22028000023812048 | BL94: 51788000002733091 | BM94: zcrm_51788000269048359, zcrm_51788000272109673 | BN94: 2024-04-30 00:00:00, 2024-07-29 00:00:00 | BO94: heena.kumar_ei | BP94: sourabh.mehta_eiindia | BQ94: heena.kumar@ei.study | BR94: Heena kumar | BS94: Nakul Swamy | BU94: 2024-05-02 14:38:50, 2024-07-31 10:26:28 | BV94: Ms. Shoba Menon | BW94: Principal | BX94: shoba.menon@nalandaschool.org | BY94: +919974021668 | BZ94: Info@nalandaschool.org | CA94: Ms. Shoba Menon | CB94: shoba.menon@nalandaschool.org | CC94: +919974021668 | CD94: Ms. Divya Prashant | CE94: divya.prashant50@gmail.com | CF94: +918867042390 | CG94: 100000 | CH94: Sevasi-Mahapura Road, Sevasi | CJ94: 391101 | CK94: Sevasi-Mahapura Road, Sevasi | CL94: Vadodara | CM94: Gujarat | CN94: 391101 | CP94: Sevasi-Mahapura Road, Sevasi | CQ94: Sevasi-Mahapura Road, Sevasi
A95: Retention School | B95: 2104860 | C95: Vedavalli Vidyalaya | D95: =VLOOKUP(B95,'2025'!B:C,2,0) -> Vineeth T V | F95: 2024 | G95: 2024-06-20 00:00:00 | H95: Ei CARES | I95: Regular | J95: IN-2022002254 | K95: Approved By Logistic Team | L95: 453188 | M95: 453188 | N95: 0 | O95: 0 | Q95: 453188 | R95: 259 | S95: 1750 | T95: 0 | U95: 0 | W95: 0 | X95: Installments | Y95: 4 | AA95: 2024-06-25 00:00:00 | AB95: 113297 | AC95: 2024-09-30 00:00:00 | AD95: 113297 | AE95: 2024-12-01 00:00:00 | AF95: 113297 | AG95: 2024-12-31 00:00:00 | AH95: 113297 | AI95: 22419 | AJ95: 2024-07-20 00:00:00 | AK95: 2025-03-11 00:00:00 | AL95: 453188 | AM95: 404120 | AN95: 26649 | AO95: 0.7265999999999999 | AP95: 0.7265999999999999 | AU95: 0 | AW95: 8 | AX95: MCQ | AZ95: Online | BB95: CBSE | BC95: Ranipet | BD95: Tamil Nadu | BE95: South | BF95: Tamil Nadu | BG95: National Sales | BH95: 2024-06-05 00:00:00 | BI95: 2025-05-31 00:00:00 | BJ95: Regular School: Active school with student count and rate per student defined | BK95: 22028000023070336 | BL95: 51788000002767979 | BM95: zcrm_51788000270794001 | BN95: 2024-06-20 00:00:00 | BO95: vineeth.v_ei | BP95: hakim.kanchwala_eiindia1 | BQ95: vineeth.v@ei.study | BR95: Vineeth v | BS95: Vineeth T V | BU95: 2024-06-25 13:27:07 | BV95: Mr. Anantha Raman M K | BX95: anantharaman@vedavallividyalaya.org | BY95: +914172246013 | BZ95: anantharaman@vedavallividyalaya.org | CG95: 0 | CH95: Thirumalai Nagar, Vanapadi Road, Vellore District, ,Ranipet | CJ95: 632404 | CK95: Thirumalai Nagar, Vanapadi Road, Vellore District, ,Ranipet | CL95: Ranipet | CM95: TAMIL NADU | CN95: 632404 | CO95: CHET03629D | CP95: Thirumalai Nagar, Vanapadi Road, Vellore District, ,Ranipet | CQ95: Thirumalai Nagar, Vanapadi Road, Vellore District, ,Ranipet
A96: Retention School | B96: 210666 | C96: Lakshmi School | F96: 2024 | G96: 2024-03-07 00:00:00 | H96: Ei ASSET, Ei ASSET,Ei Mindspark | I96: Regular | J96: IN-2022001595, IN-2022001596 | K96: Approved By Logistic Team | L96: 807134 | M96: 846119 | N96: 590549 | O96: 1150 | P96: 500, 588 | Q96: 0 | R96: 0 | T96: 216585 | U96: 181 | V96: 1197 | W96: 0 | X96: Installments | Y96: 2, 4 | AA96: 2024-05-27 00:00:00, 2024-07-01 00:00:00 | AB96: 146279, 89631 | AC96: 2024-09-01 00:00:00, 2024-10-01 00:00:00 | AD96: 341318, 89631 | AE96: 2000-01-01 00:00:00, 2024-12-01 00:00:00 | AF96: 0, 89631 | AG96: 2000-01-01 00:00:00, 2024-12-31 00:00:00 | AH96: 0, 89631 | AI96: 14096, 14718 | AJ96: 2024-06-18 00:00:00, 2024-07-25 00:00:00 | AK96: 2024-07-25 00:00:00, 2025-01-27 00:00:00 | AL96: 358524, 487597 | AM96: 132461, 625245 | AN96: -280817, 340418 | AO96: 0.6078, 0.6666 | AP96: 0.6078, 0.6666 | AU96: Winter Round | AV96: OMR | AW96: 0 | AX96: MCQ | BA96: Online | BB96: CISCE | BC96: Madurai | BD96: Tamil Nadu | BE96: South | BF96: Tamil Nadu | BG96: National Sales | BH96: 2024-06-01 00:00:00 | BI96: 2025-04-30 00:00:00, 2025-05-31 00:00:00 | BJ96: Regular School: Active school with student count and rate per student defined | BK96: 22028000021397280, 22028000021397344 | BL96: 51788000002733098 | BM96: zcrm_51788000266318001, zcrm_51788000266324204 | BN96: 2024-03-07 00:00:00 | BO96: nisha.murali_eiindia | BP96: hakim.kanchwala_eiindia1 | BQ96: nisha.murali@ei.study | BR96: Nisha murali | BS96: Nisha Murali | BU96: 2024-04-06 07:35:13, 2024-04-06 07:35:17 | BV96: Ms. Subhashini P | BW96: Principal | BX96: lakshmischool@tvslvs.com | BY96: +919787315159 | BZ96: lakshmischool@tvslvs.com | CA96: Ms. Subhashini P | CB96: lakshmischool@tvslvs.com | CC96: +919787315159 | CD96: Rajalakshmi Krishnamani | CE96: rajalakshmi@tvslvs.com | CF96: +919994905311 | CG96: 0 | CH96: Veerapanchan, Karuppayurani | CJ96: 625020 | CK96: TVS School | CL96: Madurai | CM96: Tamil Nadu | CN96: 625020 | CO96: MRIL00055G | CP96: Veerapanchan, Karuppayurani | CQ96: TVS School
A97: New School | B97: 212432 | C97: Delhi Public School, Delhi Public School Society, Delhi Public School, Dwarka | D97: =VLOOKUP(B97,'2025'!B:C,2,0) -> Chaitanya | F97: 2024 | G97: 2024-04-06 00:00:00, 2024-08-21 00:00:00 | H97: Ei ASSET, Ei Teacher Training | I97: Regular | J97: 2124322024.00, IN-2022002453, IN-2022002461 | K97: Approved By Logistic Team | L97: 7935819 | M97: 8007819 | N97: 7535819 | O97: 15547 | P97: 0, 522 | Q97: 0 | R97: 0 | S97: 0 | T97: 0 | U97: 0 | V97: 0 | W97: 0, 400000 | X97: Installments | Y97: 1, 3 | Z97: 2024-04-06 00:00:00 | AA97: 2024-04-06 00:00:00, 2024-08-21 00:00:00, 2024-08-22 00:00:00 | AB97: 0, 1883955 | AC97: 2024-04-06 00:00:00, 2024-10-01 00:00:00, 2024-10-15 00:00:00 | AD97: 0, 3391119 | AE97: 2024-04-06 00:00:00, 2024-12-16 00:00:00, 2024-12-23 00:00:00 | AF97: 0, 2260746 | AG97: 2000-01-01 00:00:00, 2024-04-06 00:00:00 | AH97: 0 | AI97: 0, 1233660 | AJ97: 2024-04-06 00:00:00, 2024-08-22 00:00:00 | AK97: 2024-04-06 00:00:00, 2025-03-28 00:00:00 | AL97: 0, 400000, 7535820 | AM97: 0, 11966940 | AN97: -5664780, 0, 400000 | AO97: 0, 0.6517000000000001, 1 | AP97: 0, 0.6017, 1 | AQ97: 0 | AR97: 0, 0.05 | AS97: 0 | AT97: 0 | AU97: 0, Summer Round | AV97: OMR | AW97: 0 | AX97: MCQ | BB97: CBSE | BC97: New Delhi | BD97: Delhi | BE97: North | BF97: Delhi/Haryana | BG97: National Sales | BH97: 2024-04-01 00:00:00, 2024-04-06 00:00:00 | BI97: 2024-04-06 00:00:00, 2025-03-31 00:00:00 | BJ97: Regular School: Active school with student count and rate per student defined, Regular School: Active school with teacher count and rate per teacher defined | BK97: 2124322024, 22028000024247380, 22028000024266300 | BL97: 51788000002733112 | BM97: zcrm_51788000273015159, zcrm_51788000273186167 | BN97: 2024-04-06 00:00:00, 2024-08-21 00:00:00 | BO97: maruf.shaikh@ei.study, vibhor.tyagi_ei | BP97: fagun.saraiya_eiindia1, maruf.shaikh@ei.study | BQ97: maruf.shaikh@ei.study, vibhor.tyagi@ei.study | BR97: Maruf shaikh, Vibhor tyagi | BS97: Vibhor Tyagi | BT97: Chaitanya Kolluri, Vibhor Tyagi | BU97: 2024-04-06 00:00:00, 2024-08-21 16:00:49, 2024-08-21 17:14:57 | BV97: Ms. Sunita Tanwar, Priya Narayanan | BW97: Principal | BX97: maruf.shaikh@ei.sstudy, maruf.shaikh@ei.study | BY97: +919016039311, +919818643444 | BZ97: mail@dpsdwarka.com | CG97: 0, 95000 | CH97: Phase I, Dwarka Sector-3, Dwarka, New Delhi, Delhi 110078 | CJ97: 110078 | CK97: Phase I, Dwarka Sector-3, Dwarka, New Delhi, Delhi 110078 | CL97: New Delhi | CM97: DELHI | CN97: 110078 | CO97: DELT05304F | CP97: Phase I, Dwarka Sector-3, Dwarka, New Delhi, Delhi 110078 | CQ97: Phase I, Dwarka Sector-3, Dwarka, New Delhi, Delhi 110078
A98: Key Account | B98: 2144857 | C98: Little Star High School | E98: Dropped | F98: 2024 | G98: 2024-10-22 00:00:00 | H98: Ei ASSET | I98: Regular | J98: IN-2022002537 | K98: Approved By Logistic Team | L98: 0 | M98: 0 | N98: 0 | O98: 492 | P98: 0 | Q98: 0 | R98: 0 | T98: 0 | U98: 0 | W98: 0 | X98: Full Payment | Z98: 2024-10-23 00:00:00 | AA98: 2000-01-01 00:00:00 | AB98: 0 | AC98: 2000-01-01 00:00:00 | AD98: 0 | AE98: 2000-01-01 00:00:00 | AF98: 0 | AG98: 2000-01-01 00:00:00 | AH98: 0 | AI98: 0 | AL98: 0 | AM98: 0 | AN98: 0 | AO98: 1 | AP98: 1 | AU98: Winter Round | AV98: OMR | AW98: 0 | AX98: MCQ | BB98: CBSE | BC98: Adilabad | BD98: Telangana | BE98: South | BF98: AP/Telangana | BG98: National Sales | BH98: 2024-09-01 00:00:00 | BI98: 2025-03-31 00:00:00 | BJ98: Regular School: Active school with student count and rate per student defined | BK98: 22028000025644100 | BL98: 51788000002768775 | BM98: zcrm_51788000274553426 | BN98: 2024-10-22 00:00:00 | BO98: maruf.shaikh1 | BP98: maruf.shaikh1 | BQ98: maruf.shaikh@ei.study | BR98: Maruf shaikh | BS98: Manjeetsingh Ladhad | BU98: 2024-10-22 12:55:47 | BV98: Y. Kamalakarreddy | BW98: Principal | BX98: kamalakar.reddy@akesi.org | BY98: +919490024940 | CA98: Y. Kamalakarreddy | CB98: kamalakar.reddy@akesi.org | CC98: +919490024940 | CD98: Ramesh | CE98: kamalakar.reddy@akesi.org | CF98: +918555028565 | CG98: 0 | CH98: 1-2-98, Shanti Nagar, Adilabad, Telangana 504001 | CJ98: 504001 | CK98: 1-2-98, Shanti Nagar, Adilabad, Telangana 504001 | CL98: Adilabad | CM98: Telangana | CN98: 504001 | CP98: 1-2-98, Shanti Nagar, Adilabad, Telangana 504001 | CQ98: 1-2-98, Shanti Nagar, Adilabad, Telangana 504001
A99: Retention School | B99: 2171347 | C99: Learning Paths School | D99: =VLOOKUP(B99,'2025'!B:C,2,0) -> Bhavishya | F99: 2024 | G99: 2024-04-13 00:00:00 | H99: Ei CARES | I99: Regular | J99: IN-2022001905, IN-2022001906 | K99: Approved By Logistic Team | L99: 1728118 | M99: 1728118 | N99: 0 | O99: 0 | Q99: 1728118 | R99: 1008 | S99: 1440, 1920 | T99: 0 | U99: 0 | W99: 0 | X99: Full Payment | Z99: 2024-03-31 00:00:00 | AA99: 2000-01-01 00:00:00 | AB99: 0 | AC99: 2000-01-01 00:00:00 | AD99: 0 | AE99: 2000-01-01 00:00:00 | AF99: 0 | AG99: 2000-01-01 00:00:00 | AH99: 0 | AI99: 0 | AJ99: 2024-04-15 00:00:00 | AK99: 2024-04-15 00:00:00 | AL99: 1105978, 622140 | AM99: 503933, 895842 | AN99: 118207, 210136 | AO99: 0.4461, 0.4514 | AP99: 0.4461, 0.4514 | AU99: 0 | AW99: 4 | AX99: MCQ + Subjective | AY99: Printing By EI | AZ99: OMR | BB99: State Board | BC99: Mohali | BD99: Punjab | BE99: North | BF99: Punjab/Chandigarh | BG99: National Sales | BH99: 2024-04-01 00:00:00 | BI99: 2025-03-31 00:00:00 | BJ99: Regular School: Active school with student count and rate per student defined | BK99: 22028000022060448, 22028000022060488 | BL99: 51788000002769241 | BM99: zcrm_51788000268398181, zcrm_51788000268398361 | BN99: 2024-04-13 00:00:00 | BO99: virender.verma_ei | BP99: fagun.saraiya_eiindia1 | BQ99: virender.verma@ei.study | BR99: Virender verma | BS99: Bhavishya Bansal | BU99: 2024-04-15 14:16:07, 2024-04-15 14:16:12 | BV99: Robin Aggarwal | BW99: School Owner | BX99: raggarwal@gmail.com | BY99: +919216798899 | BZ99: principal@learningpaths.in | CG99: 0 | CH99: Plot No. 3, Sector 67, Behind Niper Institute, | CJ99: 160055 | CK99: Plot No. 3, Sector 67, Behind Niper Institute, | CL99: Mohali | CM99: Punjab | CN99: 160055 | CP99: Plot No. 3, Sector 67, Behind Niper Institute, | CQ99: Plot No. 3, Sector 67, Behind Niper Institute,
A100: 1-year School | B100: 2183623 | C100: Indus Valley World School | E100: Dropped | F100: 2024 | G100: 2024-06-20 00:00:00 | H100: Ei ASSET | I100: Regular | J100: IN-2022002251 | K100: Approved By Logistic Team | L100: 195000 | M100: 195000 | N100: 195000 | O100: 260 | P100: 750 | Q100: 0 | R100: 0 | T100: 0 | U100: 0 | W100: 0 | X100: Installments | Y100: 2 | AA100: 2024-06-24 00:00:00 | AB100: 48750 | AC100: 2024-10-01 00:00:00 | AD100: 146250 | AE100: 2000-01-01 00:00:00 | AF100: 0 | AG100: 2000-01-01 00:00:00 | AH100: 0 | AI100: 0 | AJ100: 2024-06-22 00:00:00 | AK100: 2024-11-08 00:00:00 | AL100: 195000 | AM100: 191100 | AN100: 3900 | AO100: 0.5 | AP100: 0.5 | AU100: Winter Round | AV100: OMR | AW100: 0 | AX100: MCQ | BB100: CBSE | BC100: kolkata | BD100: West Bengal | BE100: East | BF100: West Bengal | BG100: National Sales | BH100: 2024-07-01 00:00:00 | BI100: 2025-01-31 00:00:00 | BJ100: Regular School: Active school with student count and rate per student defined | BK100: 22028000023069264 | BL100: 51788000002769463 | BM100: zcrm_51788000270863071 | BN100: 2024-06-20 00:00:00 | BO100: mayukh.chowdhury_ei1 | BP100: mitul.patel_ei1 | BQ100: mayukh.chowdhury@ei.study | BR100: Mayukh chowdhury | BS100: Soumodeep Ghosh | BT100: Gargi Ghosh | BU100: 2024-06-20 14:02:23 | BV100: Ms. Amita Prasad | BW100: Other | BX100: admin@ivws.org | BY100: +919073657861 | BZ100: principal@ivws.org | CG100: 0 | CH100: 488, Ajoy Nagar, Eastern Metropolitan Bypass, near Peerless Hospital, | CJ100: 700094 | CK100: 488, Ajoy Nagar, Eastern Metropolitan Bypass, near Peerless Hospital, | CL100: kolkata | CM100: West Bengal | CN100: 700094 | CP100: 488, Ajoy Nagar, Eastern Metropolitan Bypass, near Peerless Hospital, | CQ100: 488, Ajoy Nagar, Eastern Metropolitan Bypass, near Peerless Hospital,
...

Sheet 2025
A1: School Type | B1: School No | C1: ACAD Name | D1: School Name | E1: Offering 2026 | F1: Total Rev-2026 | G1: ASSET Rev-2026 | H1: CARES Rev 2026 | I1: MS Rev 2026 | K1: Offering 2025 | L1: Total Order Value (Exclusive GST) | M1: Total Order Value (Inclusive GST) | N1: ASSET Revenue | O1: ASSETStudents | P1: ASSET rate | Q1: CARES Revenue | R1: CARESStudents | S1: CARES rate | T1: Mindspark Revenue | U1: MindsparkStudents | V1: Mindspark rate | W1: Teacher Training Revenue | X1: Payment Mode | Y1: No Of Installments | Z1: Full Payment Date | AA1: First Installment Date | AB1: First Installment Amount | AC1: Second Installment Date | AD1: Second Installment Amount | AE1: Third Installment Date | AF1: Third Installment Amount | AG1: Fourth Installment Date | AH1: Fourth Installment Amount | AI1: TDS Amount | AJ1: First payment Date | AK1: Latest payment Date | AL1: To be invoiced till date | AM1: Amount Received | AN1: Due till date as per payment schedule | AO1: Total Discount % | AP1: Standard Discount % | AQ1: Pre Payment Discount % | AR1: Volume Discount % | AS1: Bundle Discount % | AT1: Loyalty Discount % | AU1: ASSETRound | AV1: Ei ASSET Mode | AW1: CAREStestpack | AX1: Ei CARES Version | AY1: Ei CARES Mode Of Printing | AZ1: Ei CARES Mode | BA1: Ei Mindspark Mode | BB1: Board | BC1: City | BD1: State | BE1: Division | BF1: Zone | BG1: Vertical | BH1: Program Start Date | BI1: Program End Date | BJ1: Order Type | BK1: ID | BL1: Zoho CRM Account ID | BM1: Deal ID | BN1: Created Date | BO1: Added User | BP1: Modified User | BQ1: SSF Creator Email | BR1: SSF Creator | BS1: CRM Account Owner | BT1: CRM Acad Consultant | BU1: Logistic Approved Date | BV1: SSF Signing Perosn Name | BW1: SSF Signing Perosn Designation | BX1: SSF Signing Perosn Mail ID | BY1: SSF Signing Perosn Phone No | BZ1: School CRM Email | CA1: Principal Name | CB1: Principal Email | CC1: Principal Phone No | CD1: Coordinator Name | CE1: Coordinator Email | CF1: Coordinator Phone No | CG1: School Fees | CH1: Billing Address Line 1 | CI1: Billing Address Line 2 | CJ1: Billing Postal Code | CK1: Shipping Address Line 1 | CL1: Shipping City | CM1: Shipping State | CN1: Shipping Postal Code | CO1: TAN NO | CP1: CRM Billing Street | CQ1: CRM Shipping Street | CR1: STAGES
A2: New School | B2: 3515636 | C2: Rohit | D2: Rungta Public School | E2: =VLOOKUP(B2,aa!B:F,5,0) -> #N/A | F2: =VLOOKUP(B2,aa!B:J,9,0) -> #N/A | G2: =VLOOKUP(B2,aa!B:L,11,0) -> #N/A | H2: =VLOOKUP(B2,aa!B:O,14,0) -> #N/A | I2: =VLOOKUP(B2,aa!B:R,17,0) -> #N/A | K2: Ei CARES | L2: 582192 | M2: 582192 | N2: 0 | O2: 0 | Q2: 582192 | R2: 311 | S2: 1872 | T2: 0 | U2: 0 | W2: 0 | X2: Installments | Y2: 3 | AA2: 2025-04-14 00:00:00 | AB2: 197945 | AC2: 2025-07-21 00:00:00 | AD2: 192123 | AE2: 2025-10-20 00:00:00 | AF2: 192123 | AG2: 2000-01-01 00:00:00 | AH2: 0 | AI2: 0 | AL2: 582191 | AM2: 0 | AN2: 582191 | AO2: 0.28 | AP2: 0.28 | AU2: 0 | AW2: 4 | AX2: MCQ | AY2: Printing By EI | AZ2: OMR | BB2: CBSE | BC2: Bhilai | BD2: Chhattisgarh | BE2: North | BF2: MP/Chattisgarh | BG2: National Sales | BH2: 2025-04-01 00:00:00 | BI2: 2026-03-31 00:00:00 | BJ2: Regular School: Active school with student count and rate per student defined | BK2: 22028000024261096 | BL2: 51788000002795115 | BM2: zcrm_51788000272833808 | BN2: 2024-08-21 00:00:00 | BO2: sanjay.rai_eiindia1 | BP2: fagun.saraiya_eiindia1 | BQ2: sanjay.rai@ei.study | BR2: Sanjay rai | BS2: Sanjay Rai | BT2: Rohit Kumar | BU2: 2024-08-21 17:54:15 | BV2: Mr. Jawahar Surisetti | BW2: Other | BX2: jawahar@rungtainternational.org | BY2: +919229155515 | BZ2: principal@rungtapublicschool.ac.in | CG2: 53500 | CH2: Kohka Road, Kurud, Bhilai | CJ2: 490023 | CK2: Kohka Road, Kurud, Bhilai | CL2: Bhilai | CM2: Chhattisgarh | CN2: 490023 | CP2: Kohka Road, Kurud, Bhilai | CQ2: Kohka Road, Kurud, Bhilai
A3: New School | B3: 5018241 | C3: Pooja | D3: St Christopher Mission School | E3: =VLOOKUP(B3,aa!B:F,5,0) -> Ei Mindspark | F3: =VLOOKUP(B3,aa!B:J,9,0) -> 534389 | G3: =VLOOKUP(B3,aa!B:L,11,0) -> 0 | H3: =VLOOKUP(B3,aa!B:O,14,0) -> 0 | I3: =VLOOKUP(B3,aa!B:R,17,0) -> 534389 | K3: Ei ASSET | L3: 399750 | M3: 399750 | N3: 399750 | O3: 533 | P3: 750 | Q3: 0 | R3: 0 | T3: 0 | U3: 0 | W3: 0 | X3: Installments | Y3: 3 | AA3: 2024-09-20 00:00:00 | AB3: 39975 | AC3: 2025-04-20 00:00:00 | AD3: 179888 | AE3: 2025-05-20 00:00:00 | AF3: 179888 | AG3: 2000-01-01 00:00:00 | AH3: 0 | AI3: 0 | AJ3: 2024-12-12 00:00:00 | AK3: 2024-12-12 00:00:00 | AL3: 399751 | AM3: 30000 | AN3: 369751 | AO3: 0.5 | AP3: 0.5 | AU3: Winter Round | AV3: OMR | AW3: 0 | AX3: MCQ | BB3: CBSE | BC3: Asansol | BD3: West Bengal | BE3: East | BF3: West Bengal | BG3: National Sales | BH3: 2025-07-25 00:00:00 | BI3: 2025-12-31 00:00:00 | BJ3: Regular School: Active school with student count and rate per student defined | BK3: 22028000024402612 | BL3: 51788000273209037 | BM3: zcrm_51788000273205402 | BN3: 2024-08-29 00:00:00 | BO3: rudra.mishra_ei | BP3: sourabh.mehta_eiindia | BQ3: rudra.mishra@ei.study | BR3: Rudra mishra | BS3: Rudra Mishra | BU3: 2024-09-03 10:34:30 | BV3: Mr. Christopher Gomes | BW3: School Owner | BX3: ck_gomes@yahoo.co.in | BZ3: ck_gomes@yahoo.co.in | CA3: Ashok Kumar Rana | CB3: scms28896@gmail.com | CC3: +918436007209 | CD3: Sailendra Prasad | CE3: scms28896@gmail.com | CF3: +918906960550 | CG3: 18000 | CH3: Radhanagar Hatia,Sunderchak | CJ3: 713360 | CK3: Radhanagar Hatia,Sunderchak | CL3: Asansol | CM3: West Bengal | CN3: 713360 | CP3: Radhanagar Hatia,Sunderchak | CQ3: Radhanagar Hatia,Sunderchak
A4: New School | B4: 1035545 | C4: Sudhi | D4: Doon Valley Public School | E4: =VLOOKUP(B4,aa!B:F,5,0) -> #N/A | F4: =VLOOKUP(B4,aa!B:J,9,0) -> #N/A | G4: =VLOOKUP(B4,aa!B:L,11,0) -> #N/A | H4: =VLOOKUP(B4,aa!B:O,14,0) -> #N/A | I4: =VLOOKUP(B4,aa!B:R,17,0) -> #N/A | K4: Ei CARES | L4: 1938522 | M4: 1938522 | N4: 0 | O4: 0 | Q4: 1938522 | R4: 1436 | S4: 1350 | T4: 0 | U4: 0 | W4: 0 | X4: Full Payment | Z4: 2025-03-31 00:00:00 | AA4: 2000-01-01 00:00:00 | AB4: 0 | AC4: 2000-01-01 00:00:00 | AD4: 0 | AE4: 2000-01-01 00:00:00 | AF4: 0 | AG4: 2000-01-01 00:00:00 | AH4: 0 | AI4: 0 | AJ4: 2025-04-05 00:00:00 | AK4: 2025-04-05 00:00:00 | AL4: 1938522 | AM4: 1330734 | AN4: 607788 | AO4: 0.5231 | AP4: 0.42310000000000003 | AQ4: 0.1 | AU4: 0 | AW4: 4 | AX4: MCQ + Subjective | AY4: Printing By EI | AZ4: OMR | BB4: CBSE | BC4: Nalagarh | BD4: Himachal Pradesh | BE4: North | BF4: Punjab/Chandigarh | BG4: National Sales | BH4: 2025-04-01 00:00:00 | BI4: 2026-03-31 00:00:00 | BJ4: Regular School: Active school with student count and rate per student defined | BK4: 22028000024444176 | BL4: 51788000002747410 | BM4: zcrm_51788000273345737 | BN4: 2024-08-30 00:00:00 | BO4: sajan.thareja | BP4: fagun.saraiya_eiindia1 | BQ4: sajan.thareja@ei.study | BR4: Sajan thareja | BS4: Bhavishya Bansal | BU4: 2024-09-02 14:34:52 | BV4: Mr. Rajeev Sharma | BW4: School Owner | BX4: rajeevdvps@yahoo.co.in | BY4: +919805316667 | BZ4: rajeevdvps@gmail.com | CG4: 36000 | CH4: Pinjore - Swarghat Rd, Nalagarh, Himachal Pradesh 174101 | CJ4: 174101 | CK4: Pinjore - Swarghat Rd, Nalagarh, Himachal Pradesh 174101 | CL4: Nalagarh | CM4: Himachal Pradesh | CN4: 174101 | CP4: Pinjore - Swarghat Rd, Nalagarh, Himachal Pradesh 174101 | CQ4: Pinjore - Swarghat Rd, Nalagarh, Himachal Pradesh 174101
